Workbook

Sheet 1-COSTO X KM
A1: ANEXO 1 - DETERMINACIÓN DEL COSTO POR KM
L2: PORCENTAJE DE INCIDENCIA DE CADA RUBRO EN EL COSTO/KM | V2: VARIACION PORCENTUAL POR RUBRO COSTO/KM. OCTUBRE 2025/ OCTUBRE2024 | AF2: VARIACION PORCENTUAL POR RUBRO COSTO/KM. OCTUBRE 2025/ JUNIO 2025
A3: RUBROS | B3: DF $/km | C3: SGI $/km | D3: SGI KM $/km | E3: SGII $/km | F3: INP $/km | G3: UPA $/km | H3: UPA KM $/km | I3: UMA 1 $/km | J3: UMA 2 $/km | L3: =+A3 -> RUBROS | M3: DF $/km | N3: SGI $/km | O3: SGI KM $/km | P3: SGII $/km | Q3: INP $/km | R3: UPA $/km | S3: UPA KM $/km | T3: UMA 1 $/km | U3: UMA 2 $/km | V3: =+A3 -> RUBROS | W3: DF $/km | X3: SGI $/km | Y3: SGI KM $/km | Z3: SGII $/km | AA3: INP $/km | AB3: UPA $/km | AC3: UPA KM $/km | AD3: UMA 1 $/km | AE3: UMA 2 $/km | AF3: =+L3 -> RUBROS | AG3: DF $/km | AH3: SGI $/km | AI3: SGI KM $/km | AJ3: SGII $/km | AK3: INP $/km | AL3: UPA $/km | AM3: UPA KM $/km | AN3: UMA 1 $/km | AO3: UMA 2 $/km
A4: 1. COMBUSTIBLE | B4: =+'3- REND Y CONS'!B4*'5-PRECIOS SIN IVA'!B5 -> 769.86709 | C4: =+'3- REND Y CONS'!C4*'5-PRECIOS SIN IVA'!C5 -> 626.32826 | D4: =+'3- REND Y CONS'!D4*'5-PRECIOS SIN IVA'!D5 -> 588.76106 | E4: =+'3- REND Y CONS'!E4*'5-PRECIOS SIN IVA'!E5 -> 462.23252 | F4: =+'3- REND Y CONS'!F4*'5-PRECIOS SIN IVA'!F5 -> 407.45207 | G4: =+'3- REND Y CONS'!G4*'5-PRECIOS SIN IVA'!G5 -> 516.22122 | H4: =+'3- REND Y CONS'!H4*'5-PRECIOS SIN IVA'!H5 -> 527.32088 | I4: =+'3- REND Y CONS'!I4*'5-PRECIOS SIN IVA'!I5 -> 501.95111 | J4: =+'3- REND Y CONS'!J4*'5-PRECIOS SIN IVA'!J5 -> 501.95112 | L4: =+A4 -> 1. COMBUSTIBLE | M4: =+B4/B$51 -> 0.198636 | N4: =+C4/C$51 -> 0.18093229 | O4: =+D4/D$51 -> 0.21115931 | P4: =+E4/E$51 -> 0.19651053 | Q4: =+F4/F$51 -> 0.17140724 | R4: =+G4/G$51 -> 0.16772597 | S4: =+H4/H$51 -> 0.21305062 | T4: =+I4/I$51 -> 0.16147247 | U4: =+J4/J$51 -> 0.17040527 | V4: =+A4 -> 1. COMBUSTIBLE | W4: =+B4/'[1]1-COSTO X KM'!B4-1 -> 0.63747829 | X4: =+C4/'[1]1-COSTO X KM'!C4-1 -> 0.34701109 | Y4: =+D4/'[1]1-COSTO X KM'!D4-1 -> 0.34701109 | Z4: =+E4/'[1]1-COSTO X KM'!E4-1 -> 0.34701109 | AA4: =+F4/'[1]1-COSTO X KM'!F4-1 -> 0.34701109 | AB4: =+G4/'[1]1-COSTO X KM'!G4-1 -> 0.34701109 | AC4: =+H4/'[1]1-COSTO X KM'!H4-1 -> 0.34701109 | AD4: =+I4/'[1]1-COSTO X KM'!I4-1 -> 0.34701109 | AE4: =+J4/'[1]1-COSTO X KM'!J4-1 -> 0.34701106 | AF4: =+L4 -> 1. COMBUSTIBLE | AG4: =+B4/'[2]1-COSTO X KM'!B4-1 -> 0.47278978 | AH4: =+C4/'[2]1-COSTO X KM'!C4-1 -> 0.21153617 | AI4: =+D4/'[2]1-COSTO X KM'!D4-1 -> 0.21153617 | AJ4: =+E4/'[2]1-COSTO X KM'!E4-1 -> 0.21153617 | AK4: =+F4/'[2]1-COSTO X KM'!F4-1 -> 0.21153617 | AL4: =+G4/'[2]1-COSTO X KM'!G4-1 -> 0.21153617 | AM4: =+H4/'[2]1-COSTO X KM'!H4-1 -> 0.21153617 | AN4: =+I4/'[2]1-COSTO X KM'!I4-1 -> 0.21153617 | AO4: =+J4/'[2]1-COSTO X KM'!J4-1 -> 0.21153614
A5: 2. LUBRICANTES | B5: =+('3- REND Y CONS'!B5*'5-PRECIOS SIN IVA'!B6+('3- REND Y CONS'!B6+'3- REND Y CONS'!B7)*'5-PRECIOS SIN IVA'!B7)*(1+'2- EMP. REP'!B9) -> 21.787509 | C5: =+('3- REND Y CONS'!C5*'5-PRECIOS SIN IVA'!C6+('3- REND Y CONS'!C6+'3- REND Y CONS'!C7)*'5-PRECIOS SIN IVA'!C7)*(1+'2- EMP. REP'!C9) -> 21.787509 | D5: =+('3- REND Y CONS'!D5*'5-PRECIOS SIN IVA'!D6+('3- REND Y CONS'!D6+'3- REND Y CONS'!D7)*'5-PRECIOS SIN IVA'!D7)*(1+'2- EMP. REP'!D9) -> 21.787509 | E5: =+('3- REND Y CONS'!E5*'5-PRECIOS SIN IVA'!E6+('3- REND Y CONS'!E6+'3- REND Y CONS'!E7)*'5-PRECIOS SIN IVA'!E7)*(1+'2- EMP. REP'!E9) -> 21.787509 | F5: =+('3- REND Y CONS'!F5*'5-PRECIOS SIN IVA'!F6+('3- REND Y CONS'!F6+'3- REND Y CONS'!F7)*'5-PRECIOS SIN IVA'!F7)*(1+'2- EMP. REP'!F9) -> 21.787509 | G5: =+('3- REND Y CONS'!G5*'5-PRECIOS SIN IVA'!G6+('3- REND Y CONS'!G6+'3- REND Y CONS'!G7)*'5-PRECIOS SIN IVA'!G7)*(1+'2- EMP. REP'!G9) -> 21.787509 | H5: =+('3- REND Y CONS'!H5*'5-PRECIOS SIN IVA'!H6+('3- REND Y CONS'!H6+'3- REND Y CONS'!H7)*'5-PRECIOS SIN IVA'!H7)*(1+'2- EMP. REP'!H9) -> 21.787509 | I5: =+('3- REND Y CONS'!I5*'5-PRECIOS SIN IVA'!I6+('3- REND Y CONS'!I6+'3- REND Y CONS'!I7)*'5-PRECIOS SIN IVA'!I7)*(1+'2- EMP. REP'!I9) -> 21.787509 | J5: =+('3- REND Y CONS'!J5*'5-PRECIOS SIN IVA'!J6+('3- REND Y CONS'!J6+'3- REND Y CONS'!J7)*'5-PRECIOS SIN IVA'!J7)*(1+'2- EMP. REP'!J9) -> 21.787509 | L5: =+A5 -> 2. LUBRICANTES | M5: =+B5/B$51 -> 0.0056214686 | N5: =+C5/C$51 -> 0.0062939264 | O5: =+D5/D$51 -> 0.0078140961 | P5: =+E5/E$51 -> 0.0092626002 | Q5: =+F5/F$51 -> 0.0091655859 | R5: =+G5/G$51 -> 0.0070790024 | S5: =+H5/H$51 -> 0.0088026901 | T5: =+I5/I$51 -> 0.0070088162 | U5: =+J5/J$51 -> 0.0073965499 | V5: =+A5 -> 2. LUBRICANTES | W5: =+B5/'[1]1-COSTO X KM'!B5-1 -> 0.2474288 | X5: =+C5/'[1]1-COSTO X KM'!C5-1 -> 0.2474288 | Y5: =+D5/'[1]1-COSTO X KM'!D5-1 -> 0.2474288 | Z5: =+E5/'[1]1-COSTO X KM'!E5-1 -> 0.2474288 | AA5: =+F5/'[1]1-COSTO X KM'!F5-1 -> 0.2474288 | AB5: =+G5/'[1]1-COSTO X KM'!G5-1 -> 0.2474288 | AC5: =+H5/'[1]1-COSTO X KM'!H5-1 -> 0.2474288 | AD5: =+I5/'[1]1-COSTO X KM'!I5-1 -> 0.2474288 | AE5: =+J5/'[1]1-COSTO X KM'!J5-1 -> 0.2474288 | AF5: =+L5 -> 2. LUBRICANTES | AG5: =+B5/'[2]1-COSTO X KM'!B5-1 -> 0.20023066 | AH5: =+C5/'[2]1-COSTO X KM'!C5-1 -> 0.20023066 | AI5: =+D5/'[2]1-COSTO X KM'!D5-1 -> 0.20023066 | AJ5: =+E5/'[2]1-COSTO X KM'!E5-1 -> 0.20023066 | AK5: =+F5/'[2]1-COSTO X KM'!F5-1 -> 0.20023066 | AL5: =+G5/'[2]1-COSTO X KM'!G5-1 -> 0.20023066 | AM5: =+H5/'[2]1-COSTO X KM'!H5-1 -> 0.20023066 | AN5: =+I5/'[2]1-COSTO X KM'!I5-1 -> 0.20023066 | AO5: =+J5/'[2]1-COSTO X KM'!J5-1 -> 0.20023066
A6: 3. NEUMATICOS | B6: =((+'3- REND Y CONS'!B8*'5-PRECIOS SIN IVA'!B8)+('3- REND Y CONS'!B14*'5-PRECIOS SIN IVA'!B9*'3- REND Y CONS'!B8))*(1+'2- EMP. REP'!B9)/('3- REND Y CONS'!B13) -> 79.139001 | C6: =((+'3- REND Y CONS'!C8*'5-PRECIOS SIN IVA'!C8)+('3- REND Y CONS'!C14*'5-PRECIOS SIN IVA'!C9*'3- REND Y CONS'!C8))*(1+'2- EMP. REP'!C9)/('3- REND Y CONS'!C13) -> 79.139001 | D6: =+C6 -> 79.139001 | E6: =+D6 -> 79.139001 | F6: =+E6 -> 79.139001 | G6: =+F6 -> 79.139001 | H6: =+G6 -> 79.139001 | I6: =+H6 -> 79.139001 | J6: =+I6 -> 79.139001 | L6: =+A6 -> 3. NEUMATICOS | M6: =+B6/B$51 -> 0.02041892 | N6: =+C6/C$51 -> 0.022861496 | O6: =+D6/D$51 -> 0.028383224 | P6: =+E6/E$51 -> 0.033644641 | Q6: =+F6/F$51 -> 0.033292255 | R6: =+G6/G$51 -> 0.025713136 | S6: =+H6/H$51 -> 0.031974105 | T6: =+I6/I$51 -> 0.025458197 | U6: =+J6/J$51 -> 0.026866567 | V6: =+A6 -> 3. NEUMATICOS | W6: =+B6/'[1]1-COSTO X KM'!B6-1 -> 0.24742929 | X6: =+C6/'[1]1-COSTO X KM'!C6-1 -> 0.24742929 | Y6: =+D6/'[1]1-COSTO X KM'!D6-1 -> 0.24742929 | Z6: =+E6/'[1]1-COSTO X KM'!E6-1 -> 0.24742929 | AA6: =+F6/'[1]1-COSTO X KM'!F6-1 -> 0.24742929 | AB6: =+G6/'[1]1-COSTO X KM'!G6-1 -> 0.24742929 | AC6: =+H6/'[1]1-COSTO X KM'!H6-1 -> 0.24742929 | AD6: =+I6/'[1]1-COSTO X KM'!I6-1 -> 0.24742929 | AE6: =+J6/'[1]1-COSTO X KM'!J6-1 -> 0.24742929 | AF6: =+L6 -> 3. NEUMATICOS | AG6: =+B6/'[2]1-COSTO X KM'!B6-1 -> 0.20023086 | AH6: =+C6/'[2]1-COSTO X KM'!C6-1 -> 0.20023086 | AI6: =+D6/'[2]1-COSTO X KM'!D6-1 -> 0.20023086 | AJ6: =+E6/'[2]1-COSTO X KM'!E6-1 -> 0.20023086 | AK6: =+F6/'[2]1-COSTO X KM'!F6-1 -> 0.20023086 | AL6: =+G6/'[2]1-COSTO X KM'!G6-1 -> 0.20023086 | AM6: =+H6/'[2]1-COSTO X KM'!H6-1 -> 0.20023086 | AN6: =+I6/'[2]1-COSTO X KM'!I6-1 -> 0.20023086 | AO6: =+J6/'[2]1-COSTO X KM'!J6-1 -> 0.20023086
A7: 4. ENGRASE Y LAVADO | B7: =+('3- REND Y CONS'!B16*'5-PRECIOS SIN IVA'!B10+'3- REND Y CONS'!B17*'5-PRECIOS SIN IVA'!B11+'3- REND Y CONS'!B18*'5-PRECIOS SIN IVA'!B12+'3- REND Y CONS'!B19*'5-PRECIOS SIN IVA'!B13+'3- REND Y CONS'!B20*'5-PRECIOS SIN IVA'!B14+'3- REND Y CONS'!B21*'5-PRECIOS SIN IVA'!B15+'3- REND Y CONS'!B22*'5-PRECIOS SIN IVA'!B16)/'3- REND Y CONS'!B23 -> 54.825193 | C7: =+('3- REND Y CONS'!C16*'5-PRECIOS SIN IVA'!C10+'3- REND Y CONS'!C17*'5-PRECIOS SIN IVA'!C11+'3- REND Y CONS'!C18*'5-PRECIOS SIN IVA'!C12+'3- REND Y CONS'!C19*'5-PRECIOS SIN IVA'!C13+'3- REND Y CONS'!C20*'5-PRECIOS SIN IVA'!C14+'3- REND Y CONS'!C21*'5-PRECIOS SIN IVA'!C15+'3- REND Y CONS'!C22*'5-PRECIOS SIN IVA'!C16)/'3- REND Y CONS'!C23 -> 54.825193 | D7: =+C7 -> 54.825193 | E7: =+D7 -> 54.825193 | F7: =+E7 -> 54.825193 | G7: =+F7 -> 54.825193 | H7: =+G7 -> 54.825193 | I7: =+H7 -> 54.825193 | J7: =+I7 -> 54.825193 | L7: =+A7 -> 4. ENGRASE Y LAVADO | M7: =+B7/B$51 -> 0.014145633 | N7: =+C7/C$51 -> 0.015837778 | O7: =+D7/D$51 -> 0.01966307 | P7: =+E7/E$51 -> 0.023308027 | Q7: =+F7/F$51 -> 0.023063904 | R7: =+G7/G$51 -> 0.017813311 | S7: =+H7/H$51 -> 0.022150728 | T7: =+I7/I$51 -> 0.017636697 | U7: =+J7/J$51 -> 0.018612374 | V7: =+A7 -> 4. ENGRASE Y LAVADO | W7: =+B7/'[1]1-COSTO X KM'!B7-1 -> 0.2474293 | X7: =+C7/'[1]1-COSTO X KM'!C7-1 -> 0.2474293 | Y7: =+D7/'[1]1-COSTO X KM'!D7-1 -> 0.2474293 | Z7: =+E7/'[1]1-COSTO X KM'!E7-1 -> 0.2474293 | AA7: =+F7/'[1]1-COSTO X KM'!F7-1 -> 0.2474293 | AB7: =+G7/'[1]1-COSTO X KM'!G7-1 -> 0.2474293 | AC7: =+H7/'[1]1-COSTO X KM'!H7-1 -> 0.2474293 | AD7: =+I7/'[1]1-COSTO X KM'!I7-1 -> 0.2474293 | AE7: =+J7/'[1]1-COSTO X KM'!J7-1 -> 0.2474293 | AF7: =+L7 -> 4. ENGRASE Y LAVADO | AG7: =+B7/'[2]1-COSTO X KM'!B7-1 -> 0.2002308 | AH7: =+C7/'[2]1-COSTO X KM'!C7-1 -> 0.2002308 | AI7: =+D7/'[2]1-COSTO X KM'!D7-1 -> 0.2002308 | AJ7: =+E7/'[2]1-COSTO X KM'!E7-1 -> 0.2002308 | AK7: =+F7/'[2]1-COSTO X KM'!F7-1 -> 0.2002308 | AL7: =+G7/'[2]1-COSTO X KM'!G7-1 -> 0.2002308 | AM7: =+H7/'[2]1-COSTO X KM'!H7-1 -> 0.2002308 | AN7: =+I7/'[2]1-COSTO X KM'!I7-1 -> 0.2002308 | AO7: =+J7/'[2]1-COSTO X KM'!J7-1 -> 0.2002308
A8: 5. REPARACION Y MANTENIMIENTO DEL MATERIAL RODANTE | B8: =+B9+B10 -> 256.95858 | C8: =+C9+C10 -> 236.57637 | D8: =+D9+D10 -> 179.31954 | E8: =+E9+E10 -> 331.63573 | F8: =+F9+F10 -> 157.16111 | G8: =+G9+G10 -> 211.81001 | H8: =+H9+H10 -> 155.52701 | I8: =+I9+I10 -> 197.02863 | J8: =+J9+J10 -> 183.0581 | L8: =+A8 -> 5. REPARACION Y MANTENIMIENTO DEL MATERIAL RODANTE | M8: =+B8/B$51 -> 0.066298747 | N8: =+C8/C$51 -> 0.068341645 | O8: =+D8/D$51 -> 0.064313003 | P8: =+E8/E$51 -> 0.14098946 | Q8: =+F8/F$51 -> 0.066114655 | R8: =+G8/G$51 -> 0.068819412 | S8: =+H8/H$51 -> 0.062836743 | T8: =+I8/I$51 -> 0.063382069 | U8: =+J8/J$51 -> 0.062145623 | V8: =+A8 -> 5. REPARACION Y MANTENIMIENTO DEL MATERIAL RODANTE | W8: =+B8/'[1]1-COSTO X KM'!B8-1 -> 0.50542842 | X8: =+C8/'[1]1-COSTO X KM'!C8-1 -> 0.77630776 | Y8: =+D8/'[1]1-COSTO X KM'!D8-1 -> 0.79036721 | Z8: =+E8/'[1]1-COSTO X KM'!E8-1 -> 0.66283191 | AA8: =+F8/'[1]1-COSTO X KM'!F8-1 -> 0.9259468 | AB8: =+G8/'[1]1-COSTO X KM'!G8-1 -> 0.5626251 | AC8: =+H8/'[1]1-COSTO X KM'!H8-1 -> 0.72614549 | AD8: =+I8/'[1]1-COSTO X KM'!I8-1 -> 0.59033901 | AE8: =+J8/'[1]1-COSTO X KM'!J8-1 -> 0.63489944 | AF8: =+L8 -> 5. REPARACION Y MANTENIMIENTO DEL MATERIAL RODANTE | AG8: =+B8/'[2]1-COSTO X KM'!B8-1 -> 0.33283839 | AH8: =+C8/'[2]1-COSTO X KM'!C8-1 -> 0.38543489 | AI8: =+D8/'[2]1-COSTO X KM'!D8-1 -> 0.400205 | AJ8: =+E8/'[2]1-COSTO X KM'!E8-1 -> 0.31315699 | AK8: =+F8/'[2]1-COSTO X KM'!F8-1 -> 0.53123515 | AL8: =+G8/'[2]1-COSTO X KM'!G8-1 -> 0.3955749 | AM8: =+H8/'[2]1-COSTO X KM'!H8-1 -> 0.48715587 | AN8: =+I8/'[2]1-COSTO X KM'!I8-1 -> 0.41863609 | AO8: =+J8/'[2]1-COSTO X KM'!J8-1 -> 0.46531434
A9: . Reparación y mant. chasis (incluye boletera y rampa) | B9: =+'3- REND Y CONS'!B24*('5-PRECIOS SIN IVA'!B17-6*'5-PRECIOS SIN IVA'!B8)*'2- EMP. REP'!B11/'2- EMP. REP'!B10 -> 176.60975 | C9: =+'3- REND Y CONS'!C24*('5-PRECIOS SIN IVA'!C17-6*'5-PRECIOS SIN IVA'!C8)*'2- EMP. REP'!C11/'2- EMP. REP'!C10 -> 162.60089 | D9: =+'3- REND Y CONS'!D24*('5-PRECIOS SIN IVA'!D17-6*'5-PRECIOS SIN IVA'!D8)*'2- EMP. REP'!D11/'2- EMP. REP'!D10 -> 123.2478 | E9: =+'3- REND Y CONS'!E24*('5-PRECIOS SIN IVA'!E17-6*'5-PRECIOS SIN IVA'!E8)*'2- EMP. REP'!E11/'2- EMP. REP'!E10 -> 211.8743 | F9: =+'3- REND Y CONS'!F24*('5-PRECIOS SIN IVA'!F17-6*'5-PRECIOS SIN IVA'!F8)*'2- EMP. REP'!F11/'2- EMP. REP'!F10 -> 108.01813 | G9: =+'3- REND Y CONS'!G24*('5-PRECIOS SIN IVA'!G17-6*'5-PRECIOS SIN IVA'!G8)*'2- EMP. REP'!G11/'2- EMP. REP'!G10 -> 145.57877 | H9: =+'3- REND Y CONS'!H24*('5-PRECIOS SIN IVA'!H17-6*'5-PRECIOS SIN IVA'!H8)*'2- EMP. REP'!H11/'2- EMP. REP'!H10 -> 106.895 | I9: =+'3- REND Y CONS'!I24*('5-PRECIOS SIN IVA'!I17-6*'5-PRECIOS SIN IVA'!I8)*'2- EMP. REP'!I11/'2- EMP. REP'!I10 -> 135.13232 | J9: =+'3- REND Y CONS'!J24*('5-PRECIOS SIN IVA'!J17-6*'5-PRECIOS SIN IVA'!J8)*'2- EMP. REP'!J11/'2- EMP. REP'!J10 -> 125.55062 | L9: =+A9 -> . Reparación y mant. chasis (incluye boletera y rampa) | V9: =+A9 -> . Reparación y mant. chasis (incluye boletera y rampa) | AF9: =+L9 -> . Reparación y mant. chasis (incluye boletera y rampa)
A10: . Reparación y Mant. carrocería | B10: =+'3- REND Y CONS'!B25*'5-PRECIOS SIN IVA'!B18*'2- EMP. REP'!B11/'2- EMP. REP'!B10 -> 80.348824 | C10: =+'3- REND Y CONS'!C25*'5-PRECIOS SIN IVA'!C18*'2- EMP. REP'!C11/'2- EMP. REP'!C10 -> 73.975475 | D10: =+'3- REND Y CONS'!D25*'5-PRECIOS SIN IVA'!D18*'2- EMP. REP'!D11/'2- EMP. REP'!D10 -> 56.07174 | E10: =+'3- REND Y CONS'!E25*'5-PRECIOS SIN IVA'!E18*'2- EMP. REP'!E11/'2- EMP. REP'!E10 -> 119.76143 | F10: =+'3- REND Y CONS'!F25*'5-PRECIOS SIN IVA'!F18*'2- EMP. REP'!F11/'2- EMP. REP'!F10 -> 49.142981 | G10: =+'3- REND Y CONS'!G25*'5-PRECIOS SIN IVA'!G18*'2- EMP. REP'!G11/'2- EMP. REP'!G10 -> 66.231241 | H10: =+'3- REND Y CONS'!H25*'5-PRECIOS SIN IVA'!H18*'2- EMP. REP'!H11/'2- EMP. REP'!H10 -> 48.632013 | I10: =+'3- REND Y CONS'!I25*'5-PRECIOS SIN IVA'!I18*'2- EMP. REP'!I11/'2- EMP. REP'!I10 -> 61.896305 | J10: =+'3- REND Y CONS'!J25*'5-PRECIOS SIN IVA'!J18*'2- EMP. REP'!J11/'2- EMP. REP'!J10 -> 57.50748 | L10: =+A10 -> . Reparación y Mant. carrocería | V10: =+A10 -> . Reparación y Mant. carrocería | AF10: =+L10 -> . Reparación y Mant. carrocería
A11: 6. DEPRECIACION DEL MATERIAL RODANTE | B11: =+B12+B13 -> 309.33279 | C11: =+C12+C13 -> 219.074 | D11: =+D12+D13 -> 166.05315 | E11: =+E12+E13 -> 153.40363 | F11: =+F12+F13 -> 145.53404 | G11: =+G12+G13 -> 196.13991 | H11: =+H12+H13 -> 144.02084 | I11: =+I12+I13 -> 182.44684 | J11: =+J12+J13 -> 169.51024 | L11: =+A11 -> 6. DEPRECIACION DEL MATERIAL RODANTE | M11: =+B11/B$51 -> 0.079811995 | N11: =+C11/C$51 -> 0.063285603 | O11: =+D11/D$51 -> 0.059555007 | P11: =+E11/E$51 -> 0.065217024 | Q11: =+F11/F$51 -> 0.06122337 | R11: =+G11/G$51 -> 0.063728023 | S11: =+H11/H$51 -> 0.058187963 | T11: =+I11/I$51 -> 0.058691258 | U11: =+J11/J$51 -> 0.057546319 | V11: =+A11 -> 6. DEPRECIACION DEL MATERIAL RODANTE | W11: =+B11/'[1]1-COSTO X KM'!B11-1 -> 0.95715192 | X11: =+C11/'[1]1-COSTO X KM'!C11-1 -> 0.77639397 | Y11: =+D11/'[1]1-COSTO X KM'!D11-1 -> 0.7904541 | Z11: =+E11/'[1]1-COSTO X KM'!E11-1 -> 0.66289825 | AA11: =+F11/'[1]1-COSTO X KM'!F11-1 -> 0.92604027 | AB11: =+G11/'[1]1-COSTO X KM'!G11-1 -> 0.56270093 | AC11: =+H11/'[1]1-COSTO X KM'!H11-1 -> 0.72622926 | AD11: =+I11/'[1]1-COSTO X KM'!I11-1 -> 0.59042916 | AE11: =+J11/'[1]1-COSTO X KM'!J11-1 -> 0.63499212 | AF11: =+L11 -> 6. DEPRECIACION DEL MATERIAL RODANTE | AG11: =+B11/'[2]1-COSTO X KM'!B11-1 -> 0.33287973 | AH11: =+C11/'[2]1-COSTO X KM'!C11-1 -> 0.38547786 | AI11: =+D11/'[2]1-COSTO X KM'!D11-1 -> 0.40024843 | AJ11: =+E11/'[2]1-COSTO X KM'!E11-1 -> 0.31319051 | AK11: =+F11/'[2]1-COSTO X KM'!F11-1 -> 0.53128265 | AL11: =+G11/'[2]1-COSTO X KM'!G11-1 -> 0.39561819 | AM11: =+H11/'[2]1-COSTO X KM'!H11-1 -> 0.487202 | AN11: =+I11/'[2]1-COSTO X KM'!I11-1 -> 0.41868747 | AO11: =+J11/'[2]1-COSTO X KM'!J11-1 -> 0.46536741
A12: . Chasis (incluye boletera y rampa) | B12: =+('5-PRECIOS SIN IVA'!B21+('5-PRECIOS SIN IVA'!B21*'5-PRECIOS SIN IVA'!B19))/'2- EMP. REP'!B10 -> 213.91856 | C12: =+('5-PRECIOS SIN IVA'!C21+('5-PRECIOS SIN IVA'!C21*'5-PRECIOS SIN IVA'!C19))/'2- EMP. REP'!C10 -> 151.50025 | D12: =+('5-PRECIOS SIN IVA'!D21+('5-PRECIOS SIN IVA'!D21*'5-PRECIOS SIN IVA'!D19))/'2- EMP. REP'!D10 -> 114.83377 | E12: =+('5-PRECIOS SIN IVA'!E21+('5-PRECIOS SIN IVA'!E21*'5-PRECIOS SIN IVA'!E19))/'2- EMP. REP'!E10 -> 98.704903 | F12: =+('5-PRECIOS SIN IVA'!F21+('5-PRECIOS SIN IVA'!F21*'5-PRECIOS SIN IVA'!F19))/'2- EMP. REP'!F10 -> 100.64382 | G12: =+('5-PRECIOS SIN IVA'!G21+('5-PRECIOS SIN IVA'!G21*'5-PRECIOS SIN IVA'!G19))/'2- EMP. REP'!G10 -> 135.64022 | H12: =+('5-PRECIOS SIN IVA'!H21+('5-PRECIOS SIN IVA'!H21*'5-PRECIOS SIN IVA'!H19))/'2- EMP. REP'!H10 -> 99.597363 | I12: =+('5-PRECIOS SIN IVA'!I21+('5-PRECIOS SIN IVA'!I21*'5-PRECIOS SIN IVA'!I19))/'2- EMP. REP'!I10 -> 125.90694 | J12: =+('5-PRECIOS SIN IVA'!J21+('5-PRECIOS SIN IVA'!J21*'5-PRECIOS SIN IVA'!J19))/'2- EMP. REP'!J10 -> 116.97937 | L12: =+A12 -> . Chasis (incluye boletera y rampa) | V12: =+A12 -> . Chasis (incluye boletera y rampa) | AF12: =+L12 -> . Chasis (incluye boletera y rampa)
A13: . Carrocería | B13: =+'5-PRECIOS SIN IVA'!B22/'2- EMP. REP'!B10 -> 95.414229 | C13: =+'5-PRECIOS SIN IVA'!C22/'2- EMP. REP'!C10 -> 67.573751 | D13: =+'5-PRECIOS SIN IVA'!D22/'2- EMP. REP'!D10 -> 51.219378 | E13: =+'5-PRECIOS SIN IVA'!E22/'2- EMP. REP'!E10 -> 54.698731 | F13: =+'5-PRECIOS SIN IVA'!F22/'2- EMP. REP'!F10 -> 44.890223 | G13: =+'5-PRECIOS SIN IVA'!G22/'2- EMP. REP'!G10 -> 60.499691 | H13: =+'5-PRECIOS SIN IVA'!H22/'2- EMP. REP'!H10 -> 44.423473 | I13: =+'5-PRECIOS SIN IVA'!I22/'2- EMP. REP'!I10 -> 56.539894 | J13: =+'5-PRECIOS SIN IVA'!J22/'2- EMP. REP'!J10 -> 52.530871 | L13: =+A13 -> . Carrocería | V13: =+A13 -> . Carrocería | AF13: =+L13 -> . Carrocería
A14: 7. SEGURO DEL VEHÍCULO | B14: =SUM(B15:B18) -> 207.38517 | C14: =SUM(C15:C18) -> 190.93517 | D14: =SUM(D15:D18) -> 144.72455 | E14: =SUM(E15:E18) -> 104.32364 | F14: =SUM(F15:F18) -> 126.841 | G14: =SUM(G15:G18) -> 170.94683 | H14: =SUM(H15:H18) -> 125.52216 | I14: =SUM(I15:I18) -> 178.69632 | J14: =SUM(J15:J18) -> 166.02566 | L14: =+A14 -> 7. SEGURO DEL VEHÍCULO | M14: =+B14/B$51 -> 0.053508145 | N14: =+C14/C$51 -> 0.055156919 | O14: =+D14/D$51 -> 0.051905498 | P14: =+E14/E$51 -> 0.044351476 | Q14: =+F14/F$51 -> 0.053359569 | R14: =+G14/G$51 -> 0.055542513 | S14: =+H14/H$51 -> 0.050714043 | T14: =+I14/I$51 -> 0.057484756 | U14: =+J14/J$51 -> 0.056363353 | V14: =+A14 -> 7. SEGURO DEL VEHÍCULO | W14: =+B14/'[1]1-COSTO X KM'!B14-1 -> 0.26100341 | X14: =+C14/'[1]1-COSTO X KM'!C14-1 -> 0.48790212 | Y14: =+D14/'[1]1-COSTO X KM'!D14-1 -> 0.49967885 | Z14: =+E14/'[1]1-COSTO X KM'!E14-1 -> 0.41486 | AA14: =+F14/'[1]1-COSTO X KM'!F14-1 -> 0.61324541 | AB14: =+G14/'[1]1-COSTO X KM'!G14-1 -> 0.3089135 | AC14: =+H14/'[1]1-COSTO X KM'!H14-1 -> 0.44588432 | AD14: =+I14/'[1]1-COSTO X KM'!I14-1 -> 0.32356718 | AE14: =+J14/'[1]1-COSTO X KM'!J14-1 -> 0.36065281 | AF14: =+L14 -> 7. SEGURO DEL VEHÍCULO | AG14: =+B14/'[2]1-COSTO X KM'!B14-1 -> 0.18592012 | AH14: =+C14/'[2]1-COSTO X KM'!C14-1 -> 0.23271892 | AI14: =+D14/'[2]1-COSTO X KM'!D14-1 -> 0.24586093 | AJ14: =+E14/'[2]1-COSTO X KM'!E14-1 -> 0.18078277 | AK14: =+F14/'[2]1-COSTO X KM'!F14-1 -> 0.36244767 | AL14: =+G14/'[2]1-COSTO X KM'!G14-1 -> 0.2417412 | AM14: =+H14/'[2]1-COSTO X KM'!H14-1 -> 0.32322724 | AN14: =+I14/'[2]1-COSTO X KM'!I14-1 -> 0.25680765 | AO14: =+J14/'[2]1-COSTO X KM'!J14-1 -> 0.29816116
A15: . Responsabilidad civil | B15: =+'5-PRECIOS SIN IVA'!B27/'2- EMP. REP'!B8 -> 78.828086 | C15: =+'5-PRECIOS SIN IVA'!C27/'2- EMP. REP'!C8 -> 72.575363 | D15: =+'5-PRECIOS SIN IVA'!D27/'2- EMP. REP'!D8 -> 55.010487 | E15: =+'5-PRECIOS SIN IVA'!E27/'2- EMP. REP'!E8 -> 36.260074 | F15: =+'5-PRECIOS SIN IVA'!F27/'2- EMP. REP'!F8 -> 48.212867 | G15: =+'5-PRECIOS SIN IVA'!G27/'2- EMP. REP'!G8 -> 64.977702 | H15: =+'5-PRECIOS SIN IVA'!H27/'2- EMP. REP'!H8 -> 47.711569 | I15: =+'5-PRECIOS SIN IVA'!I27/'2- EMP. REP'!I8 -> 70.187009 | J15: =+'5-PRECIOS SIN IVA'!J27/'2- EMP. REP'!J8 -> 65.210322 | L15: =+A15 -> . Responsabilidad civil | V15: =+A15 -> . Responsabilidad civil | AF15: =+L15 -> . Responsabilidad civil
A16: . Costo de Franquicia | B16: =+'5-PRECIOS SIN IVA'!B29/'2- EMP. REP'!B8 -> 78.828086 | C16: =+'5-PRECIOS SIN IVA'!C29/'2- EMP. REP'!C8 -> 72.575363 | D16: =+'5-PRECIOS SIN IVA'!D29/'2- EMP. REP'!D8 -> 55.010487 | E16: =+'5-PRECIOS SIN IVA'!E29/'2- EMP. REP'!E8 -> 36.260074 | F16: =+'5-PRECIOS SIN IVA'!F29/'2- EMP. REP'!F8 -> 48.212867 | G16: =+'5-PRECIOS SIN IVA'!G29/'2- EMP. REP'!G8 -> 64.977702 | H16: =+'5-PRECIOS SIN IVA'!H29/'2- EMP. REP'!H8 -> 47.711569 | I16: =+'5-PRECIOS SIN IVA'!I29/'2- EMP. REP'!I8 -> 70.187009 | J16: =+'5-PRECIOS SIN IVA'!J29/'2- EMP. REP'!J8 -> 65.210322 | L16: =+A16 -> . Costo de Franquicia | V16: =+A16 -> . Costo de Franquicia | AF16: =+L16 -> . Costo de Franquicia
A17: . Chasis | B17: =+'5-PRECIOS SIN IVA'!B34/'2- EMP. REP'!B8 -> 34.663591 | C17: =+'5-PRECIOS SIN IVA'!C34/'2- EMP. REP'!C8 -> 31.91404 | D17: =+'5-PRECIOS SIN IVA'!D34/'2- EMP. REP'!D8 -> 24.190122 | E17: =+'5-PRECIOS SIN IVA'!E34/'2- EMP. REP'!E8 -> 20.57586 | F17: =+'5-PRECIOS SIN IVA'!F34/'2- EMP. REP'!F8 -> 21.20096 | G17: =+'5-PRECIOS SIN IVA'!G34/'2- EMP. REP'!G8 -> 28.573071 | H17: =+'5-PRECIOS SIN IVA'!H34/'2- EMP. REP'!H8 -> 20.980521 | I17: =+'5-PRECIOS SIN IVA'!I34/'2- EMP. REP'!I8 -> 26.716743 | J17: =+'5-PRECIOS SIN IVA'!J34/'2- EMP. REP'!J8 -> 24.822364 | L17: =+A17 -> . Chasis | V17: =+A17 -> . Chasis | AF17: =+L17 -> . Chasis
A18: . Carrocería | B18: =+'5-PRECIOS SIN IVA'!B35/'2- EMP. REP'!B8 -> 15.065405 | C18: =+'5-PRECIOS SIN IVA'!C35/'2- EMP. REP'!C8 -> 13.870402 | D18: =+'5-PRECIOS SIN IVA'!D35/'2- EMP. REP'!D8 -> 10.513451 | E18: =+'5-PRECIOS SIN IVA'!E35/'2- EMP. REP'!E8 -> 11.227634 | F18: =+'5-PRECIOS SIN IVA'!F35/'2- EMP. REP'!F8 -> 9.214309 | G18: =+'5-PRECIOS SIN IVA'!G35/'2- EMP. REP'!G8 -> 12.418358 | H18: =+'5-PRECIOS SIN IVA'!H35/'2- EMP. REP'!H8 -> 9.1185024 | I18: =+'5-PRECIOS SIN IVA'!I35/'2- EMP. REP'!I8 -> 11.605557 | J18: =+'5-PRECIOS SIN IVA'!J35/'2- EMP. REP'!J8 -> 10.782653 | L18: =+A18 -> . Carrocería | V18: =+A18 -> . Carrocería | AF18: =+L18 -> . Carrocería
A19: 8. PATENTES Y TNFT | B19: =+('5-PRECIOS SIN IVA'!B36+'5-PRECIOS SIN IVA'!B37)/'2- EMP. REP'!B8 -> 1.0760856 | C19: =+('5-PRECIOS SIN IVA'!C36+'5-PRECIOS SIN IVA'!C37)/'2- EMP. REP'!C8 -> 1.0331299 | D19: =+('5-PRECIOS SIN IVA'!D36+'5-PRECIOS SIN IVA'!D37)/'2- EMP. REP'!D8 -> 0.78308917 | E19: =+('5-PRECIOS SIN IVA'!E36+'5-PRECIOS SIN IVA'!E37)/'2- EMP. REP'!E8 -> 0.51617197 | F19: =+('5-PRECIOS SIN IVA'!F36+'5-PRECIOS SIN IVA'!F37)/'2- EMP. REP'!F8 -> 0.6863232 | G19: =+('5-PRECIOS SIN IVA'!G36+'5-PRECIOS SIN IVA'!G37)/'2- EMP. REP'!G8 -> 0.031067929 | H19: =+('5-PRECIOS SIN IVA'!H36+'5-PRECIOS SIN IVA'!H37)/'2- EMP. REP'!H8 -> 0.022812436 | I19: =+('5-PRECIOS SIN IVA'!I36+'5-PRECIOS SIN IVA'!I37)/'2- EMP. REP'!I8 -> 0.033558667 | J19: =+('5-PRECIOS SIN IVA'!J36+'5-PRECIOS SIN IVA'!J37)/'2- EMP. REP'!J8 -> 0.031179153 | L19: =+A19 -> 8. PATENTES Y TNFT | M19: =+B19/B$51 -> 0.00027764446 | N19: =+C19/C$51 -> 0.00029844824 | O19: =+D19/D$51 -> 0.00028085514 | P19: =+E19/E$51 -> 0.000219442 | Q19: =+F19/F$51 -> 0.00028872296 | R19: =+G19/G$51 -> 1.0094313e-05 | S19: =+H19/H$51 -> 9.2167857e-06 | T19: =+I19/I$51 -> 1.0795476e-05 | U19: =+J19/J$51 -> 1.0584879e-05 | V19: =+A19 -> 8. PATENTES Y TNFT | W19: =+B19/'[1]1-COSTO X KM'!B19-1 -> -0.036461882 | X19: =+C19/'[1]1-COSTO X KM'!C19-1 -> 0.1369124 | Y19: =+D19/'[1]1-COSTO X KM'!D19-1 -> 0.14591105 | Z19: =+E19/'[1]1-COSTO X KM'!E19-1 -> 0.066687269 | AA19: =+F19/'[1]1-COSTO X KM'!F19-1 -> 0.23268774 | AB19: =+G19/'[1]1-COSTO X KM'!G19-1 -> 0.00014642168 | AC19: =+H19/'[1]1-COSTO X KM'!H19-1 -> 0.10480641 | AD19: =+I19/'[1]1-COSTO X KM'!I19-1 -> 0.016593738 | AE19: =+J19/'[1]1-COSTO X KM'!J19-1 -> 0.04507814 | AF19: =+L19 -> 8. PATENTES Y TNFT | AG19: =+B19/'[2]1-COSTO X KM'!B19-1 -> -0.043819942 | AH19: =+C19/'[2]1-COSTO X KM'!C19-1 -> -0.0060871408 | AI19: =+D19/'[2]1-COSTO X KM'!D19-1 -> 0.004508955 | AJ19: =+E19/'[2]1-COSTO X KM'!E19-1 -> -0.056579246 | AK19: =+F19/'[2]1-COSTO X KM'!F19-1 -> 0.098510161 | AL19: =+G19/'[2]1-COSTO X KM'!G19-1 -> 0.0011873132 | AM19: =+H19/'[2]1-COSTO X KM'!H19-1 -> 0.066887625 | AN19: =+I19/'[2]1-COSTO X KM'!I19-1 -> 0.016906601 | AO19: =+J19/'[2]1-COSTO X KM'!J19-1 -> 0.050366499
A20: 9. SALARIOS DEL PERSONAL | B20: =SUM(B21:B24) -> 1581.0802 | C20: =SUM(C21:C24) -> 1488.423 | D20: =SUM(D21:D24) -> 1123.2204 | E20: =SUM(E21:E24) -> 779.24119 | F20: =SUM(F21:F24) -> 1003.7772 | G20: =SUM(G21:G24) -> 1339.1591 | H20: =SUM(H21:H24) -> 984.75196 | I20: =SUM(I21:I24) -> 1402.7351 | J20: =SUM(J21:J24) -> 1307.237 | L20: =+A20 -> 9. SALARIOS DEL PERSONAL | M20: =+B20/B$51 -> 0.40793982 | N20: =+C20/C$51 -> 0.42997226 | O20: =+D20/D$51 -> 0.40284331 | P20: =+E20/E$51 -> 0.33128153 | Q20: =+F20/F$51 -> 0.42226976 | R20: =+G20/G$51 -> 0.43510759 | S20: =+H20/H$51 -> 0.39786403 | T20: =+I20/I$51 -> 0.45124535 | U20: =+J20/J$51 -> 0.44378839 | V20: =+A20 -> 9. SALARIOS DEL PERSONAL | W20: =+B20/'[1]1-COSTO X KM'!B20-1 -> 0.3007605 | X20: =+C20/'[1]1-COSTO X KM'!C20-1 -> 0.49913528 | Y20: =+D20/'[1]1-COSTO X KM'!D20-1 -> 0.52387197 | Z20: =+E20/'[1]1-COSTO X KM'!E20-1 -> 0.39501739 | AA20: =+F20/'[1]1-COSTO X KM'!F20-1 -> 0.50244662 | AB20: =+G20/'[1]1-COSTO X KM'!G20-1 -> 0.34080503 | AC20: =+H20/'[1]1-COSTO X KM'!H20-1 -> 0.47708754 | AD20: =+I20/'[1]1-COSTO X KM'!I20-1 -> 0.31139156 | AE20: =+J20/'[1]1-COSTO X KM'!J20-1 -> 0.40270603 | AF20: =+L20 -> 9. SALARIOS DEL PERSONAL | AG20: =+B20/'[2]1-COSTO X KM'!B20-1 -> 0.15009329 | AH20: =+C20/'[2]1-COSTO X KM'!C20-1 -> 0.18853242 | AI20: =+D20/'[2]1-COSTO X KM'!D20-1 -> 0.20392115 | AJ20: =+E20/'[2]1-COSTO X KM'!E20-1 -> 0.131259 | AK20: =+F20/'[2]1-COSTO X KM'!F20-1 -> 0.31289276 | AL20: =+G20/'[2]1-COSTO X KM'!G20-1 -> 0.197073 | AM20: =+H20/'[2]1-COSTO X KM'!H20-1 -> 0.27519254 | AN20: =+I20/'[2]1-COSTO X KM'!I20-1 -> 0.19587004 | AO20: =+J20/'[2]1-COSTO X KM'!J20-1 -> 0.25576395
A21: Personal de conducción | B21: =+'4- PERSONAL'!B138/'2- EMP. REP'!B8 -> 1279.4083 | C21: =+'4- PERSONAL'!C138/'2- EMP. REP'!C8 -> 1207.4801 | D21: =+'4- PERSONAL'!D138/'2- EMP. REP'!D8 -> 910.27209 | E21: =+'4- PERSONAL'!E138/'2- EMP. REP'!E8 -> 625.69666 | F21: =+'4- PERSONAL'!F138/'2- EMP. REP'!F8 -> 817.1428 | G21: =+'4- PERSONAL'!G138/'2- EMP. REP'!G8 -> 1087.6272 | H21: =+'4- PERSONAL'!H138/'2- EMP. REP'!H8 -> 800.05814 | I21: =+'4- PERSONAL'!I138/'2- EMP. REP'!I8 -> 1134.1255 | J21: =+'4- PERSONAL'!J138/'2- EMP. REP'!J8 -> 1057.6735 | L21: =+A21 -> Personal de conducción | V21: =+A21 -> Personal de conducción | AF21: =+L21 -> Personal de conducción
A22: Personal de tráfico | B22: =+'4- PERSONAL'!B139/'2- EMP. REP'!B8 -> 110.86749 | C22: =+'4- PERSONAL'!C139/'2- EMP. REP'!C8 -> 90.100612 | D22: =+'4- PERSONAL'!D139/'2- EMP. REP'!D8 -> 68.29423 | E22: =+'4- PERSONAL'!E139/'2- EMP. REP'!E8 -> 49.242951 | F22: =+'4- PERSONAL'!F139/'2- EMP. REP'!F8 -> 59.855144 | G22: =+'4- PERSONAL'!G139/'2- EMP. REP'!G8 -> 80.668294 | H22: =+'4- PERSONAL'!H139/'2- EMP. REP'!H8 -> 59.232795 | I22: =+'4- PERSONAL'!I139/'2- EMP. REP'!I8 -> 98.716808 | J22: =+'4- PERSONAL'!J139/'2- EMP. REP'!J8 -> 91.717185 | L22: =+A22 -> Personal de tráfico | V22: =+A22 -> Personal de tráfico | AF22: =+L22 -> Personal de tráfico
A23: Personal de mantenimiento | B23: =+'4- PERSONAL'!B140/'2- EMP. REP'!B8 -> 120.22468 | C23: =+'4- PERSONAL'!C140/'2- EMP. REP'!C8 -> 122.0717 | D23: =+'4- PERSONAL'!D140/'2- EMP. REP'!D8 -> 92.527591 | E23: =+'4- PERSONAL'!E140/'2- EMP. REP'!E8 -> 66.716201 | F23: =+'4- PERSONAL'!F140/'2- EMP. REP'!F8 -> 81.094 | G23: =+'4- PERSONAL'!G140/'2- EMP. REP'!G8 -> 109.2924 | H23: =+'4- PERSONAL'!H140/'2- EMP. REP'!H8 -> 80.250791 | I23: =+'4- PERSONAL'!I140/'2- EMP. REP'!I8 -> 107.04846 | J23: =+'4- PERSONAL'!J140/'2- EMP. REP'!J8 -> 99.458075 | L23: =+A23 -> Personal de mantenimiento | V23: =+A23 -> Personal de mantenimiento | AF23: =+L23 -> Personal de mantenimiento
A24: Personal de administración | B24: =+'4- PERSONAL'!B141/'2- EMP. REP'!B8 -> 70.579775 | C24: =+'4- PERSONAL'!C141/'2- EMP. REP'!C8 -> 68.770549 | D24: =+'4- PERSONAL'!D141/'2- EMP. REP'!D8 -> 52.126524 | E24: =+'4- PERSONAL'!E141/'2- EMP. REP'!E8 -> 37.585369 | F24: =+'4- PERSONAL'!F141/'2- EMP. REP'!F8 -> 45.685273 | G24: =+'4- PERSONAL'!G141/'2- EMP. REP'!G8 -> 61.571175 | H24: =+'4- PERSONAL'!H141/'2- EMP. REP'!H8 -> 45.210238 | I24: =+'4- PERSONAL'!I141/'2- EMP. REP'!I8 -> 62.844334 | J24: =+'4- PERSONAL'!J141/'2- EMP. REP'!J8 -> 58.388288 | L24: =+A24 -> Personal de administración | V24: =+A24 -> Personal de administración | AF24: =+L24 -> Personal de administración
A25: 10. SEGUROS DEL PERSONAL | B25: =+'4- PERSONAL'!B132/'2- EMP. REP'!B5 -> 81.436904 | C25: =+'4- PERSONAL'!C132/'2- EMP. REP'!C5 -> 76.663343 | D25: =+'4- PERSONAL'!D132/'2- EMP. REP'!D5 -> 57.851228 | E25: =+'4- PERSONAL'!E132/'2- EMP. REP'!E5 -> 40.135288 | F25: =+'4- PERSONAL'!F132/'2- EMP. REP'!F5 -> 51.708034 | G25: =+'4- PERSONAL'!G132/'2- EMP. REP'!G5 -> 68.977672 | H25: =+'4- PERSONAL'!H132/'2- EMP. REP'!H5 -> 50.722166 | I25: =+'4- PERSONAL'!I132/'2- EMP. REP'!I5 -> 72.253726 | J25: =+'4- PERSONAL'!J132/'2- EMP. REP'!J5 -> 67.339255 | L25: =+A25 -> 10. SEGUROS DEL PERSONAL | M25: =+B25/B$51 -> 0.02101181 | N25: =+C25/C$51 -> 0.022146333 | O25: =+D25/D$51 -> 0.020748358 | P25: =+E25/E$51 -> 0.017062855 | Q25: =+F25/F$51 -> 0.021752575 | R25: =+G25/G$51 -> 0.022411607 | S25: =+H25/H$51 -> 0.020493004 | T25: =+I25/I$51 -> 0.023243276 | U25: =+J25/J$51 -> 0.02286072 | V25: =+A25 -> 10. SEGUROS DEL PERSONAL | W25: =+B25/'[1]1-COSTO X KM'!B25-1 -> 0.30083186 | X25: =+C25/'[1]1-COSTO X KM'!C25-1 -> 0.4992198 | Y25: =+D25/'[1]1-COSTO X KM'!D25-1 -> 0.52397327 | Z25: =+E25/'[1]1-COSTO X KM'!E25-1 -> 0.39510682 | AA25: =+F25/'[1]1-COSTO X KM'!F25-1 -> 0.50249582 | AB25: =+G25/'[1]1-COSTO X KM'!G25-1 -> 0.34085948 | AC25: =+H25/'[1]1-COSTO X KM'!H25-1 -> 0.47714531 | AD25: =+I25/'[1]1-COSTO X KM'!I25-1 -> 0.31144184 | AE25: =+J25/'[1]1-COSTO X KM'!J25-1 -> 0.40269892 | AF25: =+L25 -> 10. SEGUROS DEL PERSONAL | AG25: =+B25/'[2]1-COSTO X KM'!B25-1 -> 0.15007523 | AH25: =+C25/'[2]1-COSTO X KM'!C25-1 -> 0.1885193 | AI25: =+D25/'[2]1-COSTO X KM'!D25-1 -> 0.2039155 | AJ25: =+E25/'[2]1-COSTO X KM'!E25-1 -> 0.13125225 | AK25: =+F25/'[2]1-COSTO X KM'!F25-1 -> 0.31284473 | AL25: =+G25/'[2]1-COSTO X KM'!G25-1 -> 0.19704865 | AM25: =+H25/'[2]1-COSTO X KM'!H25-1 -> 0.27516288 | AN25: =+I25/'[2]1-COSTO X KM'!I25-1 -> 0.19584244 | AO25: =+J25/'[2]1-COSTO X KM'!J25-1 -> 0.25569937
A26: 11. MÁQUINAS, HERRAMIENTAS E INMUEBLES | B26: =SUM(B27:B30) -> 13.424851 | C26: =SUM(C27:C30) -> 12.359978 | D26: =SUM(D27:D30) -> 9.3685846 | E26: =SUM(E27:E30) -> 7.7027731 | F26: =SUM(F27:F30) -> 7.8764877 | G26: =SUM(G27:G30) -> 10.615342 | H26: =SUM(H27:H30) -> 7.7945912 | I26: =SUM(I27:I30) -> 10.592917 | J26: =SUM(J27:J30) -> 9.8418146 | L26: =+A26 -> 11. MÁQUINAS, HERRAMIENTAS E INMUEBLES | M26: =+B26/B$51 -> 0.003463791 | N26: =+C26/C$51 -> 0.0035705226 | O26: =+D26/D$51 -> 0.0033600454 | P26: =+E26/E$51 -> 0.0032747069 | Q26: =+F26/F$51 -> 0.0033134868 | R26: =+G26/G$51 -> 0.0034490418 | S26: =+H26/H$51 -> 0.0031492067 | T26: =+I26/I$51 -> 0.0034076317 | U26: =+J26/J$51 -> 0.0033411562 | V26: =+A26 -> 11. MÁQUINAS, HERRAMIENTAS E INMUEBLES | W26: =+B26/'[1]1-COSTO X KM'!B26-1 -> 0.34462516 | X26: =+C26/'[1]1-COSTO X KM'!C26-1 -> 0.58657036 | Y26: =+D26/'[1]1-COSTO X KM'!D26-1 -> 0.59912805 | Z26: =+E26/'[1]1-COSTO X KM'!E26-1 -> 0.50910412 | AA26: =+F26/'[1]1-COSTO X KM'!F26-1 -> 0.70519828 | AB26: =+G26/'[1]1-COSTO X KM'!G26-1 -> 0.38351985 | AC26: =+H26/'[1]1-COSTO X KM'!H26-1 -> 0.52829783 | AD26: =+I26/'[1]1-COSTO X KM'!I26-1 -> 0.3938983 | AE26: =+J26/'[1]1-COSTO X KM'!J26-1 -> 0.43295457 | AF26: =+L26 -> 11. MÁQUINAS, HERRAMIENTAS E INMUEBLES | AG26: =+B26/'[2]1-COSTO X KM'!B26-1 -> 0.23819836 | AH26: =+C26/'[2]1-COSTO X KM'!C26-1 -> 0.28706018 | AI26: =+D26/'[2]1-COSTO X KM'!D26-1 -> 0.30078151 | AJ26: =+E26/'[2]1-COSTO X KM'!E26-1 -> 0.23282665 | AK26: =+F26/'[2]1-COSTO X KM'!F26-1 -> 0.40841014 | AL26: =+G26/'[2]1-COSTO X KM'!G26-1 -> 0.28363161 | AM26: =+H26/'[2]1-COSTO X KM'!H26-1 -> 0.36786659 | AN26: =+I26/'[2]1-COSTO X KM'!I26-1 -> 0.29570948 | AO26: =+J26/'[2]1-COSTO X KM'!J26-1 -> 0.338343
A27: Conservación de inmuebles | B27: =+('3- REND Y CONS'!B33*'3- REND Y CONS'!B38*'5-PRECIOS SIN IVA'!B43+'3- REND Y CONS'!B37*SUMPRODUCT('3- REND Y CONS'!B34:B35,'5-PRECIOS SIN IVA'!B44:B45))/'2- EMP. REP'!B5 -> 2.435158 | C27: =+('3- REND Y CONS'!C33*'3- REND Y CONS'!C38*'5-PRECIOS SIN IVA'!C43+'3- REND Y CONS'!C37*SUMPRODUCT('3- REND Y CONS'!C34:C35,'5-PRECIOS SIN IVA'!C44:C45))/'2- EMP. REP'!C5 -> 2.2419989 | D27: =+('3- REND Y CONS'!D33*'3- REND Y CONS'!D38*'5-PRECIOS SIN IVA'!D43+'3- REND Y CONS'!D37*SUMPRODUCT('3- REND Y CONS'!D34:D35,'5-PRECIOS SIN IVA'!D44:D45))/'2- EMP. REP'!D5 -> 1.6993845 | E27: =+('3- REND Y CONS'!E33*'3- REND Y CONS'!E38*'5-PRECIOS SIN IVA'!E43+'3- REND Y CONS'!E37*SUMPRODUCT('3- REND Y CONS'!E34:E35,'5-PRECIOS SIN IVA'!E44:E45))/'2- EMP. REP'!E5 -> 1.2011513 | F27: =+('3- REND Y CONS'!F33*'3- REND Y CONS'!F38*'5-PRECIOS SIN IVA'!F43+'3- REND Y CONS'!F37*SUMPRODUCT('3- REND Y CONS'!F34:F35,'5-PRECIOS SIN IVA'!F44:F45))/'2- EMP. REP'!F5 -> 1.3275737 | G27: =+('3- REND Y CONS'!G33*'3- REND Y CONS'!G38*'5-PRECIOS SIN IVA'!G43+'3- REND Y CONS'!G37*SUMPRODUCT('3- REND Y CONS'!G34:G35,'5-PRECIOS SIN IVA'!G44:G45))/'2- EMP. REP'!G5 -> 1.7892047 | H27: =+('3- REND Y CONS'!H33*'3- REND Y CONS'!H38*'5-PRECIOS SIN IVA'!H43+'3- REND Y CONS'!H37*SUMPRODUCT('3- REND Y CONS'!H34:H35,'5-PRECIOS SIN IVA'!H44:H45))/'2- EMP. REP'!H5 -> 1.3137701 | I27: =+('3- REND Y CONS'!I33*'3- REND Y CONS'!I38*'5-PRECIOS SIN IVA'!I43+'3- REND Y CONS'!I37*SUMPRODUCT('3- REND Y CONS'!I34:I35,'5-PRECIOS SIN IVA'!I44:I45))/'2- EMP. REP'!I5 -> 1.9326465 | J27: =+('3- REND Y CONS'!J33*'3- REND Y CONS'!J38*'5-PRECIOS SIN IVA'!J43+'3- REND Y CONS'!J37*SUMPRODUCT('3- REND Y CONS'!J34:J35,'5-PRECIOS SIN IVA'!J44:J45))/'2- EMP. REP'!J5 -> 1.7956101 | L27: =+A27 -> Conservación de inmuebles | V27: =+A27 -> Conservación de inmuebles | AF27: =+L27 -> Conservación de inmuebles
A28: Depreciación de inmuebles | B28: =+((('3- REND Y CONS'!B34*'5-PRECIOS SIN IVA'!B44+'3- REND Y CONS'!B35*'5-PRECIOS SIN IVA'!B45)*(1-'3- REND Y CONS'!B43))/'3- REND Y CONS'!B39+(('3- REND Y CONS'!B33*'5-PRECIOS SIN IVA'!B43)*(1-'3- REND Y CONS'!B44))/'3- REND Y CONS'!B41)/'2- EMP. REP'!B5 -> 3.696107 | C28: =+((('3- REND Y CONS'!C34*'5-PRECIOS SIN IVA'!C44+'3- REND Y CONS'!C35*'5-PRECIOS SIN IVA'!C45)*(1-'3- REND Y CONS'!C43))/'3- REND Y CONS'!C39+(('3- REND Y CONS'!C33*'5-PRECIOS SIN IVA'!C43)*(1-'3- REND Y CONS'!C44))/'3- REND Y CONS'!C41)/'2- EMP. REP'!C5 -> 3.4029281 | D28: =+((('3- REND Y CONS'!D34*'5-PRECIOS SIN IVA'!D44+'3- REND Y CONS'!D35*'5-PRECIOS SIN IVA'!D45)*(1-'3- REND Y CONS'!D43))/'3- REND Y CONS'!D39+(('3- REND Y CONS'!D33*'5-PRECIOS SIN IVA'!D43)*(1-'3- REND Y CONS'!D44))/'3- REND Y CONS'!D41)/'2- EMP. REP'!D5 -> 2.5793427 | E28: =+((('3- REND Y CONS'!E34*'5-PRECIOS SIN IVA'!E44+'3- REND Y CONS'!E35*'5-PRECIOS SIN IVA'!E45)*(1-'3- REND Y CONS'!E43))/'3- REND Y CONS'!E39+(('3- REND Y CONS'!E33*'5-PRECIOS SIN IVA'!E43)*(1-'3- REND Y CONS'!E44))/'3- REND Y CONS'!E41)/'2- EMP. REP'!E5 -> 1.8371093 | F28: =+((('3- REND Y CONS'!F34*'5-PRECIOS SIN IVA'!F44+'3- REND Y CONS'!F35*'5-PRECIOS SIN IVA'!F45)*(1-'3- REND Y CONS'!F43))/'3- REND Y CONS'!F39+(('3- REND Y CONS'!F33*'5-PRECIOS SIN IVA'!F43)*(1-'3- REND Y CONS'!F44))/'3- REND Y CONS'!F41)/'2- EMP. REP'!F5 -> 2.0880079 | G28: =+((('3- REND Y CONS'!G34*'5-PRECIOS SIN IVA'!G44+'3- REND Y CONS'!G35*'5-PRECIOS SIN IVA'!G45)*(1-'3- REND Y CONS'!G43))/'3- REND Y CONS'!G39+(('3- REND Y CONS'!G33*'5-PRECIOS SIN IVA'!G43)*(1-'3- REND Y CONS'!G44))/'3- REND Y CONS'!G41)/'2- EMP. REP'!G5 -> 2.8140611 | H28: =+((('3- REND Y CONS'!H34*'5-PRECIOS SIN IVA'!H44+'3- REND Y CONS'!H35*'5-PRECIOS SIN IVA'!H45)*(1-'3- REND Y CONS'!H43))/'3- REND Y CONS'!H39+(('3- REND Y CONS'!H33*'5-PRECIOS SIN IVA'!H43)*(1-'3- REND Y CONS'!H44))/'3- REND Y CONS'!H41)/'2- EMP. REP'!H5 -> 2.0662976 | I28: =+((('3- REND Y CONS'!I34*'5-PRECIOS SIN IVA'!I44+'3- REND Y CONS'!I35*'5-PRECIOS SIN IVA'!I45)*(1-'3- REND Y CONS'!I43))/'3- REND Y CONS'!I39+(('3- REND Y CONS'!I33*'5-PRECIOS SIN IVA'!I43)*(1-'3- REND Y CONS'!I44))/'3- REND Y CONS'!I41)/'2- EMP. REP'!I5 -> 3.0396664 | J28: =+((('3- REND Y CONS'!J34*'5-PRECIOS SIN IVA'!J44+'3- REND Y CONS'!J35*'5-PRECIOS SIN IVA'!J45)*(1-'3- REND Y CONS'!J43))/'3- REND Y CONS'!J39+(('3- REND Y CONS'!J33*'5-PRECIOS SIN IVA'!J43)*(1-'3- REND Y CONS'!J44))/'3- REND Y CONS'!J41)/'2- EMP. REP'!J5 -> 2.8241355 | L28: =+A28 -> Depreciación de inmuebles | V28: =+A28 -> Depreciación de inmuebles | AF28: =+L28 -> Depreciación de inmuebles
A29: Conservación de máquinas y herramientas | B29: =+('5-PRECIOS SIN IVA'!B17+'5-PRECIOS SIN IVA'!B18)*('3- REND Y CONS'!B45)*('3- REND Y CONS'!B46)/'2- EMP. REP'!B8 -> 1.9891598 | C29: =+('5-PRECIOS SIN IVA'!C17+'5-PRECIOS SIN IVA'!C18)*('3- REND Y CONS'!C45)*('3- REND Y CONS'!C46)/'2- EMP. REP'!C8 -> 1.8313777 | D29: =+('5-PRECIOS SIN IVA'!D17+'5-PRECIOS SIN IVA'!D18)*('3- REND Y CONS'!D45)*('3- REND Y CONS'!D46)/'2- EMP. REP'!D8 -> 1.3881429 | E29: =+('5-PRECIOS SIN IVA'!E17+'5-PRECIOS SIN IVA'!E18)*('3- REND Y CONS'!E45)*('3- REND Y CONS'!E46)/'2- EMP. REP'!E8 -> 1.2721398 | F29: =+('5-PRECIOS SIN IVA'!F17+'5-PRECIOS SIN IVA'!F18)*('3- REND Y CONS'!F45)*('3- REND Y CONS'!F46)/'2- EMP. REP'!F8 -> 1.2166108 | G29: =+('5-PRECIOS SIN IVA'!G17+'5-PRECIOS SIN IVA'!G18)*('3- REND Y CONS'!G45)*('3- REND Y CONS'!G46)/'2- EMP. REP'!G8 -> 1.6396571 | H29: =+('5-PRECIOS SIN IVA'!H17+'5-PRECIOS SIN IVA'!H18)*('3- REND Y CONS'!H45)*('3- REND Y CONS'!H46)/'2- EMP. REP'!H8 -> 1.2039609 | I29: =+('5-PRECIOS SIN IVA'!I17+'5-PRECIOS SIN IVA'!I18)*('3- REND Y CONS'!I45)*('3- REND Y CONS'!I46)/'2- EMP. REP'!I8 -> 1.532892 | J29: =+('5-PRECIOS SIN IVA'!J17+'5-PRECIOS SIN IVA'!J18)*('3- REND Y CONS'!J45)*('3- REND Y CONS'!J46)/'2- EMP. REP'!J8 -> 1.4242006 | L29: =+A29 -> Conservación de máquinas y herramientas | V29: =+A29 -> Conservación de máquinas y herramientas | AF29: =+L29 -> Conservación de máquinas y herramientas
A30: Depreciación de máquinas y herramientas | B30: =+('3- REND Y CONS'!B45*'2- EMP. REP'!B6*('5-PRECIOS SIN IVA'!B17+'5-PRECIOS SIN IVA'!B18)*(1-'3- REND Y CONS'!B48)/'3- REND Y CONS'!B47)/'2- EMP. REP'!B5 -> 5.3044262 | C30: =+('3- REND Y CONS'!C45*'2- EMP. REP'!C6*('5-PRECIOS SIN IVA'!C17+'5-PRECIOS SIN IVA'!C18)*(1-'3- REND Y CONS'!C48)/'3- REND Y CONS'!C47)/'2- EMP. REP'!C5 -> 4.8836738 | D30: =+('3- REND Y CONS'!D45*'2- EMP. REP'!D6*('5-PRECIOS SIN IVA'!D17+'5-PRECIOS SIN IVA'!D18)*(1-'3- REND Y CONS'!D48)/'3- REND Y CONS'!D47)/'2- EMP. REP'!D5 -> 3.7017145 | E30: =+('3- REND Y CONS'!E45*'2- EMP. REP'!E6*('5-PRECIOS SIN IVA'!E17+'5-PRECIOS SIN IVA'!E18)*(1-'3- REND Y CONS'!E48)/'3- REND Y CONS'!E47)/'2- EMP. REP'!E5 -> 3.3923727 | F30: =+('3- REND Y CONS'!F45*'2- EMP. REP'!F6*('5-PRECIOS SIN IVA'!F17+'5-PRECIOS SIN IVA'!F18)*(1-'3- REND Y CONS'!F48)/'3- REND Y CONS'!F47)/'2- EMP. REP'!F5 -> 3.2442953 | G30: =+('3- REND Y CONS'!G45*'2- EMP. REP'!G6*('5-PRECIOS SIN IVA'!G17+'5-PRECIOS SIN IVA'!G18)*(1-'3- REND Y CONS'!G48)/'3- REND Y CONS'!G47)/'2- EMP. REP'!G5 -> 4.372419 | H30: =+('3- REND Y CONS'!H45*'2- EMP. REP'!H6*('5-PRECIOS SIN IVA'!H17+'5-PRECIOS SIN IVA'!H18)*(1-'3- REND Y CONS'!H48)/'3- REND Y CONS'!H47)/'2- EMP. REP'!H5 -> 3.2105625 | I30: =+('3- REND Y CONS'!I45*'2- EMP. REP'!I6*('5-PRECIOS SIN IVA'!I17+'5-PRECIOS SIN IVA'!I18)*(1-'3- REND Y CONS'!I48)/'3- REND Y CONS'!I47)/'2- EMP. REP'!I5 -> 4.0877121 | J30: =+('3- REND Y CONS'!J45*'2- EMP. REP'!J6*('5-PRECIOS SIN IVA'!J17+'5-PRECIOS SIN IVA'!J18)*(1-'3- REND Y CONS'!J48)/'3- REND Y CONS'!J47)/'2- EMP. REP'!J5 -> 3.7978684 | L30: =+A30 -> Depreciación de máquinas y herramientas | V30: =+A30 -> Depreciación de máquinas y herramientas | AF30: =+L30 -> Depreciación de máquinas y herramientas
A31: 12. IMPUESTOS Y TASAS MUNICIPALES | B31: =(SUMPRODUCT('3- REND Y CONS'!B33:B36,'5-PRECIOS SIN IVA'!B43:B46)*'5-PRECIOS SIN IVA'!B52)*(SUM('5-PRECIOS SIN IVA'!B55:B57))/'2- EMP. REP'!B5 -> 2.6264971 | C31: =(SUMPRODUCT('3- REND Y CONS'!C33:C36,'5-PRECIOS SIN IVA'!C43:C46)*'5-PRECIOS SIN IVA'!C52)*(SUM('5-PRECIOS SIN IVA'!C55:C57))/'2- EMP. REP'!C5 -> 2.4181607 | D31: =(SUMPRODUCT('3- REND Y CONS'!D33:D36,'5-PRECIOS SIN IVA'!D43:D46)*'5-PRECIOS SIN IVA'!D52)*(SUM('5-PRECIOS SIN IVA'!D55:D57))/'2- EMP. REP'!D5 -> 1.8329112 | E31: =(SUMPRODUCT('3- REND Y CONS'!E33:E36,'5-PRECIOS SIN IVA'!E43:E46)*'5-PRECIOS SIN IVA'!E52)*(SUM('5-PRECIOS SIN IVA'!E55:E57))/'2- EMP. REP'!E5 -> 1.3096185 | F31: =(SUMPRODUCT('3- REND Y CONS'!F33:F36,'5-PRECIOS SIN IVA'!F43:F46)*'5-PRECIOS SIN IVA'!F52)*(SUM('5-PRECIOS SIN IVA'!F55:F57))/'2- EMP. REP'!F5 -> 1.2218363 | G31: =(SUMPRODUCT('3- REND Y CONS'!G33:G36,'5-PRECIOS SIN IVA'!G43:G46)*'5-PRECIOS SIN IVA'!G52)*(SUM('5-PRECIOS SIN IVA'!G55:G57))/'2- EMP. REP'!G5 -> 1.6466997 | H31: =(SUMPRODUCT('3- REND Y CONS'!H33:H36,'5-PRECIOS SIN IVA'!H43:H46)*'5-PRECIOS SIN IVA'!H52)*(SUM('5-PRECIOS SIN IVA'!H55:H57))/'2- EMP. REP'!H5 -> 1.2091321 | I31: =(SUMPRODUCT('3- REND Y CONS'!I33:I36,'5-PRECIOS SIN IVA'!I43:I46)*'5-PRECIOS SIN IVA'!I52)*(SUM('5-PRECIOS SIN IVA'!I55:I57))/'2- EMP. REP'!I5 -> 1.7787168 | J31: =(SUMPRODUCT('3- REND Y CONS'!J33:J36,'5-PRECIOS SIN IVA'!J43:J46)*'5-PRECIOS SIN IVA'!J52)*(SUM('5-PRECIOS SIN IVA'!J55:J57))/'2- EMP. REP'!J5 -> 1.6525949 | L31: =+A31 -> 12. IMPUESTOS Y TASAS MUNICIPALES | M31: =+B31/B$51 -> 0.00067767135 | N31: =+C31/C$51 -> 0.00069855279 | O31: =+D31/D$51 -> 0.0006573741 | P31: =+E31/E$51 -> 0.00055676271 | Q31: =+F31/F$51 -> 0.00051400302 | R31: =+G31/G$51 -> 0.00053503093 | S31: =+H31/H$51 -> 0.00048851915 | T31: =+I31/I$51 -> 0.00057219477 | U31: =+J31/J$51 -> 0.0005610325 | V31: =+A31 -> 12. IMPUESTOS Y TASAS MUNICIPALES | W31: =+B31/'[1]1-COSTO X KM'!B31-1 -> -0.21901887 | X31: =+C31/'[1]1-COSTO X KM'!C31-1 -> 0.41821785 | Y31: =+D31/'[1]1-COSTO X KM'!D31-1 -> 0.42944302 | Z31: =+E31/'[1]1-COSTO X KM'!E31-1 -> 0.33061696 | AA31: =+F31/'[1]1-COSTO X KM'!F31-1 -> 0.40840268 | AB31: =+G31/'[1]1-COSTO X KM'!G31-1 -> 0.14271349 | AC31: =+H31/'[1]1-COSTO X KM'!H31-1 -> 0.26229236 | AD31: =+I31/'[1]1-COSTO X KM'!I31-1 -> 0.1615053 | AE31: =+J31/'[1]1-COSTO X KM'!J31-1 -> 0.19405005 | AF31: =+L31 -> 12. IMPUESTOS Y TASAS MUNICIPALES | AG31: =+B31/'[2]1-COSTO X KM'!B31-1 -> -0.25430682 | AH31: =+C31/'[2]1-COSTO X KM'!C31-1 -> 0.19292491 | AI31: =+D31/'[2]1-COSTO X KM'!D31-1 -> 0.20564267 | AJ31: =+E31/'[2]1-COSTO X KM'!E31-1 -> 0.13232272 | AK31: =+F31/'[2]1-COSTO X KM'!F31-1 -> 0.20760998 | AL31: =+G31/'[2]1-COSTO X KM'!G31-1 -> 0.1006214 | AM31: =+H31/'[2]1-COSTO X KM'!H31-1 -> 0.17284681 | AN31: =+I31/'[2]1-COSTO X KM'!I31-1 -> 0.11790186 | AO31: =+J31/'[2]1-COSTO X KM'!J31-1 -> 0.15468487
A32: 13. COSTO DEL CAPITAL INVERTIDO | B32: =SUM(B33:B36) -> 139.01445 | C32: =SUM(C33:C36) -> 127.98768 | D32: =SUM(D33:D36) -> 97.011773 | E32: =SUM(E33:E36) -> 85.776594 | F32: =SUM(F33:F36) -> 81.527812 | G32: =SUM(G33:G36) -> 109.8771 | H32: =SUM(H33:H36) -> 80.680119 | I32: =SUM(I33:I36) -> 104.72111 | J32: =SUM(J33:J36) -> 97.295747 | L32: =+A32 -> 13. COSTO DEL CAPITAL INVERTIDO | M32: =+B32/B$51 -> 0.035867585 | N32: =+C32/C$51 -> 0.036972792 | O32: =+D32/D$51 -> 0.034793299 | P32: =+E32/E$51 -> 0.036466504 | Q32: =+F32/F$51 -> 0.034297181 | R32: =+G32/G$51 -> 0.035700282 | S32: =+H32/H$51 -> 0.032596754 | T32: =+I32/I$51 -> 0.033687697 | U32: =+J32/J$51 -> 0.033030524 | V32: =+A32 -> 13. COSTO DEL CAPITAL INVERTIDO | W32: =+B32/'[1]1-COSTO X KM'!B32-1 -> 0.28380747 | X32: =+C32/'[1]1-COSTO X KM'!C32-1 -> 0.69609499 | Y32: =+D32/'[1]1-COSTO X KM'!D32-1 -> 0.70951956 | Z32: =+E32/'[1]1-COSTO X KM'!E32-1 -> 0.6027828 | AA32: =+F32/'[1]1-COSTO X KM'!F32-1 -> 0.8270007 | AB32: =+G32/'[1]1-COSTO X KM'!G32-1 -> 0.48234476 | AC32: =+H32/'[1]1-COSTO X KM'!H32-1 -> 0.63746424 | AD32: =+I32/'[1]1-COSTO X KM'!I32-1 -> 0.49794982 | AE32: =+J32/'[1]1-COSTO X KM'!J32-1 -> 0.53992156 | AF32: =+L32 -> 13. COSTO DEL CAPITAL INVERTIDO | AG32: =+B32/'[2]1-COSTO X KM'!B32-1 -> 0.16258521 | AH32: =+C32/'[2]1-COSTO X KM'!C32-1 -> 0.34478702 | AI32: =+D32/'[2]1-COSTO X KM'!D32-1 -> 0.35912378 | AJ32: =+E32/'[2]1-COSTO X KM'!E32-1 -> 0.28242379 | AK32: =+F32/'[2]1-COSTO X KM'!F32-1 -> 0.47357801 | AL32: =+G32/'[2]1-COSTO X KM'!G32-1 -> 0.34302591 | AM32: =+H32/'[2]1-COSTO X KM'!H32-1 -> 0.43115849 | AN32: =+I32/'[2]1-COSTO X KM'!I32-1 -> 0.35816881 | AO32: =+J32/'[2]1-COSTO X KM'!J32-1 -> 0.40285747
A33: . Chasis (incluye boletera y rampa) | B33: =+'5-PRECIOS SIN IVA'!B39*'2- EMP. REP'!B6*('5-PRECIOS SIN IVA'!B25)/'2- EMP. REP'!B5 -> 79.466282 | C33: =+'5-PRECIOS SIN IVA'!C39*'2- EMP. REP'!C6*('5-PRECIOS SIN IVA'!C25)/'2- EMP. REP'!C5 -> 73.162937 | D33: =+'5-PRECIOS SIN IVA'!D39*'2- EMP. REP'!D6*('5-PRECIOS SIN IVA'!D25)/'2- EMP. REP'!D5 -> 55.455855 | E33: =+'5-PRECIOS SIN IVA'!E39*'2- EMP. REP'!E6*('5-PRECIOS SIN IVA'!E25)/'2- EMP. REP'!E5 -> 47.170158 | F33: =+'5-PRECIOS SIN IVA'!F39*'2- EMP. REP'!F6*('5-PRECIOS SIN IVA'!F25)/'2- EMP. REP'!F5 -> 48.6032 | G33: =+'5-PRECIOS SIN IVA'!G39*'2- EMP. REP'!G6*('5-PRECIOS SIN IVA'!G25)/'2- EMP. REP'!G5 -> 65.503764 | H33: =+'5-PRECIOS SIN IVA'!H39*'2- EMP. REP'!H6*('5-PRECIOS SIN IVA'!H25)/'2- EMP. REP'!H5 -> 48.097844 | I33: =+'5-PRECIOS SIN IVA'!I39*'2- EMP. REP'!I6*('5-PRECIOS SIN IVA'!I25)/'2- EMP. REP'!I5 -> 61.248134 | J33: =+'5-PRECIOS SIN IVA'!J39*'2- EMP. REP'!J6*('5-PRECIOS SIN IVA'!J25)/'2- EMP. REP'!J5 -> 56.905268 | L33: =+A33 -> . Chasis (incluye boletera y rampa) | V33: =+A33 -> . Chasis (incluye boletera y rampa) | AF33: =+L33 -> . Chasis (incluye boletera y rampa)
A34: . Carrocería | B34: =+'5-PRECIOS SIN IVA'!B39*'2- EMP. REP'!B6*'5-PRECIOS SIN IVA'!B26/'2- EMP. REP'!B5 -> 34.53744 | C34: =+'5-PRECIOS SIN IVA'!C39*'2- EMP. REP'!C6*'5-PRECIOS SIN IVA'!C26/'2- EMP. REP'!C5 -> 31.797896 | D34: =+'5-PRECIOS SIN IVA'!D39*'2- EMP. REP'!D6*'5-PRECIOS SIN IVA'!D26/'2- EMP. REP'!D5 -> 24.102087 | E34: =+'5-PRECIOS SIN IVA'!E39*'2- EMP. REP'!E6*'5-PRECIOS SIN IVA'!E26/'2- EMP. REP'!E5 -> 25.739352 | F34: =+'5-PRECIOS SIN IVA'!F39*'2- EMP. REP'!F6*'5-PRECIOS SIN IVA'!F26/'2- EMP. REP'!F5 -> 21.123803 | G34: =+'5-PRECIOS SIN IVA'!G39*'2- EMP. REP'!G6*'5-PRECIOS SIN IVA'!G26/'2- EMP. REP'!G5 -> 28.469085 | H34: =+'5-PRECIOS SIN IVA'!H39*'2- EMP. REP'!H6*'5-PRECIOS SIN IVA'!H26/'2- EMP. REP'!H5 -> 20.904167 | I34: =+'5-PRECIOS SIN IVA'!I39*'2- EMP. REP'!I6*'5-PRECIOS SIN IVA'!I26/'2- EMP. REP'!I5 -> 26.60574 | J34: =+'5-PRECIOS SIN IVA'!J39*'2- EMP. REP'!J6*'5-PRECIOS SIN IVA'!J26/'2- EMP. REP'!J5 -> 24.719231 | L34: =+A34 -> . Carrocería | V34: =+A34 -> . Carrocería | AF34: =+L34 -> . Carrocería
A35: . Máquinas y herramientas | B35: =+'5-PRECIOS SIN IVA'!B39*('5-PRECIOS SIN IVA'!B17+'5-PRECIOS SIN IVA'!B18)*(1+'3- REND Y CONS'!B48)/2*'2- EMP. REP'!B6*'3- REND Y CONS'!B45/'2- EMP. REP'!B5 -> 2.6057994 | C35: =+'5-PRECIOS SIN IVA'!C39*('5-PRECIOS SIN IVA'!C17+'5-PRECIOS SIN IVA'!C18)*(1+'3- REND Y CONS'!C48)/2*'2- EMP. REP'!C6*'3- REND Y CONS'!C45/'2- EMP. REP'!C5 -> 2.3991047 | D35: =+'5-PRECIOS SIN IVA'!D39*('5-PRECIOS SIN IVA'!D17+'5-PRECIOS SIN IVA'!D18)*(1+'3- REND Y CONS'!D48)/2*'2- EMP. REP'!D6*'3- REND Y CONS'!D45/'2- EMP. REP'!D5 -> 1.8184672 | E35: =+'5-PRECIOS SIN IVA'!E39*('5-PRECIOS SIN IVA'!E17+'5-PRECIOS SIN IVA'!E18)*(1+'3- REND Y CONS'!E48)/2*'2- EMP. REP'!E6*'3- REND Y CONS'!E45/'2- EMP. REP'!E5 -> 1.6665031 | F35: =+'5-PRECIOS SIN IVA'!F39*('5-PRECIOS SIN IVA'!F17+'5-PRECIOS SIN IVA'!F18)*(1+'3- REND Y CONS'!F48)/2*'2- EMP. REP'!F6*'3- REND Y CONS'!F45/'2- EMP. REP'!F5 -> 1.5937601 | G35: =+'5-PRECIOS SIN IVA'!G39*('5-PRECIOS SIN IVA'!G17+'5-PRECIOS SIN IVA'!G18)*(1+'3- REND Y CONS'!G48)/2*'2- EMP. REP'!G6*'3- REND Y CONS'!G45/'2- EMP. REP'!G5 -> 2.1479508 | H35: =+'5-PRECIOS SIN IVA'!H39*('5-PRECIOS SIN IVA'!H17+'5-PRECIOS SIN IVA'!H18)*(1+'3- REND Y CONS'!H48)/2*'2- EMP. REP'!H6*'3- REND Y CONS'!H45/'2- EMP. REP'!H5 -> 1.5771888 | I35: =+'5-PRECIOS SIN IVA'!I39*('5-PRECIOS SIN IVA'!I17+'5-PRECIOS SIN IVA'!I18)*(1+'3- REND Y CONS'!I48)/2*'2- EMP. REP'!I6*'3- REND Y CONS'!I45/'2- EMP. REP'!I5 -> 2.0080886 | J35: =+'5-PRECIOS SIN IVA'!J39*('5-PRECIOS SIN IVA'!J17+'5-PRECIOS SIN IVA'!J18)*(1+'3- REND Y CONS'!J48)/2*'2- EMP. REP'!J6*'3- REND Y CONS'!J45/'2- EMP. REP'!J5 -> 1.8657028 | L35: =+A35 -> . Máquinas y herramientas | V35: =+A35 -> . Máquinas y herramientas | AF35: =+L35 -> . Máquinas y herramientas
A36: . Inmuebles | B36: =+'5-PRECIOS SIN IVA'!B39*('3- REND Y CONS'!B34*'5-PRECIOS SIN IVA'!B44*(1+'3- REND Y CONS'!B43)/2+'3- REND Y CONS'!B35*'5-PRECIOS SIN IVA'!B45*(1+'3- REND Y CONS'!B43)/2+'3- REND Y CONS'!B33*'5-PRECIOS SIN IVA'!B43*(1+'3- REND Y CONS'!B44)/2+'3- REND Y CONS'!B36*'5-PRECIOS SIN IVA'!B46)/'2- EMP. REP'!B5 -> 22.404925 | C36: =+'5-PRECIOS SIN IVA'!C39*('3- REND Y CONS'!C34*'5-PRECIOS SIN IVA'!C44*(1+'3- REND Y CONS'!C43)/2+'3- REND Y CONS'!C35*'5-PRECIOS SIN IVA'!C45*(1+'3- REND Y CONS'!C43)/2+'3- REND Y CONS'!C33*'5-PRECIOS SIN IVA'!C43*(1+'3- REND Y CONS'!C44)/2+'3- REND Y CONS'!C36*'5-PRECIOS SIN IVA'!C46)/'2- EMP. REP'!C5 -> 20.627744 | D36: =+'5-PRECIOS SIN IVA'!D39*('3- REND Y CONS'!D34*'5-PRECIOS SIN IVA'!D44*(1+'3- REND Y CONS'!D43)/2+'3- REND Y CONS'!D35*'5-PRECIOS SIN IVA'!D45*(1+'3- REND Y CONS'!D43)/2+'3- REND Y CONS'!D33*'5-PRECIOS SIN IVA'!D43*(1+'3- REND Y CONS'!D44)/2+'3- REND Y CONS'!D36*'5-PRECIOS SIN IVA'!D46)/'2- EMP. REP'!D5 -> 15.635365 | E36: =+'5-PRECIOS SIN IVA'!E39*('3- REND Y CONS'!E34*'5-PRECIOS SIN IVA'!E44*(1+'3- REND Y CONS'!E43)/2+'3- REND Y CONS'!E35*'5-PRECIOS SIN IVA'!E45*(1+'3- REND Y CONS'!E43)/2+'3- REND Y CONS'!E33*'5-PRECIOS SIN IVA'!E43*(1+'3- REND Y CONS'!E44)/2+'3- REND Y CONS'!E36*'5-PRECIOS SIN IVA'!E46)/'2- EMP. REP'!E5 -> 11.20058 | F36: =+'5-PRECIOS SIN IVA'!F39*('3- REND Y CONS'!F34*'5-PRECIOS SIN IVA'!F44*(1+'3- REND Y CONS'!F43)/2+'3- REND Y CONS'!F35*'5-PRECIOS SIN IVA'!F45*(1+'3- REND Y CONS'!F43)/2+'3- REND Y CONS'!F33*'5-PRECIOS SIN IVA'!F43*(1+'3- REND Y CONS'!F44)/2+'3- REND Y CONS'!F36*'5-PRECIOS SIN IVA'!F46)/'2- EMP. REP'!F5 -> 10.207048 | G36: =+'5-PRECIOS SIN IVA'!G39*('3- REND Y CONS'!G34*'5-PRECIOS SIN IVA'!G44*(1+'3- REND Y CONS'!G43)/2+'3- REND Y CONS'!G35*'5-PRECIOS SIN IVA'!G45*(1+'3- REND Y CONS'!G43)/2+'3- REND Y CONS'!G33*'5-PRECIOS SIN IVA'!G43*(1+'3- REND Y CONS'!G44)/2+'3- REND Y CONS'!G36*'5-PRECIOS SIN IVA'!G46)/'2- EMP. REP'!G5 -> 13.756297 | H36: =+'5-PRECIOS SIN IVA'!H39*('3- REND Y CONS'!H34*'5-PRECIOS SIN IVA'!H44*(1+'3- REND Y CONS'!H43)/2+'3- REND Y CONS'!H35*'5-PRECIOS SIN IVA'!H45*(1+'3- REND Y CONS'!H43)/2+'3- REND Y CONS'!H33*'5-PRECIOS SIN IVA'!H43*(1+'3- REND Y CONS'!H44)/2+'3- REND Y CONS'!H36*'5-PRECIOS SIN IVA'!H46)/'2- EMP. REP'!H5 -> 10.100919 | I36: =+'5-PRECIOS SIN IVA'!I39*('3- REND Y CONS'!I34*'5-PRECIOS SIN IVA'!I44*(1+'3- REND Y CONS'!I43)/2+'3- REND Y CONS'!I35*'5-PRECIOS SIN IVA'!I45*(1+'3- REND Y CONS'!I43)/2+'3- REND Y CONS'!I33*'5-PRECIOS SIN IVA'!I43*(1+'3- REND Y CONS'!I44)/2+'3- REND Y CONS'!I36*'5-PRECIOS SIN IVA'!I46)/'2- EMP. REP'!I5 -> 14.859149 | J36: =+'5-PRECIOS SIN IVA'!J39*('3- REND Y CONS'!J34*'5-PRECIOS SIN IVA'!J44*(1+'3- REND Y CONS'!J43)/2+'3- REND Y CONS'!J35*'5-PRECIOS SIN IVA'!J45*(1+'3- REND Y CONS'!J43)/2+'3- REND Y CONS'!J33*'5-PRECIOS SIN IVA'!J43*(1+'3- REND Y CONS'!J44)/2+'3- REND Y CONS'!J36*'5-PRECIOS SIN IVA'!J46)/'2- EMP. REP'!J5 -> 13.805545 | L36: =+A36 -> . Inmuebles | V36: =+A36 -> . Inmuebles | AF36: =+L36 -> . Inmuebles
A37: 14. LICENCIA NACIONAL HABILITANTE | B37: =+'4- PERSONAL'!B135*'4- PERSONAL'!B136*'4- PERSONAL'!B26/'2- EMP. REP'!B5 -> 0.60584807 | C37: =+'4- PERSONAL'!C135*'4- PERSONAL'!C136*'4- PERSONAL'!C26/'2- EMP. REP'!C5 -> 0.57584032 | D37: =+'4- PERSONAL'!D135*'4- PERSONAL'!D136*'4- PERSONAL'!D26/'2- EMP. REP'!D5 -> 0.43647396 | E37: =+'4- PERSONAL'!E135*'4- PERSONAL'!E136*'4- PERSONAL'!E26/'2- EMP. REP'!E5 -> 0.29590831 | F37: =+'4- PERSONAL'!F135*'4- PERSONAL'!F136*'4- PERSONAL'!F26/'2- EMP. REP'!F5 -> 0.38253908 | G37: =+'4- PERSONAL'!G135*'4- PERSONAL'!G136*'4- PERSONAL'!G26/'2- EMP. REP'!G5 -> 0.5155576 | H37: =+'4- PERSONAL'!H135*'4- PERSONAL'!H136*'4- PERSONAL'!H26/'2- EMP. REP'!H5 -> 0.37856159 | I37: =+'4- PERSONAL'!I135*'4- PERSONAL'!I136*'4- PERSONAL'!I26/'2- EMP. REP'!I5 -> 0.53943545 | J37: =+'4- PERSONAL'!J135*'4- PERSONAL'!J136*'4- PERSONAL'!J26/'2- EMP. REP'!J5 -> 0.50118619 | L37: =+A37 -> 14. LICENCIA NACIONAL HABILITANTE | M37: =+B37/B$51 -> 0.0001563169 | N37: =+C37/C$51 -> 0.00016634745 | O37: =+D37/D$51 -> 0.0001565415 | P37: =+E37/E$51 -> 0.00012580054 | Q37: =+F37/F$51 -> 0.00016092683 | R37: =+G37/G$51 -> 0.00016751036 | S37: =+H37/H$51 -> 0.0001529482 | T37: =+I37/I$51 -> 0.0001735308 | U37: =+J37/J$51 -> 0.00017014559 | V37: =+A37 -> 14. LICENCIA NACIONAL HABILITANTE | W37: =+B37/'[1]1-COSTO X KM'!B37-1 -> -0.036502875 | X37: =+C37/'[1]1-COSTO X KM'!C37-1 -> 0.13691237 | Y37: =+D37/'[1]1-COSTO X KM'!D37-1 -> 0.14591101 | Z37: =+E37/'[1]1-COSTO X KM'!E37-1 -> 0.066687284 | AA37: =+F37/'[1]1-COSTO X KM'!F37-1 -> 0.2326877 | AB37: =+G37/'[1]1-COSTO X KM'!G37-1 -> 0.00014639259 | AC37: =+H37/'[1]1-COSTO X KM'!H37-1 -> 0.10480638 | AD37: =+I37/'[1]1-COSTO X KM'!I37-1 -> 0.016550488 | AE37: =+J37/'[1]1-COSTO X KM'!J37-1 -> 0.045033677 | AF37: =+L37 -> 14. LICENCIA NACIONAL HABILITANTE | AG37: =+B37/'[2]1-COSTO X KM'!B37-1 -> -0.04386068 | AH37: =+C37/'[2]1-COSTO X KM'!C37-1 -> -0.0060871408 | AI37: =+D37/'[2]1-COSTO X KM'!D37-1 -> 0.004508955 | AJ37: =+E37/'[2]1-COSTO X KM'!E37-1 -> -0.056579246 | AK37: =+F37/'[2]1-COSTO X KM'!F37-1 -> 0.098510161 | AL37: =+G37/'[2]1-COSTO X KM'!G37-1 -> 0.0011873132 | AM37: =+H37/'[2]1-COSTO X KM'!H37-1 -> 0.066887625 | AN37: =+I37/'[2]1-COSTO X KM'!I37-1 -> 0.016863276 | AO37: =+J37/'[2]1-COSTO X KM'!J37-1 -> 0.050321748
A38: 15. CONTROL TECNICO DEL MATERIAL RODANTE | B38: =+'3- REND Y CONS'!B28*'5-PRECIOS SIN IVA'!B23/'2- EMP. REP'!B8 -> 8.4174351 | C38: =+'3- REND Y CONS'!C28*'5-PRECIOS SIN IVA'!C23/'2- EMP. REP'!C8 -> 7.7497557 | D38: =+'3- REND Y CONS'!D28*'5-PRECIOS SIN IVA'!D23/'2- EMP. REP'!D8 -> 5.8741399 | E38: =+'3- REND Y CONS'!E28*'5-PRECIOS SIN IVA'!E23/'2- EMP. REP'!E8 -> 3.8719299 | F38: =+'3- REND Y CONS'!F28*'5-PRECIOS SIN IVA'!F23/'2- EMP. REP'!F8 -> 5.1482751 | G38: =+'3- REND Y CONS'!G28*'5-PRECIOS SIN IVA'!G23/'2- EMP. REP'!G8 -> 6.9384608 | H38: =+'3- REND Y CONS'!H28*'5-PRECIOS SIN IVA'!H23/'2- EMP. REP'!H8 -> 5.0947455 | I38: =+'3- REND Y CONS'!I28*'5-PRECIOS SIN IVA'!I23/'2- EMP. REP'!I8 -> 7.494722 | J38: =+'3- REND Y CONS'!J28*'5-PRECIOS SIN IVA'!J23/'2- EMP. REP'!J8 -> 6.9633006 | L38: =+A38 -> 15. CONTROL TECNICO DEL MATERIAL RODANTE | M38: =+B38/B$51 -> 0.0021718107 | N38: =+C38/C$51 -> 0.0022387319 | O38: =+D38/D$51 -> 0.0021067618 | P38: =+E38/E$51 -> 0.0016460871 | Q38: =+F38/F$51 -> 0.0021657803 | R38: =+G38/G$51 -> 0.0022543825 | S38: =+H38/H$51 -> 0.0020584026 | T38: =+I38/I$51 -> 0.0024109745 | U38: =+J38/J$51 -> 0.0023639416 | V38: =+A38 -> 15. CONTROL TECNICO DEL MATERIAL RODANTE | W38: =+B38/'[1]1-COSTO X KM'!B38-1 -> 0.20194567 | X38: =+C38/'[1]1-COSTO X KM'!C38-1 -> 0.41821782 | Y38: =+D38/'[1]1-COSTO X KM'!D38-1 -> 0.429443 | Z38: =+E38/'[1]1-COSTO X KM'!E38-1 -> 0.33061694 | AA38: =+F38/'[1]1-COSTO X KM'!F38-1 -> 0.53769079 | AB38: =+G38/'[1]1-COSTO X KM'!G38-1 -> 0.24761194 | AC38: =+H38/'[1]1-COSTO X KM'!H38-1 -> 0.37816788 | AD38: =+I38/'[1]1-COSTO X KM'!I38-1 -> 0.2681288 | AE38: =+J38/'[1]1-COSTO X KM'!J38-1 -> 0.30366108 | AF38: =+L38 -> 15. CONTROL TECNICO DEL MATERIAL RODANTE | AG38: =+B38/'[2]1-COSTO X KM'!B38-1 -> 0.14763684 | AH38: =+C38/'[2]1-COSTO X KM'!C38-1 -> 0.19292491 | AI38: =+D38/'[2]1-COSTO X KM'!D38-1 -> 0.20564267 | AJ38: =+E38/'[2]1-COSTO X KM'!E38-1 -> 0.13232273 | AK38: =+F38/'[2]1-COSTO X KM'!F38-1 -> 0.31846582 | AL38: =+G38/'[2]1-COSTO X KM'!G38-1 -> 0.20165594 | AM38: =+H38/'[2]1-COSTO X KM'!H38-1 -> 0.28051148 | AN38: =+I38/'[2]1-COSTO X KM'!I38-1 -> 0.22052271 | AO38: =+J38/'[2]1-COSTO X KM'!J38-1 -> 0.26068231
A39: 16. A.C.TRANS | B39: =+'2- EMP. REP'!B6*'5-PRECIOS SIN IVA'!B38/('2- EMP. REP'!B5/12) -> 0.0076485773 | C39: =+'2- EMP. REP'!C6*'5-PRECIOS SIN IVA'!C38/('2- EMP. REP'!C5/12) -> 0.0070418845 | D39: =+'2- EMP. REP'!D6*'5-PRECIOS SIN IVA'!D38/('2- EMP. REP'!D5/12) -> 0.0053375895 | E39: =+'2- EMP. REP'!E6*'5-PRECIOS SIN IVA'!E38/('2- EMP. REP'!E5/12) -> 0.0035182635 | F39: =+'2- EMP. REP'!F6*'5-PRECIOS SIN IVA'!F38/('2- EMP. REP'!F5/12) -> 0.004678026 | G39: =+'2- EMP. REP'!G6*'5-PRECIOS SIN IVA'!G38/('2- EMP. REP'!G5/12) -> 0.0063046942 | H39: =+'2- EMP. REP'!H6*'5-PRECIOS SIN IVA'!H38/('2- EMP. REP'!H5/12) -> 0.0046293858 | I39: =+'2- EMP. REP'!I6*'5-PRECIOS SIN IVA'!I38/('2- EMP. REP'!I5/12) -> 0.0068101459 | J39: =+'2- EMP. REP'!J6*'5-PRECIOS SIN IVA'!J38/('2- EMP. REP'!J5/12) -> 0.0063272651 | L39: =+A39 -> 16. A.C.TRANS | M39: =+B39/B$51 -> 1.9734352e-06 | N39: =+C39/C$51 -> 2.0342437e-06 | O39: =+D39/D$51 -> 1.9143279e-06 | P39: =+E39/E$51 -> 1.4957317e-06 | Q39: =+F39/F$51 -> 1.9679555e-06 | R39: =+G39/G$51 -> 2.0484648e-06 | S39: =+H39/H$51 -> 1.8703858e-06 | T39: =+I39/I$51 -> 2.1907534e-06 | U39: =+J39/J$51 -> 2.1480166e-06 | V39: =+A39 -> 16. A.C.TRANS | W39: =+B39/'[1]1-COSTO X KM'!B39-1 -> -0.036461882 | X39: =+C39/'[1]1-COSTO X KM'!C39-1 -> 0.1369124 | Y39: =+D39/'[1]1-COSTO X KM'!D39-1 -> 0.14591105 | Z39: =+E39/'[1]1-COSTO X KM'!E39-1 -> 0.066687269 | AA39: =+F39/'[1]1-COSTO X KM'!F39-1 -> 0.23268774 | AB39: =+G39/'[1]1-COSTO X KM'!G39-1 -> 0.00014642168 | AC39: =+H39/'[1]1-COSTO X KM'!H39-1 -> 0.10480641 | AD39: =+I39/'[1]1-COSTO X KM'!I39-1 -> 0.016593738 | AE39: =+J39/'[1]1-COSTO X KM'!J39-1 -> 0.04507814 | AF39: =+L39 -> 16. A.C.TRANS | AG39: =+B39/'[2]1-COSTO X KM'!B39-1 -> -0.043819942 | AH39: =+C39/'[2]1-COSTO X KM'!C39-1 -> -0.0060871408 | AI39: =+D39/'[2]1-COSTO X KM'!D39-1 -> 0.004508955 | AJ39: =+E39/'[2]1-COSTO X KM'!E39-1 -> -0.056579246 | AK39: =+F39/'[2]1-COSTO X KM'!F39-1 -> 0.098510161 | AL39: =+G39/'[2]1-COSTO X KM'!G39-1 -> 0.0011873132 | AM39: =+H39/'[2]1-COSTO X KM'!H39-1 -> 0.066887625 | AN39: =+I39/'[2]1-COSTO X KM'!I39-1 -> 0.016906601 | AO39: =+J39/'[2]1-COSTO X KM'!J39-1 -> 0.050366499
A40: 17. PEAJES | B40: 0 | C40: 0 | D40: 0 | E40: 0.173 | F40: 0.014 | G40: 0 | H40: 0 | I40: 0 | J40: 0 | L40: =+A40 -> 17. PEAJES | M40: =+B40/B$51 -> 0 | N40: =+C40/C$51 -> 0 | O40: =+D40/D$51 -> 0 | P40: =+E40/E$51 -> 7.3548096e-05 | Q40: =+F40/F$51 -> 5.8895306e-06 | R40: =+G40/G$51 -> 0 | S40: =+H40/H$51 -> 0 | T40: =+I40/I$51 -> 0 | U40: =+J40/J$51 -> 0 | V40: =+A40 -> 17. PEAJES | Z40: =+E40/'[1]1-COSTO X KM'!E40-1 -> 0 | AA40: =+F40/'[1]1-COSTO X KM'!F40-1 -> 0 | AF40: =+L40 -> 17. PEAJES | AG40: =+B40/'[2]1-COSTO X KM'!B40-1 -> #DIV/0! | AH40: =+C40/'[2]1-COSTO X KM'!C40-1 -> #DIV/0! | AI40: =+D40/'[2]1-COSTO X KM'!D40-1 -> #DIV/0! | AJ40: =+E40/'[2]1-COSTO X KM'!E40-1 -> 0 | AK40: =+F40/'[2]1-COSTO X KM'!F40-1 -> 0 | AL40: =+G40/'[2]1-COSTO X KM'!G40-1 -> #DIV/0! | AM40: =+H40/'[2]1-COSTO X KM'!H40-1 -> #DIV/0! | AN40: =+I40/'[2]1-COSTO X KM'!I40-1 -> #DIV/0! | AO40: =+J40/'[2]1-COSTO X KM'!J40-1 -> #DIV/0!
A41: 18. SERVICIO DE VIGILANCIA | B41: =+'4- PERSONAL'!B157/'2- EMP. REP'!B5 -> 1.310824 | C41: =+'4- PERSONAL'!C157/'2- EMP. REP'!C5 -> 0.97205068 | D41: =+'4- PERSONAL'!D157/'2- EMP. REP'!D5 -> 0.27563327 | E41: =+'4- PERSONAL'!E157/'2- EMP. REP'!E5 -> 0.349927 | F41: =+'4- PERSONAL'!F157/'2- EMP. REP'!F5 -> 2.4129491 | G41: =+'4- PERSONAL'!G157/'2- EMP. REP'!G5 -> 1.4658827 | H41: =+'4- PERSONAL'!H157/'2- EMP. REP'!H5 -> 0.92048564 | I41: =+'4- PERSONAL'!I157/'2- EMP. REP'!I5 -> 1.8768011 | J41: =+'4- PERSONAL'!J157/'2- EMP. REP'!J5 -> 2.8832178 | L41: =+A41 -> 18. SERVICIO DE VIGILANCIA | M41: =+B41/B$51 -> 0.00033821012 | N41: =+C41/C$51 -> 0.0002808038 | O41: =+D41/D$51 -> 9.8855948e-05 | P41: =+E41/E$51 -> 0.00014876569 | Q41: =+F41/F$51 -> 0.0010150813 | R41: =+G41/G$51 -> 0.00047628147 | S41: =+H41/H$51 -> 0.00037189886 | T41: =+I41/I$51 -> 0.00060374748 | U41: =+J41/J$51 -> 0.00097881146 | V41: =+A41 -> 18. SERVICIO DE VIGILANCIA | W41: =+B41/'[1]1-COSTO X KM'!B41-1 -> 0.0035587425 | X41: =+C41/'[1]1-COSTO X KM'!C41-1 -> 0.11435835 | Y41: =+D41/'[1]1-COSTO X KM'!D41-1 -> 0.099754232 | Z41: =+E41/'[1]1-COSTO X KM'!E41-1 -> 0.090009372 | AA41: =+F41/'[1]1-COSTO X KM'!F41-1 -> 0.22931983 | AB41: =+G41/'[1]1-COSTO X KM'!G41-1 -> -0.036954515 | AC41: =+H41/'[1]1-COSTO X KM'!H41-1 -> -0.0016885325 | AD41: =+I41/'[1]1-COSTO X KM'!I41-1 -> -0.023732587 | AE41: =+J41/'[1]1-COSTO X KM'!J41-1 -> -0.040805999 | AF41: =+L41 -> 18. SERVICIO DE VIGILANCIA | AG41: =+B41/'[2]1-COSTO X KM'!B41-1 -> -0.07466446 | AH41: =+C41/'[2]1-COSTO X KM'!C41-1 -> -0.023135336 | AI41: =+D41/'[2]1-COSTO X KM'!D41-1 -> -0.033311016 | AJ41: =+E41/'[2]1-COSTO X KM'!E41-1 -> -0.033311021 | AK41: =+F41/'[2]1-COSTO X KM'!F41-1 -> 0.098510244 | AL41: =+G41/'[2]1-COSTO X KM'!G41-1 -> -0.033311009 | AM41: =+H41/'[2]1-COSTO X KM'!H41-1 -> -0.033311012 | AN41: =+I41/'[2]1-COSTO X KM'!I41-1 -> -0.020756607 | AO41: =+J41/'[2]1-COSTO X KM'!J41-1 -> -0.033311009
A42: 19. CAMARAS DE SEGURIDAD | B42: =+'5-PRECIOS SIN IVA'!B50/('2- EMP. REP'!B8) -> 0 | C42: =+'5-PRECIOS SIN IVA'!C50/('2- EMP. REP'!C8*10) -> 0 | D42: =+'5-PRECIOS SIN IVA'!D50/('2- EMP. REP'!D8*10) -> 0 | E42: =+'5-PRECIOS SIN IVA'!E50/('2- EMP. REP'!E8*10) -> 0 | F42: =+'5-PRECIOS SIN IVA'!F50/('2- EMP. REP'!F8*10) -> 0 | G42: =+'5-PRECIOS SIN IVA'!G50/('2- EMP. REP'!G8*10) -> 3.4922856 | H42: =+'5-PRECIOS SIN IVA'!H50/('2- EMP. REP'!H8*10) -> 2.5643016 | I42: =+'5-PRECIOS SIN IVA'!I50/('2- EMP. REP'!I8*10) -> 3.7722646 | J42: =+'5-PRECIOS SIN IVA'!J50/('2- EMP. REP'!J8*10) -> 3.5047881 | L42: =+A42 -> 19. CAMARAS DE SEGURIDAD | M42: =+B42/B$51 -> 0 | N42: =+C42/C$51 -> 0 | O42: =+D42/D$51 -> 0 | P42: =+E42/E$51 -> 0 | Q42: =+F42/F$51 -> 0 | R42: =+G42/G$51 -> 0.0011346822 | S42: =+H42/H$51 -> 0.001036041 | T42: =+I42/I$51 -> 0.0012134985 | U42: =+J42/J$51 -> 0.0011898257 | V42: =+A42 -> 19. CAMARAS DE SEGURIDAD | AB42: =+G42/'[1]1-COSTO X KM'!G42-1 -> 0.00014642168 | AC42: =+H42/'[1]1-COSTO X KM'!H42-1 -> 0.10480641 | AD42: =+I42/'[1]1-COSTO X KM'!I42-1 -> 0.016593738 | AE42: =+J42/'[1]1-COSTO X KM'!J42-1 -> 0.04507814 | AF42: =+L42 -> 19. CAMARAS DE SEGURIDAD | AG42: =+B42/'[2]1-COSTO X KM'!B42-1 -> -1 | AH42: =+C42/'[2]1-COSTO X KM'!C42-1 -> #DIV/0! | AI42: =+D42/'[2]1-COSTO X KM'!D42-1 -> #DIV/0! | AJ42: =+E42/'[2]1-COSTO X KM'!E42-1 -> #DIV/0! | AK42: =+F42/'[2]1-COSTO X KM'!F42-1 -> #DIV/0! | AL42: =+G42/'[2]1-COSTO X KM'!G42-1 -> 0.0011873132 | AM42: =+H42/'[2]1-COSTO X KM'!H42-1 -> 0.066887625 | AN42: =+I42/'[2]1-COSTO X KM'!I42-1 -> 0.016906601 | AO42: =+J42/'[2]1-COSTO X KM'!J42-1 -> 0.050366499
A43: SUBTOTAL SIN GASTOS GENERALES | B43: =+B4+B5+B6+B7+B8+B11+B14+B19+B20+B25+B26+B31+B32+B37+B38+B39+B40+B41+B42 -> 3528.2961 | C43: =+C4+C5+C6+C7+C8+C11+C14+C19+C20+C25+C26+C31+C32+C37+C38+C39+C40+C41+C42 -> 3146.8554 | D43: =+D4+D5+D6+D7+D8+D11+D14+D19+D20+D25+D26+D31+D32+D37+D38+D39+D40+D41+D42 -> 2531.2696 | E43: =+E4+E5+E6+E7+E8+E11+E14+E19+E20+E25+E26+E31+E32+E37+E38+E39+E40+E41+E42 -> 2126.7231 | F43: =+F4+F5+F6+F7+F8+F11+F14+F19+F20+F25+F26+F31+F32+F37+F38+F39+F40+F41+F42 -> 2147.5001 | G43: =+G4+G5+G6+G7+G8+G11+G14+G19+G20+G25+G26+G31+G32+G37+G38+G39+G40+G41+G42 -> 2793.5952 | H43: =+H4+H5+H6+H7+H8+H11+H14+H19+H20+H25+H26+H31+H32+H37+H38+H39+H40+H41+H42 -> 2242.2861 | I43: =+I4+I5+I6+I7+I8+I11+I14+I19+I20+I25+I26+I31+I32+I37+I38+I39+I40+I41+I42 -> 2821.6797 | J43: =+J4+J5+J6+J7+J8+J11+J14+J19+J20+J25+J26+J31+J32+J37+J38+J39+J40+J41+J42 -> 2673.5533 | L43: =+A43 -> SUBTOTAL SIN GASTOS GENERALES | V43: =+A43 -> SUBTOTAL SIN GASTOS GENERALES | AF43: =+L43 -> SUBTOTAL SIN GASTOS GENERALES
A44: 20. GASTOS GENERALES | B44: =+'5-PRECIOS SIN IVA'!B58*'1-COSTO X KM'!B43/(1-'5-PRECIOS SIN IVA'!B58) -> 109.12256 | C44: =+'5-PRECIOS SIN IVA'!C58*'1-COSTO X KM'!C43/(1-'5-PRECIOS SIN IVA'!C58) -> 97.325426 | D44: =+'5-PRECIOS SIN IVA'!D58*'1-COSTO X KM'!D43/(1-'5-PRECIOS SIN IVA'!D58) -> 78.286689 | E44: =+'5-PRECIOS SIN IVA'!E58*'1-COSTO X KM'!E43/(1-'5-PRECIOS SIN IVA'!E58) -> 65.774943 | F44: =+'5-PRECIOS SIN IVA'!F58*'1-COSTO X KM'!F43/(1-'5-PRECIOS SIN IVA'!F58) -> 66.417528 | G44: =+'5-PRECIOS SIN IVA'!G58*'1-COSTO X KM'!G43/(1-'5-PRECIOS SIN IVA'!G58) -> 86.39985 | H44: =+'5-PRECIOS SIN IVA'!H58*'1-COSTO X KM'!H43/(1-'5-PRECIOS SIN IVA'!H58) -> 69.349055 | I44: =+'5-PRECIOS SIN IVA'!I58*'1-COSTO X KM'!I43/(1-'5-PRECIOS SIN IVA'!I58) -> 87.268446 | J44: =+'5-PRECIOS SIN IVA'!J58*'1-COSTO X KM'!J43/(1-'5-PRECIOS SIN IVA'!J58) -> 82.687214 | L44: =+A44 -> 20. GASTOS GENERALES | M44: =+B44/B$51 -> 0.028155079 | N44: =+C44/C$51 -> 0.028115149 | O44: =+D44/D$51 -> 0.028077542 | P44: =+E44/E$51 -> 0.027963132 | Q44: =+F44/F$51 -> 0.027940576 | R44: =+G44/G$51 -> 0.028072266 | S44: =+H44/H$51 -> 0.028018725 | T44: =+I44/I$51 -> 0.028073355 | U44: =+J44/J$51 -> 0.028071134 | V44: =+A44 -> 20. GASTOS GENERALES | W44: =+B44/'[1]1-COSTO X KM'!B44-1 -> 0.41244027 | X44: =+C44/'[1]1-COSTO X KM'!C44-1 -> 0.49043111 | Y44: =+D44/'[1]1-COSTO X KM'!D44-1 -> 0.49274722 | Z44: =+E44/'[1]1-COSTO X KM'!E44-1 -> 0.43255219 | AA44: =+F44/'[1]1-COSTO X KM'!F44-1 -> 0.51025183 | AB44: =+G44/'[1]1-COSTO X KM'!G44-1 -> 0.36650434 | AC44: =+H44/'[1]1-COSTO X KM'!H44-1 -> 0.45571078 | AD44: =+I44/'[1]1-COSTO X KM'!I44-1 -> 0.35201427 | AE44: =+J44/'[1]1-COSTO X KM'!J44-1 -> 0.40805179 | AF44: =+L44 -> 20. GASTOS GENERALES | AG44: =+B44/'[2]1-COSTO X KM'!B44-1 -> 0.2367885 | AH44: =+C44/'[2]1-COSTO X KM'!C44-1 -> 0.22768019 | AI44: =+D44/'[2]1-COSTO X KM'!D44-1 -> 0.23715047 | AJ44: =+E44/'[2]1-COSTO X KM'!E44-1 -> 0.19989368 | AK44: =+F44/'[2]1-COSTO X KM'!F44-1 -> 0.31763256 | AL44: =+G44/'[2]1-COSTO X KM'!G44-1 -> 0.23334085 | AM44: =+H44/'[2]1-COSTO X KM'!H44-1 -> 0.28561722 | AN44: =+I44/'[2]1-COSTO X KM'!I44-1 -> 0.23413588 | AO44: =+J44/'[2]1-COSTO X KM'!J44-1 -> 0.27452367
A45: COSTO TOTAL SIN IMPUESTOS | B45: =+B44+B43 -> 3637.4186 | C45: =+C44+C43 -> 3244.1809 | D45: =+D44+D43 -> 2609.5563 | E45: =+E44+E43 -> 2192.4981 | F45: =+F44+F43 -> 2213.9176 | G45: =+G44+G43 -> 2879.995 | H45: =+H44+H43 -> 2311.6352 | I45: =+I44+I43 -> 2908.9482 | J45: =+J44+J43 -> 2756.2405 | L45: =+A45 -> COSTO TOTAL SIN IMPUESTOS | V45: =+A45 -> COSTO TOTAL SIN IMPUESTOS | AF45: =+L45 -> COSTO TOTAL SIN IMPUESTOS
A46: 21. IMPUESTOS NACIONALES Y COMPENSACIONES | B46: =SUM(B47) -> 43.649024 | C46: =SUM(C47) -> 38.93017 | D46: =SUM(D47) -> 31.314676 | E46: =SUM(E47) -> 26.309977 | F46: =SUM(F47) -> 26.567011 | G46: =SUM(G47) -> 34.55994 | H46: =SUM(H47) -> 27.739622 | I46: =SUM(I47) -> 34.907378 | J46: =SUM(J47) -> 33.074886 | L46: =+A46 -> 21. IMPUESTOS NACIONALES Y COMPENSACIONES | M46: =+B46/B$51 -> 0.011262031 | N46: =+C46/C$51 -> 0.01124606 | O46: =+D46/D$51 -> 0.011231017 | P46: =+E46/E$51 -> 0.011185253 | Q46: =+F46/F$51 -> 0.01117623 | R46: =+G46/G$51 -> 0.011228906 | S46: =+H46/H$51 -> 0.01120749 | T46: =+I46/I$51 -> 0.011229342 | U46: =+J46/J$51 -> 0.011228454 | V46: =+A46 -> 21. IMPUESTOS NACIONALES Y COMPENSACIONES | W46: =+B46/'[1]1-COSTO X KM'!B46-1 -> 0.41244027 | X46: =+C46/'[1]1-COSTO X KM'!C46-1 -> 0.49043111 | Y46: =+D46/'[1]1-COSTO X KM'!D46-1 -> 0.49274722 | Z46: =+E46/'[1]1-COSTO X KM'!E46-1 -> 0.43255219 | AA46: =+F46/'[1]1-COSTO X KM'!F46-1 -> 0.51025183 | AB46: =+G46/'[1]1-COSTO X KM'!G46-1 -> 0.36650434 | AC46: =+H46/'[1]1-COSTO X KM'!H46-1 -> 0.45571078 | AD46: =+I46/'[1]1-COSTO X KM'!I46-1 -> 0.35201427 | AE46: =+J46/'[1]1-COSTO X KM'!J46-1 -> 0.40805179 | AF46: =+L46 -> 21. IMPUESTOS NACIONALES Y COMPENSACIONES | AG46: =+B46/'[2]1-COSTO X KM'!B46-1 -> 0.2367885 | AH46: =+C46/'[2]1-COSTO X KM'!C46-1 -> 0.22768019 | AI46: =+D46/'[2]1-COSTO X KM'!D46-1 -> 0.23715047 | AJ46: =+E46/'[2]1-COSTO X KM'!E46-1 -> 0.19989368 | AK46: =+F46/'[2]1-COSTO X KM'!F46-1 -> 0.31763256 | AL46: =+G46/'[2]1-COSTO X KM'!G46-1 -> 0.23334085 | AM46: =+H46/'[2]1-COSTO X KM'!H46-1 -> 0.28561722 | AN46: =+I46/'[2]1-COSTO X KM'!I46-1 -> 0.23413588 | AO46: =+J46/'[2]1-COSTO X KM'!J46-1 -> 0.27452367
A47: Impuesto al cheque | B47: =+'6- IMPUESTOS'!B3+'6- IMPUESTOS'!B4 -> 43.649024 | C47: =+'6- IMPUESTOS'!C3+'6- IMPUESTOS'!C4 -> 38.93017 | D47: =+'6- IMPUESTOS'!D3+'6- IMPUESTOS'!D4 -> 31.314676 | E47: =+'6- IMPUESTOS'!E3+'6- IMPUESTOS'!E4 -> 26.309977 | F47: =+'6- IMPUESTOS'!F3+'6- IMPUESTOS'!F4 -> 26.567011 | G47: =+'6- IMPUESTOS'!G3+'6- IMPUESTOS'!G4 -> 34.55994 | H47: =+'6- IMPUESTOS'!H3+'6- IMPUESTOS'!H4 -> 27.739622 | I47: =+'6- IMPUESTOS'!I3+'6- IMPUESTOS'!I4 -> 34.907378 | J47: =+'6- IMPUESTOS'!J3+'6- IMPUESTOS'!J4 -> 33.074886 | L47: =+A47 -> Impuesto al cheque | V47: =+A47 -> Impuesto al cheque | AF47: =+L47 -> Impuesto al cheque
A48: 22. IMPUESTO A LOS INGRESOS BRUTOS | B48: =(+'5-PRECIOS SIN IVA'!B47*'2- EMP. REP'!B13/1.105)-(0.1*'8- COSTO COMBUST'!$B$11+0.9*'8- COSTO COMBUST'!B11)*'8- COSTO COMBUST'!B16 -> -7.3826519 | C48: =(+'5-PRECIOS SIN IVA'!C47*'2- EMP. REP'!C13/1.105)-(0.1*'8- COSTO COMBUST'!$D$11+0.9*'8- COSTO COMBUST'!E11)*'8- COSTO COMBUST'!E16 -> -3.3910061 | D48: =(+'5-PRECIOS SIN IVA'!D47*'2- EMP. REP'!D13/1.105)-(0.1*'8- COSTO COMBUST'!$D$11+0.9*'8- COSTO COMBUST'!F11)*'8- COSTO COMBUST'!F16 -> -4.8662761 | E48: =(+'5-PRECIOS SIN IVA'!E47*'2- EMP. REP'!E13/1.105)-(0.1*'8- COSTO COMBUST'!$D$11+0.9*'8- COSTO COMBUST'!G11)*'8- COSTO COMBUST'!G16 -> -0.17023915 | F48: =(+'5-PRECIOS SIN IVA'!F47*'2- EMP. REP'!F13/1.105)-(0.1*'8- COSTO COMBUST'!$D$11+0.9*'8- COSTO COMBUST'!H11)*'8- COSTO COMBUST'!H16 -> 18.368135 | G48: =(+'5-PRECIOS SIN IVA'!G47*'2- EMP. REP'!G13/1.105)-(0.1*'8- COSTO COMBUST'!$D$11+0.9*'8- COSTO COMBUST'!I11)*'8- COSTO COMBUST'!I16 -> 3.6153127 | H48: =(+'5-PRECIOS SIN IVA'!H47*'2- EMP. REP'!H13/1.105)-(0.1*'8- COSTO COMBUST'!$D$11+0.9*'8- COSTO COMBUST'!J11)*'8- COSTO COMBUST'!J16 -> 0.57517387 | I48: =(+'5-PRECIOS SIN IVA'!I47*'2- EMP. REP'!I13/1.105)-(0.1*'8- COSTO COMBUST'!$D$11+0.9*'8- COSTO COMBUST'!K11)*'8- COSTO COMBUST'!K16 -> 4.6446846 | J48: =(+'5-PRECIOS SIN IVA'!J47*'2- EMP. REP'!J13/1.105)-(0.1*'8- COSTO COMBUST'!$D$11+0.9*'8- COSTO COMBUST'!L11)*'8- COSTO COMBUST'!L16 -> 2.2167248 | L48: =+A48 -> 22. IMPUESTO A LOS INGRESOS BRUTOS | M48: =+B48/B$51 -> -0.0019048229 | N48: =+C48/C$51 -> -0.00097958618 | O48: =+D48/D$51 -> -0.0017452912 | P48: =+E48/E$51 -> -7.2374365e-05 | Q48: =+F48/F$51 -> 0.0077271209 | R48: =+G48/G$51 -> 0.001174655 | S48: =+H48/H$51 -> 0.0002323844 | T48: =+I48/I$51 -> 0.001494147 | U48: =+J48/J$51 -> 0.00075254658 | V48: =+A48 -> 22. IMPUESTO A LOS INGRESOS BRUTOS | W48: =+B48/'[1]1-COSTO X KM'!B48-1 -> 0.86420619 | X48: =+C48/'[1]1-COSTO X KM'!C48-1 -> 0.41688393 | Y48: =+D48/'[1]1-COSTO X KM'!D48-1 -> 0.30567922 | Z48: =+E48/'[1]1-COSTO X KM'!E48-1 -> -0.6224931 | AA48: =+F48/'[1]1-COSTO X KM'!F48-1 -> 1.0273018 | AB48: =+G48/'[1]1-COSTO X KM'!G48-1 -> -0.20759799 | AC48: =+H48/'[1]1-COSTO X KM'!H48-1 -> -0.63575601 | AD48: =+I48/'[1]1-COSTO X KM'!I48-1 -> -0.20750404 | AE48: =+J48/'[1]1-COSTO X KM'!J48-1 -> -0.45898931 | AF48: =+L48 -> 22. IMPUESTO A LOS INGRESOS BRUTOS | AG48: =+B48/'[2]1-COSTO X KM'!B48-1 -> 0.6199831 | AH48: =+C48/'[2]1-COSTO X KM'!C48-1 -> -0.090171165 | AI48: =+D48/'[2]1-COSTO X KM'!D48-1 -> -0.021919099 | AJ48: =+E48/'[2]1-COSTO X KM'!E48-1 -> -0.89226147 | AK48: =+F48/'[2]1-COSTO X KM'!F48-1 -> 1.233965 | AL48: =+G48/'[2]1-COSTO X KM'!G48-1 -> 2.9935961 | AM48: =+H48/'[2]1-COSTO X KM'!H48-1 -> -1.4892765 | AN48: =+I48/'[2]1-COSTO X KM'!I48-1 -> 1.7701407 | AO48: =+J48/'[2]1-COSTO X KM'!J48-1 -> 170.92653
A49: 23. Costo de gerenciamiento | B49: =+(B$4+B$5+B$6+B$7+B$8+B$14+B$19+B$27+B$39+B$29+B$31+B$37+B$38+B$40+B$41+B$42+B$44)*('5-PRECIOS SIN IVA'!B41)+(+B$20+B$25)*('5-PRECIOS SIN IVA'!B42) -> 187.90498 | C49: =+(C$4+C$5+C$6+C$7+C$8+C$14+C$19+C$27+C$39+C$29+C$31+C$37+C$38+C$40+C$41+C$42+C$44)*('5-PRECIOS SIN IVA'!C41)+(+C$20+C$25)*('5-PRECIOS SIN IVA'!C42) -> 168.50315 | D49: =+(D$4+D$5+D$6+D$7+D$8+D$14+D$19+D$27+D$39+D$29+D$31+D$37+D$38+D$40+D$41+D$42+D$44)*('5-PRECIOS SIN IVA'!D41)+(+D$20+D$25)*('5-PRECIOS SIN IVA'!D42) -> 139.97396 | E49: =+(E$4+E$5+E$6+E$7+E$8+E$14+E$19+E$27+E$39+E$29+E$31+E$37+E$38+E$40+E$41+E$42+E$44)*('5-PRECIOS SIN IVA'!E41)+(+E$20+E$25)*('5-PRECIOS SIN IVA'!E42) -> 123.07201 | F49: =+(F$4+F$5+F$6+F$7+F$8+F$14+F$19+F$27+F$39+F$29+F$31+F$37+F$38+F$40+F$41+F$42+F$44)*('5-PRECIOS SIN IVA'!F41)+(+F$20+F$25)*('5-PRECIOS SIN IVA'!F42) -> 116.30247 | G49: =+(G$4+G$5+G$6+G$7+G$8+G$14+G$19+G$27+G$39+G$29+G$31+G$37+G$38+G$40+G$41+G$42+G$44)*('5-PRECIOS SIN IVA'!G41)+(+G$20+G$25)*('5-PRECIOS SIN IVA'!G42) -> 149.01785 | H49: =+(H$4+H$5+H$6+H$7+H$8+H$14+H$19+H$27+H$39+H$29+H$31+H$37+H$38+H$40+H$41+H$42+H$44)*('5-PRECIOS SIN IVA'!H41)+(+H$20+H$25)*('5-PRECIOS SIN IVA'!H42) -> 125.11362 | I49: =+(I$4+I$5+I$6+I$7+I$8+I$14+I$19+I$27+I$39+I$29+I$31+I$37+I$38+I$40+I$41+I$42+I$44)*('5-PRECIOS SIN IVA'!I41)+(+I$20+I$25)*('5-PRECIOS SIN IVA'!I42) -> 150.17268 | J49: =+(J$4+J$5+J$6+J$7+J$8+J$14+J$19+J$27+J$39+J$29+J$31+J$37+J$38+J$40+J$41+J$42+J$44)*('5-PRECIOS SIN IVA'!J41)+(+J$20+J$25)*('5-PRECIOS SIN IVA'!J42) -> 143.64195 | L49: =+A49 -> 23. Costo de gerenciamiento | M49: =+B49/B$51 -> 0.048481997 | N49: =+C49/C$51 -> 0.04867681 | O49: =+D49/D$51 -> 0.050201698 | P49: =+E49/E$51 -> 0.052322035 | Q49: =+F49/F$51 -> 0.048926209 | R49: =+G49/G$51 -> 0.048417545 | S49: =+H49/H$51 -> 0.050548983 | T49: =+I49/I$51 -> 0.048308995 | U49: =+J49/J$51 -> 0.0487644 | V49: =+A49 -> 23. Costo de gerenciamiento | W49: =+B49/'[1]1-COSTO X KM'!B49-1 -> 0.41217673 | X49: =+C49/'[1]1-COSTO X KM'!C49-1 -> 0.4518903 | Y49: =+D49/'[1]1-COSTO X KM'!D49-1 -> 0.44929982 | Z49: =+E49/'[1]1-COSTO X KM'!E49-1 -> 0.41448432 | AA49: =+F49/'[1]1-COSTO X KM'!F49-1 -> 0.46639523 | AB49: =+G49/'[1]1-COSTO X KM'!G49-1 -> 0.35206382 | AC49: =+H49/'[1]1-COSTO X KM'!H49-1 -> 0.41999885 | AD49: =+I49/'[1]1-COSTO X KM'!I49-1 -> 0.34128916 | AE49: =+J49/'[1]1-COSTO X KM'!J49-1 -> 0.38533877 | AF49: =+L49 -> 23. Costo de gerenciamiento | AG49: =+B49/'[2]1-COSTO X KM'!B49-1 -> 0.26322941 | AH49: =+C49/'[2]1-COSTO X KM'!C49-1 -> 0.22144272 | AI49: =+D49/'[2]1-COSTO X KM'!D49-1 -> 0.22865677 | AJ49: =+E49/'[2]1-COSTO X KM'!E49-1 -> 0.20453618 | AK49: =+F49/'[2]1-COSTO X KM'!F49-1 -> 0.29324344 | AL49: =+G49/'[2]1-COSTO X KM'!G49-1 -> 0.22623568 | AM49: =+H49/'[2]1-COSTO X KM'!H49-1 -> 0.26630106 | AN49: =+I49/'[2]1-COSTO X KM'!I49-1 -> 0.22753071 | AO49: =+J49/'[2]1-COSTO X KM'!J49-1 -> 0.25973173
A50: 24. Saldo Técnico a Favor IVA | B50: =+'5.A SALDO A FAVOR IVA'!D8 -> 14.178225 | C50: =+'5.A SALDO A FAVOR IVA'!E8 -> 13.448899 | D50: =+'5.A SALDO A FAVOR IVA'!F8 -> 12.252906 | E50: =+'5.A SALDO A FAVOR IVA'!G8 -> 10.492457 | F50: =+'5.A SALDO A FAVOR IVA'!H8 -> 1.9442437 | G50: =+'5.A SALDO A FAVOR IVA'!I8 -> 10.577387 | H50: =+'5.A SALDO A FAVOR IVA'!J8 -> 10.033136 | I50: =+'5.A SALDO A FAVOR IVA'!K8 -> 9.9132817 | J50: =+'5.A SALDO A FAVOR IVA'!L8 -> 10.457359 | L50: =+A50 -> 24. Saldo Técnico a Favor IVA | M50: =+B50/B$51 -> 0.0036581717 | N50: =+C50/C$51 -> 0.0038850875 | O50: =+D50/D$51 -> 0.0043945081 | P50: =+E50/E$51 -> 0.004460695 | Q50: =+F50/F$51 -> 0.00081790591 | R50: =+G50/G$51 -> 0.0034367099 | S50: =+H50/H$51 -> 0.0040536341 | T50: =+I50/I$51 -> 0.0031890001 | U50: =+J50/J$51 -> 0.0035501247 | V50: =+A50 -> 24. Saldo Técnico a Favor IVA | W50: =+B50/'[1]1-COSTO X KM'!B50-1 -> 0.60108965 | X50: =+C50/'[1]1-COSTO X KM'!C50-1 -> 0.56963589 | Y50: =+D50/'[1]1-COSTO X KM'!D50-1 -> 0.51984882 | Z50: =+E50/'[1]1-COSTO X KM'!E50-1 -> 0.50510356 | AA50: =+F50/'[1]1-COSTO X KM'!F50-1 -> -0.14987782 | AB50: =+G50/'[1]1-COSTO X KM'!G50-1 -> 0.63210947 | AC50: =+H50/'[1]1-COSTO X KM'!H50-1 -> 0.63636878 | AD50: =+I50/'[1]1-COSTO X KM'!I50-1 -> 0.7235221 | AE50: =+J50/'[1]1-COSTO X KM'!J50-1 -> 0.73254634 | AF50: =+L50 -> 24. Saldo Técnico a Favor IVA | AG50: =+B50/'[2]1-COSTO X KM'!B50-1 -> 0.35064154 | AH50: =+C50/'[2]1-COSTO X KM'!C50-1 -> 0.22235286 | AI50: =+D50/'[2]1-COSTO X KM'!D50-1 -> 0.2118057 | AJ50: =+E50/'[2]1-COSTO X KM'!E50-1 -> 0.15405348 | AK50: =+F50/'[2]1-COSTO X KM'!F50-1 -> -0.47965628 | AL50: =+G50/'[2]1-COSTO X KM'!G50-1 -> 0.17208445 | AM50: =+H50/'[2]1-COSTO X KM'!H50-1 -> 0.21167187 | AN50: =+I50/'[2]1-COSTO X KM'!I50-1 -> 0.16983319 | AO50: =+J50/'[2]1-COSTO X KM'!J50-1 -> 0.20747047
A51: COSTO TOTAL POR KILOMETRO SIN IVA | B51: =+B45+B46+B48+B49+B50 -> 3875.7682 | C51: =+C45+C46+C48+C49+C50 -> 3461.6721 | D51: =+D45+D46+D48+D49+D50 -> 2788.2316 | E51: =+E45+E46+E48+E49+E50 -> 2352.2023 | F51: =+F45+F46+F48+F49+F50 -> 2377.0995 | G51: =+G45+G46+G48+G49+G50 -> 3077.7655 | H51: =+H45+H46+H48+H49+H50 -> 2475.0967 | I51: =+I45+I46+I48+I49+I50 -> 3108.5862 | J51: =+J45+J46+J48+J49+J50 -> 2945.6314 | L51: =+A51 -> COSTO TOTAL POR KILOMETRO SIN IVA | M51: =SUM(M4:M50) -> 1 | N51: =SUM(N4:N50) -> 1 | O51: =SUM(O4:O50) -> 1 | P51: =SUM(P4:P50) -> 1 | Q51: =SUM(Q4:Q50) -> 1 | R51: =SUM(R4:R50) -> 1 | S51: =SUM(S4:S50) -> 1 | T51: =SUM(T4:T50) -> 1 | U51: =SUM(U4:U50) -> 1 | V51: =+A51 -> COSTO TOTAL POR KILOMETRO SIN IVA | W51: =+B51/'[1]1-COSTO X KM'!B51-1 -> 0.4123843 | X51: =+C51/'[1]1-COSTO X KM'!C51-1 -> 0.48887487 | Y51: =+D51/'[1]1-COSTO X KM'!D51-1 -> 0.490993 | Z51: =+E51/'[1]1-COSTO X KM'!E51-1 -> 0.43219265 | AA51: =+F51/'[1]1-COSTO X KM'!F51-1 -> 0.51005909 | AB51: =+G51/'[1]1-COSTO X KM'!G51-1 -> 0.36539989 | AC51: =+H51/'[1]1-COSTO X KM'!H51-1 -> 0.45350133 | AD51: =+I51/'[1]1-COSTO X KM'!I51-1 -> 0.3509959 | AE51: =+J51/'[1]1-COSTO X KM'!J51-1 -> 0.40616662 | AF51: =+L51 -> COSTO TOTAL POR KILOMETRO SIN IVA | AG51: =+B51/'[2]1-COSTO X KM'!B51-1 -> 0.23786864 | AH51: =+C51/'[2]1-COSTO X KM'!C51-1 -> 0.22777438 | AI51: =+D51/'[2]1-COSTO X KM'!D51-1 -> 0.23717933 | AJ51: =+E51/'[2]1-COSTO X KM'!E51-1 -> 0.20080405 | AK51: =+F51/'[2]1-COSTO X KM'!F51-1 -> 0.31894308 | AL51: =+G51/'[2]1-COSTO X KM'!G51-1 -> 0.2337748 | AM51: =+H51/'[2]1-COSTO X KM'!H51-1 -> 0.28539168 | AN51: =+I51/'[2]1-COSTO X KM'!I51-1 -> 0.23462139 | AO51: =+J51/'[2]1-COSTO X KM'!J51-1 -> 0.27449464
A52: ÍNDICE PASAJERO KILÓMETRO (IPK) | B52: =+'2- EMP. REP'!B14 -> 3.4444686 | C52: =+'2- EMP. REP'!C14 -> 2.7196435 | D52: =+'2- EMP. REP'!D14 -> 1.7471024 | E52: =+'2- EMP. REP'!E14 -> 0.86686079 | F52: =+'2- EMP. REP'!F14 -> 1.1243147 | G52: =+'2- EMP. REP'!G14 -> 2.7832035 | H52: =+'2- EMP. REP'!H14 -> 1.7259652 | I52: =+'2- EMP. REP'!I14 -> 3.1186188 | J52: =+'2- EMP. REP'!J14 -> 2.4992934 | L52: =+A52 -> ÍNDICE PASAJERO KILÓMETRO (IPK) | V52: =+A52 -> ÍNDICE PASAJERO KILÓMETRO (IPK) | W52: =+B52/'[1]1-COSTO X KM'!B52-1 -> 0.056334122 | X52: =+C52/'[1]1-COSTO X KM'!C52-1 -> 0.050035912 | Y52: =+D52/'[1]1-COSTO X KM'!D52-1 -> 0.071137335 | Z52: =+E52/'[1]1-COSTO X KM'!E52-1 -> 0.032181828 | AA52: =+F52/'[1]1-COSTO X KM'!F52-1 -> 0.1166319 | AB52: =+G52/'[1]1-COSTO X KM'!G52-1 -> -0.091704417 | AC52: =+H52/'[1]1-COSTO X KM'!H52-1 -> -0.09499377 | AD52: =+I52/'[1]1-COSTO X KM'!I52-1 -> -0.086935719 | AE52: =+J52/'[1]1-COSTO X KM'!J52-1 -> -0.081172594 | AF52: =+L52 -> ÍNDICE PASAJERO KILÓMETRO (IPK) | AG52: =+B52/'[2]1-COSTO X KM'!B52-1 -> 0.090526412 | AH52: =+C52/'[2]1-COSTO X KM'!C52-1 -> 0.018247953 | AI52: =+D52/'[2]1-COSTO X KM'!D52-1 -> 0.018247943 | AJ52: =+E52/'[2]1-COSTO X KM'!E52-1 -> 0.018247924 | AK52: =+F52/'[2]1-COSTO X KM'!F52-1 -> 0.15709999 | AL52: =+G52/'[2]1-COSTO X KM'!G52-1 -> 0.018247953 | AM52: =+H52/'[2]1-COSTO X KM'!H52-1 -> 0.018247949 | AN52: =+I52/'[2]1-COSTO X KM'!I52-1 -> 0.018247952 | AO52: =+J52/'[2]1-COSTO X KM'!J52-1 -> 0.018247956
A53: Tarifa media sin compensación (Tm = Cm / IPK) | B53: =+B51/B52 -> 1125.2152 | C53: =+C51/C52 -> 1272.8404 | D53: =+D51/D52 -> 1595.9177 | E53: =+E51/E52 -> 2713.4718 | F53: =+F51/F52 -> 2114.2652 | G53: =+G51/G52 -> 1105.8356 | H53: =+H51/H52 -> 1434.0363 | I53: =+I51/I52 -> 996.78299 | J53: =+J51/J52 -> 1178.5857 | L53: =+A53 -> Tarifa media sin compensación (Tm = Cm / IPK) | V53: =+A53 -> Tarifa media sin compensación (Tm = Cm / IPK) | W53: =+B53/'[1]1-COSTO X KM'!B53-1 -> 0.33706208 | X53: =+C53/'[1]1-COSTO X KM'!C53-1 -> 0.41792757 | Y53: =+D53/'[1]1-COSTO X KM'!D53-1 -> 0.39197184 | Z53: =+E53/'[1]1-COSTO X KM'!E53-1 -> 0.3875391 | AA53: =+F53/'[1]1-COSTO X KM'!F53-1 -> 0.35233382 | AB53: =+G53/'[1]1-COSTO X KM'!G53-1 -> 0.50325502 | AC53: =+H53/'[1]1-COSTO X KM'!H53-1 -> 0.60606776 | AD53: =+I53/'[1]1-COSTO X KM'!I53-1 -> 0.47962847 | AE53: =+J53/'[1]1-COSTO X KM'!J53-1 -> 0.53039255 | AF53: =+L53 -> Tarifa media sin compensación (Tm = Cm / IPK) | AG53: =+B53/'[2]1-COSTO X KM'!B53-1 -> 0.13511111 | AH53: =+C53/'[2]1-COSTO X KM'!C53-1 -> 0.20577152 | AI53: =+D53/'[2]1-COSTO X KM'!D53-1 -> 0.21500794 | AJ53: =+E53/'[2]1-COSTO X KM'!E53-1 -> 0.17928456 | AK53: =+F53/'[2]1-COSTO X KM'!F53-1 -> 0.13986958 | AL53: =+G53/'[2]1-COSTO X KM'!G53-1 -> 0.21166441 | AM53: =+H53/'[2]1-COSTO X KM'!H53-1 -> 0.26235626 | AN53: =+I53/'[2]1-COSTO X KM'!I53-1 -> 0.21249583 | AO53: =+J53/'[2]1-COSTO X KM'!J53-1 -> 0.2516545
V55: ESTIMACION INFLACION PERIODO OCTUBRE 2024 - OCTUBRE 2025 | Y55: 0.29395972 | AF55: ESTIMACION INFLACION PERIODO JUNIO 2025 - OCTUBRE 2025 | AI55: 0.068701864

Sheet 2- EMP. REP
A1: ANEXO 2- CARACTERÍSTICAS DE LAS EMPRESAS REPRESENTATIVAS
A3: CARACTERÍSTICAS DE LA EMPRESA | B3: DF | C3: SGI | D3: SGI KM | E3: SGII | F3: INP | G3: UPA | H3: UPA KM | I3: UMA 1 | J3: UMA 2
A4: PASAJEROS TRANSPORTADOS | B4: =+'7-CALCULO TARIFARIO'!B11/'7-CALCULO TARIFARIO'!B6 -> 9679415 | C4: =+'7-CALCULO TARIFARIO'!C11/'7-CALCULO TARIFARIO'!C6 -> 10306100 | D4: =+'7-CALCULO TARIFARIO'!D11/'7-CALCULO TARIFARIO'!D6 -> 23348447 | E4: =+'7-CALCULO TARIFARIO'!E11/'7-CALCULO TARIFARIO'!E6 -> 9125216.8 | F4: =+'7-CALCULO TARIFARIO'!F11/'7-CALCULO TARIFARIO'!F6 -> 1716370.4 | G4: =+'7-CALCULO TARIFARIO'!G11/'7-CALCULO TARIFARIO'!G6 -> 6993861.5 | H4: =+'7-CALCULO TARIFARIO'!H11/'7-CALCULO TARIFARIO'!H6 -> 6906949.7 | I4: =+'7-CALCULO TARIFARIO'!I11/'7-CALCULO TARIFARIO'!I6 -> 6120900.7 | J4: =+'7-CALCULO TARIFARIO'!J11/'7-CALCULO TARIFARIO'!J6 -> 3193089.4
A5: KILOMETRAJE ANUAL RECORRIDO POR LA EMPRESA | B5: =+'7-CALCULO TARIFARIO'!B17/'7-CALCULO TARIFARIO'!B6 -> 2810133.1 | C5: =+'7-CALCULO TARIFARIO'!C17/'7-CALCULO TARIFARIO'!C6 -> 3789504.1 | D5: =+'7-CALCULO TARIFARIO'!D17/'7-CALCULO TARIFARIO'!D6 -> 13364098 | E5: =+'7-CALCULO TARIFARIO'!E17/'7-CALCULO TARIFARIO'!E6 -> 10526738 | F5: =+'7-CALCULO TARIFARIO'!F17/'7-CALCULO TARIFARIO'!F6 -> 1526592.5 | G5: =+'7-CALCULO TARIFARIO'!G17/'7-CALCULO TARIFARIO'!G6 -> 2512881.8 | H5: =+'7-CALCULO TARIFARIO'!H17/'7-CALCULO TARIFARIO'!H6 -> 4001789.8 | I5: =+'7-CALCULO TARIFARIO'!I17/'7-CALCULO TARIFARIO'!I6 -> 1962696 | J5: =+'7-CALCULO TARIFARIO'!J17/'7-CALCULO TARIFARIO'!J6 -> 1277596.9
A6: PARQUE MOVIL DE LA EMPRESA TIPO (vehículos) | B6: =+'7-CALCULO TARIFARIO'!B30/'7-CALCULO TARIFARIO'!B6 -> 51.766667 | C6: =+'7-CALCULO TARIFARIO'!C30/'7-CALCULO TARIFARIO'!C6 -> 64.270833 | D6: =+'7-CALCULO TARIFARIO'!D30/'7-CALCULO TARIFARIO'!D6 -> 171.8017 | E6: =+'7-CALCULO TARIFARIO'!E30/'7-CALCULO TARIFARIO'!E6 -> 89.2 | F6: =+'7-CALCULO TARIFARIO'!F30/'7-CALCULO TARIFARIO'!F6 -> 17.199999 | G6: =+'7-CALCULO TARIFARIO'!G30/'7-CALCULO TARIFARIO'!G6 -> 38.157398 | H6: =+'7-CALCULO TARIFARIO'!H30/'7-CALCULO TARIFARIO'!H6 -> 44.619048 | I6: =+'7-CALCULO TARIFARIO'!I30/'7-CALCULO TARIFARIO'!I6 -> 32.192308 | J6: =+'7-CALCULO TARIFARIO'!J30/'7-CALCULO TARIFARIO'!J6 -> 19.469398
A7: RECAUDACIÓN POR VENTA DE BOLETOS | B7: =+'7-CALCULO TARIFARIO'!B23/'7-CALCULO TARIFARIO'!B6 -> 4.4059114e+09 | C7: =+'7-CALCULO TARIFARIO'!C23/'7-CALCULO TARIFARIO'!C6 -> 4.1071335e+09 | D7: =+'7-CALCULO TARIFARIO'!D23/'7-CALCULO TARIFARIO'!D6 -> 11419794112 | E7: =+'7-CALCULO TARIFARIO'!E23/'7-CALCULO TARIFARIO'!E6 -> 1.0822932e+10 | F7: =+'7-CALCULO TARIFARIO'!F23/'7-CALCULO TARIFARIO'!F6 -> 3.1238787e+09 | G7: =+'7-CALCULO TARIFARIO'!G23/'7-CALCULO TARIFARIO'!G6 -> 2.8761526e+09 | H7: =+'7-CALCULO TARIFARIO'!H23/'7-CALCULO TARIFARIO'!H6 -> 3.7596419e+09 | I7: =+'7-CALCULO TARIFARIO'!I23/'7-CALCULO TARIFARIO'!I6 -> 2.3476129e+09 | J7: =+'7-CALCULO TARIFARIO'!J23/'7-CALCULO TARIFARIO'!J6 -> 1.299644e+09
A8: RECORRIDO PRODUCTIVO MEDIO ANUAL POR VEHICULO (Km) | B8: =+'7-CALCULO TARIFARIO'!B17/'7-CALCULO TARIFARIO'!B30 -> 54284.605 | C8: =+'7-CALCULO TARIFARIO'!C17/'7-CALCULO TARIFARIO'!C30 -> 58961.49 | D8: =+'7-CALCULO TARIFARIO'!D17/'7-CALCULO TARIFARIO'!D30 -> 77787.923 | E8: =+'7-CALCULO TARIFARIO'!E17/'7-CALCULO TARIFARIO'!E30 -> 118012.76 | F8: =+'7-CALCULO TARIFARIO'!F17/'7-CALCULO TARIFARIO'!F30 -> 88755.385 | G8: =+'7-CALCULO TARIFARIO'!G17/'7-CALCULO TARIFARIO'!G30 -> 65855.692 | H8: =+'7-CALCULO TARIFARIO'!H17/'7-CALCULO TARIFARIO'!H30 -> 89687.923 | I8: =+'7-CALCULO TARIFARIO'!I17/'7-CALCULO TARIFARIO'!I30 -> 60967.857 | J8: =+'7-CALCULO TARIFARIO'!J17/'7-CALCULO TARIFARIO'!J30 -> 65620.769
A9: KILOMETRAJE IMPRODUCTIVO (%) | B9: 0.03 | C9: 0.03 | D9: 0.03 | E9: 0.03 | F9: 0.03 | G9: 0.03 | H9: 0.03 | I9: 0.03 | J9: 0.03
A10: VIDA ÚTIL DEL VEHÍCULO (en km) | B10: =+B11*B8 -> 542846.05 | C10: =+C11*C8 -> 766499.37 | D10: =+D11*D8 -> 1011243 | E10: =+E11*E8 -> 1534165.9 | F10: =+F11*F8 -> 1153820 | G10: =+G11*G8 -> 856124 | H10: =+H11*H8 -> 1165943 | I10: =+I11*I8 -> 792582.14 | J10: =+J11*J8 -> 853070
A11: VIDA ÚTIL DEL VEHÍCULO (en años) | B11: 10 | C11: 13 | D11: =+C11 -> 13 | E11: =+D11 -> 13 | F11: =+E11 -> 13 | G11: 13 | H11: =+G11 -> 13 | I11: =+H11 -> 13 | J11: =+I11 -> 13
A12: VELOCIDAD COMERCIAL (Km/Hora) | B12: 13.43 | C12: 16.238046 | D12: 20.033442 | E12: 31.560404 | F12: 25.630109 | G12: 16.157449 | H12: 21.719 | I12: 15.075926 | J12: 17.523861
A13: Recaudación media por KM | B13: =+B7/B5 -> 1567.8657 | C13: =+C7/C5 -> 1083.8182 | D13: =+D7/D5 -> 854.51292 | E13: =+E7/E5 -> 1028.1373 | F13: =+F7/F5 -> 2046.3082 | G13: =+G7/G5 -> 1144.5634 | H13: =+H7/H5 -> 939.4901 | I13: =+I7/I5 -> 1196.1164 | J13: =+J7/J5 -> 1017.2567
A14: IPK | B14: =+B4/B5 -> 3.4444686 | C14: =+C4/C5 -> 2.7196435 | D14: =+D4/D5 -> 1.7471024 | E14: =+E4/E5 -> 0.86686079 | F14: =+F4/F5 -> 1.1243147 | G14: =+G4/G5 -> 2.7832035 | H14: =+H4/H5 -> 1.7259652 | I14: =+I4/I5 -> 3.1186188 | J14: =+J4/J5 -> 2.4992934
A15: Antiguedad Media del Parque | B15: =+B11/2 -> 5 | C15: =+C11/2 -> 6.5 | D15: =+D11/2 -> 6.5 | E15: =+E11/2 -> 6.5 | F15: =+F11/2 -> 6.5 | G15: =+G11/2 -> 6.5 | H15: =+H11/2 -> 6.5 | I15: =+I11/2 -> 6.5 | J15: =+J11/2 -> 6.5
A16: Ingreso medio por Pasajero (Im) | B16: =+B7/B4/1.105 -> 411.9309 | C16: =+C7/C4/1.105 -> 360.64688 | D16: =+D7/D4/1.105 -> 442.6271 | E16: =+E7/E4/1.105 -> 1073.3453 | F16: =+F7/F4/1.105 -> 1647.1034 | G16: =+G7/G4/1.105 -> 372.1625 | H16: =+H7/H4/1.105 -> 492.60397 | I16: =+I7/I4/1.105 -> 347.09541 | J16: =+J7/J4/1.105 -> 368.34183
B18: 2.8292903 | C18: 2.9073597 | D18: 2.9073597 | E18: 3.0303553 | F18: 2.9073597 | G18: 2.9073597 | H18: 2.9073597 | I18: 2.8292903 | J18: 2.8292903
B19: =+B18*B6 -> 146.46293 | C19: =+C18*C6 -> 186.85843 | D19: =+D18*D6 -> 499.48935 | E19: =+E18*E6 -> 270.30769 | F19: =+F18*F6 -> 50.006584 | G19: =+G18*G6 -> 110.93728 | H19: =+H18*H6 -> 129.72362 | I19: =+I18*I6 -> 91.081383 | J19: =+J18*J6 -> 55.084579

Sheet 3- REND Y CONS
A1: ANEXO 3 -RENDIMIENTOS Y CONSUMOS ESPECÍFICOS
A3: PARAMETROS DE CALCULO | B3: DF | C3: SGI | D3: SGI KM | E3: SGII | F3: INP | G3: UPA | H3: UPA KM | I3: UMA 1 | J3: UMA 2
A4: CONSUMO DE COMBUSTIBLE (Lts/Km) | B4: =+'8- COSTO COMBUST'!B16 -> 0.6327615 | C4: =+'8- COSTO COMBUST'!E16 -> 0.51478549 | D4: =+'8- COSTO COMBUST'!F16 -> 0.48390863 | E4: =+'8- COSTO COMBUST'!G16 -> 0.37991355 | F4: =+'8- COSTO COMBUST'!H16 -> 0.33488895 | G4: =+'8- COSTO COMBUST'!I16 -> 0.42428741 | H4: =+'8- COSTO COMBUST'!J16 -> 0.43341033 | I4: =+'8- COSTO COMBUST'!K16 -> 0.41255866 | J4: =+'8- COSTO COMBUST'!L16 -> 0.41255867
A5: CONSUMO DE ACEITE (Lts/Km) | B5: =16.5/20000+1/600 -> 0.0024916667 | C5: =16.5/20000+1/600 -> 0.0024916667 | D5: =16.5/20000+1/600 -> 0.0024916667 | E5: =16.5/20000+1/600 -> 0.0024916667 | F5: =16.5/20000+1/600 -> 0.0024916667 | G5: =16.5/20000+1/600 -> 0.0024916667 | H5: =16.5/20000+1/600 -> 0.0024916667 | I5: =16.5/20000+1/600 -> 0.0024916667 | J5: =16.5/20000+1/600 -> 0.0024916667
A6: CONSUMO DE GRASA (Kg/Km) | B6: =0.925/1000 -> 0.000925 | C6: =+B6 -> 0.000925 | D6: =+C6 -> 0.000925 | E6: =+D6 -> 0.000925 | F6: =+E6 -> 0.000925 | G6: =+F6 -> 0.000925 | H6: =+G6 -> 0.000925 | I6: =+H6 -> 0.000925 | J6: =+I6 -> 0.000925
A7: CONSUMO DE ACEITE DE CAJA (Lts/km) | B7: =16/20000 -> 0.0008 | C7: =+B7 -> 0.0008 | D7: =+C7 -> 0.0008 | E7: =+D7 -> 0.0008 | F7: =+E7 -> 0.0008 | G7: =+F7 -> 0.0008 | H7: =+G7 -> 0.0008 | I7: =+H7 -> 0.0008 | J7: =+I7 -> 0.0008
A8: CANTIDAD DE CUBIERTAS | B8: 6 | C8: 6 | D8: 6 | E8: 6 | F8: 6 | G8: 6 | H8: 6 | I8: 6 | J8: 6
A9: CANTIDAD DE CAMARAS | B9: 12 | C9: 12 | D9: 12 | E9: 12 | F9: 12 | G9: 12 | H9: 12 | I9: 12 | J9: 12
A10: CANTIDAD DE PROTECTORES | B10: 12 | C10: 12 | D10: 12 | E10: 12 | F10: 12 | G10: 12 | H10: 12 | I10: 12 | J10: 12
A11: VIDA UTIL DE LOS NEUMATICOS (Km) | B11: 60000 | C11: =+B11 -> 60000 | D11: =+C11 -> 60000 | E11: =+D11 -> 60000 | F11: =+E11 -> 60000 | G11: =+F11 -> 60000 | H11: =+G11 -> 60000 | I11: =+H11 -> 60000 | J11: =+I11 -> 60000
A12: PROLONGACION DE VIDA UTIL POR RECAPADO | B12: =+B11/2 -> 30000 | C12: =+C11/2 -> 30000 | D12: =+D11/2 -> 30000 | E12: =+E11/2 -> 30000 | F12: =+F11/2 -> 30000 | G12: =+G11/2 -> 30000 | H12: =+H11/2 -> 30000 | I12: =+I11/2 -> 30000 | J12: =+J11/2 -> 30000
A13: VIDA UTIL TOTAL DEL JUEGO DE NEUMATICOS | B13: =+B14*B12+B11 -> 120000 | C13: =+C14*C12+C11 -> 120000 | D13: =+D14*D12+D11 -> 120000 | E13: =+E14*E12+E11 -> 120000 | F13: =+F14*F12+F11 -> 120000 | G13: =+G14*G12+G11 -> 120000 | H13: =+H14*H12+H11 -> 120000 | I13: =+I14*I12+I11 -> 120000 | J13: =+J14*J12+J11 -> 120000
A14: RECAPADOS ADMITIBLES/CUBIERTA | B14: 2 | C14: 2 | D14: 2 | E14: 2 | F14: 2 | G14: 2 | H14: 2 | I14: 2 | J14: 2
A15: CONSERV.NEUMATICOS/COSTO NEUMATICOS (%) | B15: 0 | C15: 0 | D15: 0 | E15: 0 | F15: 0 | G15: 0 | H15: 0 | I15: 0 | J15: 0
A16: CANT.DE ENGRASES GENERALES C/10.000 Km | B16: 2 | C16: 2 | D16: 2 | E16: 2 | F16: 2 | G16: 2 | H16: 2 | I16: 2 | J16: 2
A17: CANT.DE LAVADOS CARROCERIA C/10.000 Km | B17: 8 | C17: 8 | D17: 8 | E17: 8 | F17: 8 | G17: 8 | H17: 8 | I17: 8 | J17: 8
A18: CANT.DE LAVADOS MOTOR C/10.000 Km | B18: 1 | C18: 1 | D18: 1 | E18: 1 | F18: 1 | G18: 1 | H18: 1 | I18: 1 | J18: 1
A19: CANT.DE LAVADOS CHASIS C/10.000 Km | B19: 1 | C19: 1 | D19: 1 | E19: 1 | F19: 1 | G19: 1 | H19: 1 | I19: 1 | J19: 1
A20: CANT.DE FILTROS DE GASOIL C/10.000 Km | B20: 2 | C20: 2 | D20: 2 | E20: 2 | F20: 2 | G20: 2 | H20: 2 | I20: 2 | J20: 2
A21: CANT.DE FILTROS DE ACEITE C/10.000 Km | B21: 0.5 | C21: 0.5 | D21: 0.5 | E21: 0.5 | F21: 0.5 | G21: 0.5 | H21: 0.5 | I21: 0.5 | J21: 0.5
A22: CANT.DE FILTROS DE AIRE C/10.000 Km | B22: 0.75 | C22: 0.75 | D22: 0.75 | E22: 0.75 | F22: 0.75 | G22: 0.75 | H22: 0.75 | I22: 0.75 | J22: 0.75
A23: VIDA UTIL DEL SERVICE (Km) | B23: 10000 | C23: 10000 | D23: 10000 | E23: 10000 | F23: 10000 | G23: 10000 | H23: 10000 | I23: 10000 | J23: 10000
A24: REPARACION CHASIS/PRECIO DEL VEHICULO RENOV. (%) | B24: 0.08 | C24: 0.08 | D24: 0.08 | E24: 0.16 | F24: 0.08 | G24: =+F24 -> 0.08 | H24: =+G24 -> 0.08 | I24: =+H24 -> 0.08 | J24: =+I24 -> 0.08
A25: REPARACION CARROCERIA/PREC. CARROCERÍA NUEVA (%) | B25: 0.08 | C25: 0.08 | D25: 0.08 | E25: 0.16 | F25: 0.08 | G25: =+F25 -> 0.08 | H25: =+G25 -> 0.08 | I25: =+H25 -> 0.08 | J25: =+I25 -> 0.08
A26: PROPORCIÓN DE VEHÍCULOS GRANDES | B26: 0.58287734 | C26: 0.58287734 | D26: 0.58287734 | E26: 0.58287734 | F26: 0.58287734 | G26: 0.58287734 | H26: 0.58287734 | I26: 0.58287734 | J26: 0.58287734
A27: PROPORCION DE VEHICULOS MEDIANOS | B27: =1-B26 -> 0.41712266 | C27: =1-C26 -> 0.41712266 | D27: =1-D26 -> 0.41712266 | E27: =1-E26 -> 0.41712266 | F27: =1-F26 -> 0.41712266 | G27: =1-G26 -> 0.41712266 | H27: =1-H26 -> 0.41712266 | I27: =1-I26 -> 0.41712266 | J27: =1-J26 -> 0.41712266
A28: CANTIDAD ANUAL DE CONTROLES TECNICOS | B28: 2 | C28: 2 | D28: 2 | E28: 2 | F28: 2 | G28: 2 | H28: 2 | I28: 2 | J28: 2
A29: METROS CUADRADOS DE PLAYA/VEHICULO | B29: 40 | C29: 40 | D29: 40 | E29: 44 | F29: 40 | G29: 40 | H29: 40 | I29: 40 | J29: 40
A30: METROS CUADRADOS DE GARAGE/VEHICULO | B30: 1.8 | C30: 1.8 | D30: 1.8 | E30: 1.98 | F30: 1.8 | G30: 1.8 | H30: 1.8 | I30: 1.8 | J30: 1.8
A31: METROS CUADRADOS ADMINISTRACION/VEHICULO | B31: 3 | C31: 3 | D31: 3 | E31: 3 | F31: 3 | G31: 3 | H31: 3 | I31: 3 | J31: 3
A32: METROS CUADRADOS DE TERRENO/VEHICULO | B32: =SUM(B29:B31) -> 44.8 | C32: =SUM(C29:C31) -> 44.8 | D32: =SUM(D29:D31) -> 44.8 | E32: =SUM(E29:E31) -> 48.98 | F32: =SUM(F29:F31) -> 44.8 | G32: =SUM(G29:G31) -> 44.8 | H32: =SUM(H29:H31) -> 44.8 | I32: =SUM(I29:I31) -> 44.8 | J32: =SUM(J29:J31) -> 44.8
A33: SUPERFICIE DESTINADA A PLAYA (m²) | B33: =+B29*'2- EMP. REP'!B$6 -> 2070.6667 | C33: =+C29*'2- EMP. REP'!C$6 -> 2570.8333 | D33: =+D29*'2- EMP. REP'!D$6 -> 6872.0681 | E33: =+E29*'2- EMP. REP'!E$6 -> 3924.8 | F33: =+F29*'2- EMP. REP'!F$6 -> 687.99995 | G33: =+G29*'2- EMP. REP'!G$6 -> 1526.2959 | H33: =+H29*'2- EMP. REP'!H$6 -> 1784.7619 | I33: =+I29*'2- EMP. REP'!I$6 -> 1287.6923 | J33: =+J29*'2- EMP. REP'!J$6 -> 778.77592
A34: SUPERFICIE DESTINADA A GARAGE (m²) | B34: =+B30*'2- EMP. REP'!B$6 -> 93.18 | C34: =+C30*'2- EMP. REP'!C$6 -> 115.6875 | D34: =+D30*'2- EMP. REP'!D$6 -> 309.24307 | E34: =+E30*'2- EMP. REP'!E$6 -> 176.616 | F34: =+F30*'2- EMP. REP'!F$6 -> 30.959998 | G34: =+G30*'2- EMP. REP'!G$6 -> 68.683316 | H34: =+H30*'2- EMP. REP'!H$6 -> 80.314287 | I34: =+I30*'2- EMP. REP'!I$6 -> 57.946154 | J34: =+J30*'2- EMP. REP'!J$6 -> 35.044917
A35: SUPERFICIE DESTINADA A ADMINISTRACION (m²) | B35: =+B31*'2- EMP. REP'!B$6 -> 155.3 | C35: =+C31*'2- EMP. REP'!C$6 -> 192.8125 | D35: =+D31*'2- EMP. REP'!D$6 -> 515.40511 | E35: =+E31*'2- EMP. REP'!E$6 -> 267.6 | F35: =+F31*'2- EMP. REP'!F$6 -> 51.599996 | G35: =+G31*'2- EMP. REP'!G$6 -> 114.47219 | H35: =+H31*'2- EMP. REP'!H$6 -> 133.85714 | I35: =+I31*'2- EMP. REP'!I$6 -> 96.576923 | J35: =+J31*'2- EMP. REP'!J$6 -> 58.408194
A36: SUPERFICIE DE TERRENO (m²) | B36: =+B32*'2- EMP. REP'!B$6 -> 2319.1467 | C36: =+C32*'2- EMP. REP'!C$6 -> 2879.3333 | D36: =+D32*'2- EMP. REP'!D$6 -> 7696.7163 | E36: =+E32*'2- EMP. REP'!E$6 -> 4369.016 | F36: =+F32*'2- EMP. REP'!F$6 -> 770.55994 | G36: =+G32*'2- EMP. REP'!G$6 -> 1709.4514 | H36: =+H32*'2- EMP. REP'!H$6 -> 1998.9334 | I36: =+I32*'2- EMP. REP'!I$6 -> 1442.2154 | J36: =+J32*'2- EMP. REP'!J$6 -> 872.22903
A37: COEFICIENTE DE CONSERVACION DE EDIFICIOS | B37: 0.015 | C37: 0.015 | D37: 0.015 | E37: 0.015 | F37: 0.015 | G37: 0.015 | H37: 0.015 | I37: 0.015 | J37: 0.015
A38: COEFICIENTE DE CONSERVACION DE PLAYAS | B38: 0.025 | C38: 0.025 | D38: 0.025 | E38: 0.025 | F38: 0.025 | G38: 0.025 | H38: 0.025 | I38: 0.025 | J38: 0.025
A39: VIDA UTIL DEL EDIFICIO EN AÑOS | B39: 50 | C39: 50 | D39: 50 | E39: 50 | F39: 50 | G39: 50 | H39: 50 | I39: 50 | J39: 50
A40: COEFICIENTE DE AMORTIZACION DE EDIFICIOS | B40: =+('5-PRECIOS SIN IVA'!$B$40)/(((1+'5-PRECIOS SIN IVA'!$B$40)^$B$39)-1) -> 0.0034442864 | C40: =+('5-PRECIOS SIN IVA'!$B$40)/(((1+'5-PRECIOS SIN IVA'!$B$40)^$B$39)-1) -> 0.0034442864 | D40: =+('5-PRECIOS SIN IVA'!$B$40)/(((1+'5-PRECIOS SIN IVA'!$B$40)^$B$39)-1) -> 0.0034442864 | E40: =+('5-PRECIOS SIN IVA'!$B$40)/(((1+'5-PRECIOS SIN IVA'!$B$40)^$B$39)-1) -> 0.0034442864 | F40: =+('5-PRECIOS SIN IVA'!$B$40)/(((1+'5-PRECIOS SIN IVA'!$B$40)^$B$39)-1) -> 0.0034442864 | G40: =+('5-PRECIOS SIN IVA'!$B$40)/(((1+'5-PRECIOS SIN IVA'!$B$40)^$B$39)-1) -> 0.0034442864 | H40: =+('5-PRECIOS SIN IVA'!$B$40)/(((1+'5-PRECIOS SIN IVA'!$B$40)^$B$39)-1) -> 0.0034442864 | I40: =+('5-PRECIOS SIN IVA'!$B$40)/(((1+'5-PRECIOS SIN IVA'!$B$40)^$B$39)-1) -> 0.0034442864 | J40: =+('5-PRECIOS SIN IVA'!$B$40)/(((1+'5-PRECIOS SIN IVA'!$B$40)^$B$39)-1) -> 0.0034442864
A41: VIDA UTIL DE PLAYAS EN AÑOS | B41: 20 | C41: 20 | D41: 20 | E41: 20 | F41: 20 | G41: 20 | H41: 20 | I41: 20 | J41: 20
A42: COEFICIENTE DE AMORTIZACION DE PLAYAS | B42: =+('5-PRECIOS SIN IVA'!$B$40)/(((1+'5-PRECIOS SIN IVA'!$B$40)^$B$41)-1) -> 0.027184557 | C42: =+('5-PRECIOS SIN IVA'!$B$40)/(((1+'5-PRECIOS SIN IVA'!$B$40)^$B$41)-1) -> 0.027184557 | D42: =+('5-PRECIOS SIN IVA'!$B$40)/(((1+'5-PRECIOS SIN IVA'!$B$40)^$B$41)-1) -> 0.027184557 | E42: =+('5-PRECIOS SIN IVA'!$B$40)/(((1+'5-PRECIOS SIN IVA'!$B$40)^$B$41)-1) -> 0.027184557 | F42: =+('5-PRECIOS SIN IVA'!$B$40)/(((1+'5-PRECIOS SIN IVA'!$B$40)^$B$41)-1) -> 0.027184557 | G42: =+('5-PRECIOS SIN IVA'!$B$40)/(((1+'5-PRECIOS SIN IVA'!$B$40)^$B$41)-1) -> 0.027184557 | H42: =+('5-PRECIOS SIN IVA'!$B$40)/(((1+'5-PRECIOS SIN IVA'!$B$40)^$B$41)-1) -> 0.027184557 | I42: =+('5-PRECIOS SIN IVA'!$B$40)/(((1+'5-PRECIOS SIN IVA'!$B$40)^$B$41)-1) -> 0.027184557 | J42: =+('5-PRECIOS SIN IVA'!$B$40)/(((1+'5-PRECIOS SIN IVA'!$B$40)^$B$41)-1) -> 0.027184557
A43: VALOR RESIDUAL EDIFICIO (%) | B43: 0.2 | C43: 0.2 | D43: 0.2 | E43: 0.2 | F43: 0.2 | G43: 0.2 | H43: 0.2 | I43: 0.2 | J43: 0.2
A44: VALOR RESIDUAL DE PLAYA (%) | B44: 0.1 | C44: 0.1 | D44: 0.1 | E44: 0.1 | F44: 0.1 | G44: 0.1 | H44: 0.1 | I44: 0.1 | J44: 0.1
A45: INVERSION EN MAQ.Y HERR./ INV. EN VEHICULOS (%) | B45: 0.02 | C45: 0.02 | D45: 0.02 | E45: 0.02 | F45: 0.02 | G45: 0.02 | H45: 0.02 | I45: 0.02 | J45: 0.02
A46: CONSERVACION MAQ.Y HERR./ INV. MAQ.Y HERR. (%) | B46: 0.03 | C46: 0.03 | D46: 0.03 | E46: 0.03 | F46: 0.03 | G46: 0.03 | H46: 0.03 | I46: 0.03 | J46: 0.03
A47: VIDA UTIL MAQUINAS Y HERRAMIENTAS (Años) | B47: 10 | C47: 10 | D47: 10 | E47: 10 | F47: 10 | G47: 10 | H47: 10 | I47: 10 | J47: 10
A48: VALOR RESIDUAL MAQUINAS Y HERRAMIENTAS (%) | B48: 0.2 | C48: 0.2 | D48: 0.2 | E48: 0.2 | F48: 0.2 | G48: 0.2 | H48: 0.2 | I48: 0.2 | J48: 0.2
A49: COEF.DE AMORTIZ. DE MAQUINAS Y HERRAMIENTAS | B49: =+('5-PRECIOS SIN IVA'!$B$40)/(((1+'5-PRECIOS SIN IVA'!$B$40)^$B$47)-1) -> 0.075867958 | C49: =+('5-PRECIOS SIN IVA'!$B$40)/(((1+'5-PRECIOS SIN IVA'!$B$40)^$B$47)-1) -> 0.075867958 | D49: =+('5-PRECIOS SIN IVA'!$B$40)/(((1+'5-PRECIOS SIN IVA'!$B$40)^$B$47)-1) -> 0.075867958 | E49: =+('5-PRECIOS SIN IVA'!$B$40)/(((1+'5-PRECIOS SIN IVA'!$B$40)^$B$47)-1) -> 0.075867958 | F49: =+('5-PRECIOS SIN IVA'!$B$40)/(((1+'5-PRECIOS SIN IVA'!$B$40)^$B$47)-1) -> 0.075867958 | G49: =+('5-PRECIOS SIN IVA'!$B$40)/(((1+'5-PRECIOS SIN IVA'!$B$40)^$B$47)-1) -> 0.075867958 | H49: =+('5-PRECIOS SIN IVA'!$B$40)/(((1+'5-PRECIOS SIN IVA'!$B$40)^$B$47)-1) -> 0.075867958 | I49: =+('5-PRECIOS SIN IVA'!$B$40)/(((1+'5-PRECIOS SIN IVA'!$B$40)^$B$47)-1) -> 0.075867958 | J49: =+('5-PRECIOS SIN IVA'!$B$40)/(((1+'5-PRECIOS SIN IVA'!$B$40)^$B$47)-1) -> 0.075867958
A50: VIDA UTIL DE CAMARAS DE SEGURIDAD EN AÑOS | B50: 5 | C50: 10 | D50: 10 | E50: 10 | F50: 10 | G50: 10 | H50: 10 | I50: 10 | J50: 10
A51: VALOR RESIDUAL DE CAMARAS DE SEGURIDAD | B51: 0 | C51: 0 | D51: 0 | E51: 0 | F51: 0 | G51: 0 | H51: 0 | I51: 0 | J51: 0

Sheet 4- PERSONAL
A1: ANEXO 4 -COSTO DEL PERSONAL
A3: Dotación de Personal por Vehículo | B3: DF | C3: SGI | D3: SGI KM | E3: SGII | F3: INP | G3: UPA | H3: UPA KM | I3: UMA 1 | J3: UMA 2
A4: Conductores | B4: 2.2226653 | C4: 2.2945852 | D4: =+C4 -> 2.2945852 | E4: 2.3600424 | F4: =+D4 -> 2.2945852 | G4: =+C4 -> 2.2945852 | H4: =+G4 -> 2.2945852 | I4: =+B4 -> 2.2226653 | J4: =+I4 -> 2.2226653
A5: Tráfico
A6: Jefes de tráfico | B6: 0.0025958016 | C6: 0.0022939493 | D6: =+C6 -> 0.0022939493 | E6: 0.0025093469 | F6: =+D6 -> 0.0022939493 | G6: =+F6 -> 0.0022939493 | H6: =+G6 -> 0.0022939493 | I6: 0.0025988407 | J6: =+I6 -> 0.0025988407
A7: Inspectores | B7: 0.13578966 | C7: 0.11985905 | D7: 0.11985905 | E7: 0.13111359 | F7: =+D7 -> 0.11985905 | G7: =+F7 -> 0.11985905 | H7: =+G7 -> 0.11985905 | I7: =+B7 -> 0.13578966 | J7: =+I7 -> 0.13578966
A8: Otros | B8: 0.089660164 | C8: 0.079141392 | D8: 0.079141392 | E8: 0.086572615 | F8: =+D8 -> 0.079141392 | G8: =+F8 -> 0.079141392 | H8: =+G8 -> 0.079141392 | I8: =+B8 -> 0.089660164 | J8: =+I8 -> 0.089660164
A9: Total tráfico | B9: =SUM(B6:B8) -> 0.22804562 | C9: =SUM(C6:C8) -> 0.2012944 | D9: =+C9 -> 0.2012944 | E9: =SUM(E6:E8) -> 0.22019555 | F9: =+D9 -> 0.2012944 | G9: =+F9 -> 0.2012944 | H9: =+G9 -> 0.2012944 | I9: =SUM(I6:I8) -> 0.22804866 | J9: =SUM(J6:J8) -> 0.22804866
A10: Mantenimiento
A11: Jefes de taller | B11: 0.0051574565 | C11: 0.0056946912 | D11: =+C11 -> 0.0056946912 | E11: 0.0062294117 | F11: =+D11 -> 0.0056946912 | G11: 0.0056913212 | H11: =+G11 -> 0.0056913212 | I11: 0.0051607299 | J11: =+I11 -> 0.0051607299
A12: Oficiales mecánicos, electricistas, etc | B12: 0.15895156 | C12: 0.17529387 | D12: =+C12 -> 0.17529387 | E12: 0.19175362 | F12: =+D12 -> 0.17529387 | G12: 0.17529387 | H12: =+G12 -> 0.17529387 | I12: =+B12 -> 0.15895156 | J12: =+I12 -> 0.15895156
A13: Gomeros | B13: 0.017546601 | C13: 0.019350622 | D13: =+C13 -> 0.019350622 | E13: 0.021167608 | F13: =+D13 -> 0.019350622 | G13: 0.019350622 | H13: =+G13 -> 0.019350622 | I13: =+B13 -> 0.017546601 | J13: =+I13 -> 0.017546601
A14: Otros | B14: 0.063993552 | C14: 0.070572928 | D14: =+C14 -> 0.070572928 | E14: 0.077199589 | F14: =+D14 -> 0.070572928 | G14: 0.070572928 | H14: =+G14 -> 0.070572928 | I14: =+B14 -> 0.063993552 | J14: =+I14 -> 0.063993552
A15: Total mantenimiento | B15: =SUM(B11:B14) -> 0.24564917 | C15: =SUM(C11:C14) -> 0.27091211 | D15: =SUM(D11:D14) -> 0.27091211 | E15: =SUM(E11:E14) -> 0.29635023 | F15: =SUM(F11:F14) -> 0.27091211 | G15: =SUM(G11:G14) -> 0.27090874 | H15: =SUM(H11:H14) -> 0.27090874 | I15: =SUM(I11:I14) -> 0.24565244 | J15: =SUM(J11:J14) -> 0.24565244
A16: Administración y Dirección
A17: Gerentes | B17: 0.0041826233 | C17: 0.0044297469 | D17: =+C17 -> 0.0044297469 | E17: 0.0048456912 | F17: =+D17 -> 0.0044297469 | G17: 0.0044274197 | H17: =+G17 -> 0.0044274197 | I17: 0.0041835696 | J17: =+I17 -> 0.0041835696
A18: Jefes | B18: 0.0062753547 | C18: 0.0066411299 | D18: =+C18 -> 0.0066411299 | E18: 0.0072647192 | F18: =+D18 -> 0.0066411299 | G18: =+F18 -> 0.0066411299 | H18: =+G18 -> 0.0066411299 | I18: =+B18 -> 0.0062753547 | J18: =+I18 -> 0.0062753547
A19: Administrativos | B19: 0.080533718 | C19: 0.085227834 | D19: =+C19 -> 0.085227834 | E19: 0.093230563 | F19: =+D19 -> 0.085227834 | G19: =+F19 -> 0.085227834 | H19: =+G19 -> 0.085227834 | I19: =+B19 -> 0.080533718 | J19: =+I19 -> 0.080533718
A20: Recaudadores | B20: 0.018826064 | C20: 0.01992339 | D20: =+C20 -> 0.01992339 | E20: 0.021794158 | F20: =+D20 -> 0.01992339 | G20: =+F20 -> 0.01992339 | H20: =+G20 -> 0.01992339 | I20: =+B20 -> 0.018826064 | J20: =+I20 -> 0.018826064
A21: Otros | B21: 0.023009611 | C21: 0.024350786 | D21: =+C21 -> 0.024350786 | E21: 0.026637278 | F21: =+D21 -> 0.024350786 | G21: =+F21 -> 0.024350786 | H21: =+G21 -> 0.024350786 | I21: =+B21 -> 0.023009611 | J21: =+I21 -> 0.023009611
A22: Total Administración y Dirección | B22: =SUM(B17:B21) -> 0.13282737 | C22: =SUM(C17:C21) -> 0.14057289 | D22: =SUM(D17:D21) -> 0.14057289 | E22: =SUM(E17:E21) -> 0.15377241 | F22: =SUM(F17:F21) -> 0.14057289 | G22: =SUM(G17:G21) -> 0.14057056 | H22: =SUM(H17:H21) -> 0.14057056 | I22: =SUM(I17:I21) -> 0.13282832 | J22: =SUM(J17:J21) -> 0.13282832
A23: TOTAL DEL PERSONAL DE LA EMPRESA | B23: =+B22+B15+B9+B4 -> 2.8291875 | C23: =+C22+C15+C9+C4 -> 2.9073645 | D23: =+D22+D15+D9+D4 -> 2.9073645 | E23: =+E22+E15+E9+E4 -> 3.0303605 | F23: =+F22+F15+F9+F4 -> 2.9073645 | G23: =+G22+G15+G9+G4 -> 2.9073588 | H23: =+H22+H15+H9+H4 -> 2.9073588 | I23: =+I22+I15+I9+I4 -> 2.8291948 | J23: =+J22+J15+J9+J4 -> 2.8291948
A25: Categoría | B25: Dotación total | C25: Dotación total | D25: Dotación total | E25: Dotación total | F25: Dotación total | G25: Dotación total | H25: Dotación total | I25: Dotación total | J25: Dotación total
A26: Conductores | B26: =+B4*'2- EMP. REP'!B$6 -> 115.05998 | C26: =+C4*'2- EMP. REP'!C$6 -> 147.4749 | D26: =+D4*'2- EMP. REP'!D$6 -> 394.21364 | E26: =+E4*'2- EMP. REP'!E$6 -> 210.51578 | F26: =+F4*'2- EMP. REP'!F$6 -> 39.466862 | G26: =+G4*'2- EMP. REP'!G$6 -> 87.555398 | H26: =+H4*'2- EMP. REP'!H$6 -> 102.38221 | I26: =+I4*'2- EMP. REP'!I$6 -> 71.552726 | J26: =+J4*'2- EMP. REP'!J$6 -> 43.273956
A27: Tráfico
A28: Jefes de tráfico | B28: =+B6*'2- EMP. REP'!B$6 -> 0.134376 | C28: =+C6*'2- EMP. REP'!C$6 -> 0.14743403 | D28: =+D6*'2- EMP. REP'!D$6 -> 0.3941044 | E28: =+E6*'2- EMP. REP'!E$6 -> 0.22383375 | F28: =+F6*'2- EMP. REP'!F$6 -> 0.039455925 | G28: =+G6*'2- EMP. REP'!G$6 -> 0.087531137 | H28: =+H6*'2- EMP. REP'!H$6 -> 0.10235384 | I28: =+I6*'2- EMP. REP'!I$6 -> 0.08366268 | J28: =+J6*'2- EMP. REP'!J$6 -> 0.050597865
A29: Inspectores | B29: =+B7*'2- EMP. REP'!B$6 -> 7.0293779 | C29: =+C7*'2- EMP. REP'!C$6 -> 7.7034413 | D29: =+D7*'2- EMP. REP'!D$6 -> 20.59199 | E29: =+E7*'2- EMP. REP'!E$6 -> 11.695332 | F29: =+F7*'2- EMP. REP'!F$6 -> 2.0615756 | G29: =+G7*'2- EMP. REP'!G$6 -> 4.5735096 | H29: =+H7*'2- EMP. REP'!H$6 -> 5.3479969 | I29: =+I7*'2- EMP. REP'!I$6 -> 4.3713824 | J29: =+J7*'2- EMP. REP'!J$6 -> 2.6437429
A30: Otros | B30: =+B8*'2- EMP. REP'!B$6 -> 4.6414078 | C30: =+C8*'2- EMP. REP'!C$6 -> 5.0864832 | D30: =+D8*'2- EMP. REP'!D$6 -> 13.596626 | E30: =+E8*'2- EMP. REP'!E$6 -> 7.7222773 | F30: =+F8*'2- EMP. REP'!F$6 -> 1.3612318 | G30: =+G8*'2- EMP. REP'!G$6 -> 3.0198296 | H30: =+H8*'2- EMP. REP'!H$6 -> 3.5312136 | I30: =+I8*'2- EMP. REP'!I$6 -> 2.8863676 | J30: =+J8*'2- EMP. REP'!J$6 -> 1.7456294
A31: Total tráfico | B31: =SUM(B28:B30) -> 11.805162 | C31: =SUM(C28:C30) -> 12.937359 | D31: =SUM(D28:D30) -> 34.58272 | E31: =SUM(E28:E30) -> 19.641443 | F31: =SUM(F28:F30) -> 3.4622633 | G31: =SUM(G28:G30) -> 7.6808703 | H31: =SUM(H28:H30) -> 8.9815643 | I31: =SUM(I28:I30) -> 7.3414127 | J31: =SUM(J28:J30) -> 4.4399702
A32: Mantenimiento
A33: Jefes de taller | B33: =+B11*'2- EMP. REP'!B$6 -> 0.26698433 | C33: =+C11*'2- EMP. REP'!C$6 -> 0.36600255 | D33: =+D11*'2- EMP. REP'!D$6 -> 0.97835765 | E33: =+E11*'2- EMP. REP'!E$6 -> 0.55566352 | F33: =+F11*'2- EMP. REP'!F$6 -> 0.097948681 | G33: =+G11*'2- EMP. REP'!G$6 -> 0.21716601 | H33: =+H11*'2- EMP. REP'!H$6 -> 0.25394134 | I33: =+I11*'2- EMP. REP'!I$6 -> 0.16613581 | J33: =+J11*'2- EMP. REP'!J$6 -> 0.10047631
A34: Oficiales mecánicos, electricistas, etc | B34: =+B12*'2- EMP. REP'!B$6 -> 8.2283925 | C34: =+C12*'2- EMP. REP'!C$6 -> 11.266283 | D34: =+D12*'2- EMP. REP'!D$6 -> 30.115785 | E34: =+E12*'2- EMP. REP'!E$6 -> 17.104423 | F34: =+F12*'2- EMP. REP'!F$6 -> 3.0150543 | G34: =+G12*'2- EMP. REP'!G$6 -> 6.6887578 | H34: =+H12*'2- EMP. REP'!H$6 -> 7.8214455 | I34: =+I12*'2- EMP. REP'!I$6 -> 5.1170176 | J34: =+J12*'2- EMP. REP'!J$6 -> 3.0946912
A35: Gomeros | B35: =+B13*'2- EMP. REP'!B$6 -> 0.90832904 | C35: =+C13*'2- EMP. REP'!C$6 -> 1.2436806 | D35: =+D13*'2- EMP. REP'!D$6 -> 3.3244697 | E35: =+E13*'2- EMP. REP'!E$6 -> 1.8881506 | F35: =+F13*'2- EMP. REP'!F$6 -> 0.33283067 | G35: =+G13*'2- EMP. REP'!G$6 -> 0.73836936 | H35: =+H13*'2- EMP. REP'!H$6 -> 0.86340632 | I35: =+I13*'2- EMP. REP'!I$6 -> 0.56486558 | J35: =+J13*'2- EMP. REP'!J$6 -> 0.34162176
A36: Otros | B36: =+B14*'2- EMP. REP'!B$6 -> 3.3127329 | C36: =+C14*'2- EMP. REP'!C$6 -> 4.5357809 | D36: =+D14*'2- EMP. REP'!D$6 -> 12.124549 | E36: =+E14*'2- EMP. REP'!E$6 -> 6.8862034 | F36: =+F14*'2- EMP. REP'!F$6 -> 1.2138543 | G36: =+G14*'2- EMP. REP'!G$6 -> 2.6928793 | H36: =+H14*'2- EMP. REP'!H$6 -> 3.1488969 | I36: =+I14*'2- EMP. REP'!I$6 -> 2.0601001 | J36: =+J14*'2- EMP. REP'!J$6 -> 1.2459159
A37: Total mantenimiento | B37: =SUM(B33:B36) -> 12.716439 | C37: =SUM(C33:C36) -> 17.411747 | D37: =SUM(D33:D36) -> 46.543161 | E37: =SUM(E33:E36) -> 26.43444 | F37: =SUM(F33:F36) -> 4.6596879 | G37: =SUM(G33:G36) -> 10.337172 | H37: =SUM(H33:H36) -> 12.08769 | I37: =SUM(I33:I36) -> 7.9081191 | J37: =SUM(J33:J36) -> 4.7827052
A38: Administración y Dirección
A39: Gerentes | B39: =+B17*'2- EMP. REP'!B$6 -> 0.21652046 | C39: =+C17*'2- EMP. REP'!C$6 -> 0.28470353 | D39: =+D17*'2- EMP. REP'!D$6 -> 0.76103807 | E39: =+E17*'2- EMP. REP'!E$6 -> 0.43223566 | F39: =+F17*'2- EMP. REP'!F$6 -> 0.076191642 | G39: =+G17*'2- EMP. REP'!G$6 -> 0.16893881 | H39: =+H17*'2- EMP. REP'!H$6 -> 0.19754725 | I39: =+I17*'2- EMP. REP'!I$6 -> 0.13467876 | J39: =+J17*'2- EMP. REP'!J$6 -> 0.081451581
A40: Jefes | B40: =+B18*'2- EMP. REP'!B$6 -> 0.32485419 | C40: =+C18*'2- EMP. REP'!C$6 -> 0.42683096 | D40: =+D18*'2- EMP. REP'!D$6 -> 1.1409574 | E40: =+E18*'2- EMP. REP'!E$6 -> 0.64801295 | F40: =+F18*'2- EMP. REP'!F$6 -> 0.11422743 | G40: =+G18*'2- EMP. REP'!G$6 -> 0.25340824 | H40: =+H18*'2- EMP. REP'!H$6 -> 0.2963209 | I40: =+I18*'2- EMP. REP'!I$6 -> 0.20201815 | J40: =+J18*'2- EMP. REP'!J$6 -> 0.12217738
A41: Administrativos | B41: =+B19*'2- EMP. REP'!B$6 -> 4.1689622 | C41: =+C19*'2- EMP. REP'!C$6 -> 5.4776639 | D41: =+D19*'2- EMP. REP'!D$6 -> 14.642287 | E41: =+E19*'2- EMP. REP'!E$6 -> 8.3161662 | F41: =+F19*'2- EMP. REP'!F$6 -> 1.4659186 | G41: =+G19*'2- EMP. REP'!G$6 -> 3.2520724 | H41: =+H19*'2- EMP. REP'!H$6 -> 3.8027848 | I41: =+I19*'2- EMP. REP'!I$6 -> 2.5925662 | J41: =+J19*'2- EMP. REP'!J$6 -> 1.567943
A42: Recaudadores | B42: =+B20*'2- EMP. REP'!B$6 -> 0.97456258 | C42: =+C20*'2- EMP. REP'!C$6 -> 1.2804929 | D42: =+D20*'2- EMP. REP'!D$6 -> 3.4228723 | E42: =+E20*'2- EMP. REP'!E$6 -> 1.9440389 | F42: =+F20*'2- EMP. REP'!F$6 -> 0.34268228 | G42: =+G20*'2- EMP. REP'!G$6 -> 0.76022471 | H42: =+H20*'2- EMP. REP'!H$6 -> 0.88896269 | I42: =+I20*'2- EMP. REP'!I$6 -> 0.60605445 | J42: =+J20*'2- EMP. REP'!J$6 -> 0.36653213
A43: Otros | B43: =+B21*'2- EMP. REP'!B$6 -> 1.1911309 | C43: =+C21*'2- EMP. REP'!C$6 -> 1.5650453 | D43: =+D21*'2- EMP. REP'!D$6 -> 4.1835065 | E43: =+E21*'2- EMP. REP'!E$6 -> 2.3760452 | F43: =+F21*'2- EMP. REP'!F$6 -> 0.41883349 | G43: =+G21*'2- EMP. REP'!G$6 -> 0.92916262 | H43: =+H21*'2- EMP. REP'!H$6 -> 1.0865089 | I43: =+I21*'2- EMP. REP'!I$6 -> 0.74073248 | J43: =+J21*'2- EMP. REP'!J$6 -> 0.44798328
A44: Total Administración y Dirección | B44: =SUM(B39:B43) -> 6.8760303 | C44: =SUM(C39:C43) -> 9.0347366 | D44: =SUM(D39:D43) -> 24.150661 | E44: =SUM(E39:E43) -> 13.716499 | F44: =SUM(F39:F43) -> 2.4178535 | G44: =SUM(G39:G43) -> 5.3638067 | H44: =SUM(H39:H43) -> 6.2721246 | I44: =SUM(I39:I43) -> 4.2760501 | J44: =SUM(J39:J43) -> 2.5860874
A45: TOTAL DEL PERSONAL DE LA EMPRESA | B45: =+B44+B37+B31+B26 -> 146.45761 | C45: =+C44+C37+C31+C26 -> 186.85874 | D45: =+D44+D37+D31+D26 -> 499.49018 | E45: =+E44+E37+E31+E26 -> 270.30816 | F45: =+F44+F37+F31+F26 -> 50.006666 | G45: =+G44+G37+G31+G26 -> 110.93725 | H45: =+H44+H37+H31+H26 -> 129.72358 | I45: =+I44+I37+I31+I26 -> 91.078308 | J45: =+J44+J37+J31+J26 -> 55.082719
A48: DF | C48: SGI | D48: SGI KM | E48: SGII | F48: INP | G48: UPA | H48: UPA KM | I48: UMA 1 | J48: UMA 2
A50: Determinación de las Asignaciones remunerativas por conductor (convenio)
A51: Sueldo Básico | B51: 972700 | C51: =+B51 -> 972700 | D51: =+C51 -> 972700 | E51: =+D51 -> 972700 | F51: =+E51 -> 972700 | G51: =+F51 -> 972700 | H51: =+G51 -> 972700 | I51: =+H51 -> 972700 | J51: =+I51 -> 972700
A52: Premio Asistencia | B52: 274000 | C52: =+B52 -> 274000 | D52: =+C52 -> 274000 | E52: =+D52 -> 274000 | F52: =+E52 -> 274000 | G52: =+F52 -> 274000 | H52: =+G52 -> 274000 | I52: =+H52 -> 274000 | J52: =+I52 -> 274000
A53: Atención S.U.B.E. | B53: 123300 | C53: =+B53 -> 123300 | D53: =+C53 -> 123300 | E53: =+D53 -> 123300 | F53: =+E53 -> 123300 | G53: =+F53 -> 123300 | H53: =+G53 -> 123300 | I53: =+H53 -> 123300 | J53: =+I53 -> 123300
A54: Bonificación por antigüedad | B54: =0.015*(B51+B52+B53) -> 20550 | C54: =0.015*(C51+C52+C53) -> 20550 | D54: =0.015*(D51+D52+D53) -> 20550 | E54: =0.015*(E51+E52+E53) -> 20550 | F54: =0.015*(F51+F52+F53) -> 20550 | G54: =0.015*(G51+G52+G53) -> 20550 | H54: =+G54 -> 20550 | I54: =+H54 -> 20550 | J54: =+I54 -> 20550
A55: Antigüedad promedio del personal | B55: 11 | C55: =+B55 -> 11 | D55: =+C55 -> 11 | E55: =+D55 -> 11 | F55: =+E55 -> 11 | G55: =+F55 -> 11 | H55: =+G55 -> 11 | I55: =+H55 -> 11 | J55: =+I55 -> 11
A56: Remuneración por antigüedad | B56: =+B55*B54 -> 226050 | C56: =+C55*C54 -> 226050 | D56: =+D55*D54 -> 226050 | E56: =+E55*E54 -> 226050 | F56: =+F55*F54 -> 226050 | G56: =+G55*G54 -> 226050 | H56: =+G56 -> 226050 | I56: =+H56 -> 226050 | J56: =+I56 -> 226050
A57: Total de asignación remunerativa | B57: =+B51+B53+B56+(B52*B58) -> 1584727.2 | C57: =+B57 -> 1584727.2 | D57: =+C57 -> 1584727.2 | E57: =+D57 -> 1584727.2 | F57: =+E57 -> 1584727.2 | G57: =+G51+G53+G56+(G52*G58) -> 1584727.2 | H57: =+G57 -> 1584727.2 | I57: =+H57 -> 1584727.2 | J57: =+I57 -> 1584727.2
A58: Porcentaje Premio Asistencia | B58: 0.958676 | C58: =+B58 -> 0.958676 | D58: =+C58 -> 0.958676 | E58: =+D58 -> 0.958676 | F58: =+E58 -> 0.958676 | G58: =+F58 -> 0.958676 | H58: =+G58 -> 0.958676 | I58: =+H58 -> 0.958676 | J58: =+I58 -> 0.958676
A59: Determinación de las Asignaciones no remunerativas por conductor (convenio)
A60: Viáticos diarios | B60: 13000 | C60: =+B60 -> 13000 | D60: =+C60 -> 13000 | E60: =+D60 -> 13000 | F60: =+E60 -> 13000 | G60: =+F60 -> 13000 | H60: =+G60 -> 13000 | I60: =+H60 -> 13000 | J60: =+I60 -> 13000
A61: Días trabajados | B61: 21 | C61: =+B61 -> 21 | D61: =+C61 -> 21 | E61: =+D61 -> 21 | F61: =+E61 -> 21 | G61: =+F61 -> 21 | H61: =+G61 -> 21 | I61: =+H61 -> 21 | J61: =+I61 -> 21
A62: Viáticos mensuales | B62: =+B61*B60 -> 273000 | C62: =+B62 -> 273000 | D62: =+C62 -> 273000 | E62: =+D62 -> 273000 | F62: =+E62 -> 273000 | G62: =+G61*G60 -> 273000 | H62: =+G62 -> 273000 | I62: =+H62 -> 273000 | J62: =+I62 -> 273000
A63: Adicional No remunerativo | B63: 0 | C63: =+B63 -> 0 | D63: =+C63 -> 0 | E63: =+D63 -> 0 | F63: =+E63 -> 0 | G63: =+F63 -> 0 | H63: =+G63 -> 0 | I63: =+H63 -> 0 | J63: =+I63 -> 0
A64: Aporte Obra Social por adicional no remunerativo | B64: 0 | C64: =+B64 -> 0 | D64: =+C64 -> 0 | E64: =+D64 -> 0 | F64: =+E64 -> 0 | G64: =+F64 -> 0 | H64: =+G64 -> 0 | I64: =+H64 -> 0 | J64: =+I64 -> 0
A65: Total de asignación no remunerativa | B65: =+B62+B63 -> 273000 | C65: =+B65 -> 273000 | D65: =+C65 -> 273000 | E65: =+D65 -> 273000 | F65: =+F62+F63 -> 273000 | G65: =+G62+G63 -> 273000 | H65: =+G65 -> 273000 | I65: =+H65 -> 273000 | J65: =+I65 -> 273000
A66: Determinación de las Cargas Sociales
A67: Régimen de Jubilaciones y Pensiones (ley 24.241) | B67: 0.1077 | C67: =+B67 -> 0.1077 | D67: =+C67 -> 0.1077 | E67: =+D67 -> 0.1077 | F67: =+E67 -> 0.1077 | G67: =+F67 -> 0.1077 | H67: =+G67 -> 0.1077 | I67: =+H67 -> 0.1077 | J67: =+I67 -> 0.1077
A68: Instituto Nacional de Jubilaciones y Pensiones | B68: 0.0159 | C68: =+B68 -> 0.0159 | D68: =+C68 -> 0.0159 | E68: =+D68 -> 0.0159 | F68: =+E68 -> 0.0159 | G68: =+F68 -> 0.0159 | H68: =+G68 -> 0.0159 | I68: =+H68 -> 0.0159 | J68: =+I68 -> 0.0159
A69: Asignaciones Familiares (Ley 24.471) | B69: 0.047 | C69: =+B69 -> 0.047 | D69: =+C69 -> 0.047 | E69: =+D69 -> 0.047 | F69: =+E69 -> 0.047 | G69: =+F69 -> 0.047 | H69: =+G69 -> 0.047 | I69: =+H69 -> 0.047 | J69: =+I69 -> 0.047
A70: Obra Social | B70: 0.06 | C70: =+B70 -> 0.06 | D70: =+C70 -> 0.06 | E70: =+D70 -> 0.06 | F70: =+E70 -> 0.06 | G70: =+F70 -> 0.06 | H70: =+G70 -> 0.06 | I70: =+H70 -> 0.06 | J70: =+I70 -> 0.06
A71: Previsión para despidos | B71: 0.0094 | C71: =+B71 -> 0.0094 | D71: =+C71 -> 0.0094 | E71: =+D71 -> 0.0094 | F71: =+E71 -> 0.0094 | G71: =+F71 -> 0.0094 | H71: =+G71 -> 0.0094 | I71: =+H71 -> 0.0094 | J71: =+I71 -> 0.0094
A72: Seguro de vida obligatorio | B72: 0.001 | C72: =+B72 -> 0.001 | D72: =+C72 -> 0.001 | E72: =+D72 -> 0.001 | F72: =+E72 -> 0.001 | G72: =+F72 -> 0.001 | H72: =+G72 -> 0.001 | I72: =+H72 -> 0.001 | J72: =+I72 -> 0.001
A73: Decreto 633/18 | B73: 0.02 | C73: =+B73 -> 0.02 | D73: =+C73 -> 0.02 | E73: =+D73 -> 0.02 | F73: =+E73 -> 0.02 | G73: =+F73 -> 0.02 | H73: =+G73 -> 0.02 | I73: =+H73 -> 0.02 | J73: =+I73 -> 0.02
A74: Total de cargas sociales + Previsión + Seguro vida obligatorio | B74: =SUM(B67:B72) -> 0.241 | C74: =SUM(C67:C72) -> 0.241 | D74: =SUM(D67:D72) -> 0.241 | E74: =SUM(E67:E72) -> 0.241 | F74: =SUM(F67:F72) -> 0.241 | G74: =SUM(G67:G72) -> 0.241 | H74: =SUM(H67:H72) -> 0.241 | I74: =SUM(I67:I72) -> 0.241 | J74: =SUM(J67:J72) -> 0.241
A76: Premio Estimulo | B76: 0 | C76: 0 | D76: 0 | E76: 0 | F76: 0 | G76: =+(G51+G52+G53)*(10.78%) -> 147686 | H76: =+G76 -> 147686 | I76: =+H76 -> 147686 | J76: =+I76 -> 147686
A77: Incidencia Antigüedad (11 años - 1,5% x año) | B77: 0 | C77: 0 | D77: 0 | E77: 0 | F77: 0 | G77: =+(G76*1.5%)*11 -> 24368.19 | H77: =+G77 -> 24368.19 | I77: =+H77 -> 24368.19 | J77: =+I77 -> 24368.19
A78: Incidencia Hs Extras y feriados | B78: 0 | C78: 0 | D78: 0 | E78: 0 | F78: 0 | G78: =+G76*3.37% -> 4977.0182 | H78: =+G78 -> 4977.0182 | I78: =+H78 -> 4977.0182 | J78: =+I78 -> 4977.0182
A79: Incidencia Enfermedad | B79: 0 | C79: 0 | D79: 0 | E79: 0 | F79: 0 | G79: =+G76*1.25% -> 1846.075 | H79: =+G79 -> 1846.075 | I79: =+H79 -> 1846.075 | J79: =+I79 -> 1846.075
A80: Incidencia ART | B80: 0 | C80: 0 | D80: 0 | E80: 0 | F80: 0 | G80: =+G76*0.9% -> 1329.174 | H80: =+G80 -> 1329.174 | I80: =+H80 -> 1329.174 | J80: =+I80 -> 1329.174
A81: SAC | B81: 0 | C81: 0 | D81: 0 | E81: 0 | F81: 0 | G81: =+G76*10.1644% -> 15011.396 | H81: =+G81 -> 15011.396 | I81: =+H81 -> 15011.396 | J81: =+I81 -> 15011.396
A82: Cargas Sociales (incluye ART al 5,58%) | B82: 0 | C82: 0 | D82: 0 | E82: 0 | F82: 0 | G82: 51868 | H82: =+G82 -> 51868 | I82: =+H82 -> 51868 | J82: =+I82 -> 51868
A83: Costo Total Premio Estímulo | B83: 0 | C83: 0 | D83: 0 | E83: 0 | F83: 0 | G83: =SUM(G76:G82) -> 247085.85 | H83: =+G83 -> 247085.85 | I83: =+H83 -> 247085.85 | J83: =+I83 -> 247085.85
A84: Total personal de la línea ajustados por AFIP | B84: 0 | C84: 0 | D84: 0 | E84: 0 | F84: 0 | G84: 911 | H84: 27 | I84: 0 | J84: 876
B86: DF | C86: SGI | D86: SGI KM | E86: SGII | F86: INP | G86: UPA | H86: UPA KM | I86: UMA 1 | J86: UMA 2
A87: Otras sumas fijas anuales | P87: Grupo Tarifario | Q87: %Hs Nocturnas/Hs Totales | R87: Horas Totales | S87: Horas nocturnas | T87: Factor nocturnidad | U87: 1/(1+8minutos/60minutos)*%Hs.nocturnas)
A88: Indumentaria por trabajador por año ($) | B88: 130713 | C88: =+B88 -> 130713 | D88: =+C88 -> 130713 | E88: =+D88 -> 130713 | F88: =+E88 -> 130713 | G88: =+F88 -> 130713 | H88: =+G88 -> 130713 | I88: =+H88 -> 130713 | J88: =+I88 -> 130713 | P88: DF | Q88: =+S88/R88 -> 0.16160772 | R88: 579007 | S88: 93572 | T88: =1/(1+(8/60)*Q88) -> 0.97890681
A89: Costo capacitación por trabajor por año | B89: 140511 | C89: =+B89 -> 140511 | D89: =+C89 -> 140511 | E89: =+D89 -> 140511 | F89: =+E89 -> 140511 | G89: =+F89 -> 140511 | H89: =+G89 -> 140511 | I89: =+H89 -> 140511 | J89: =+I89 -> 140511 | P89: SGI | Q89: =+S89/R89 -> 0.17183468 | R89: 2160920 | S89: 371321 | T89: =1/(1+(8/60)*Q89) -> 0.97760188
A90: Contribución UTA por trabajador por año ($) | B90: 72 | C90: 72 | D90: 72 | E90: 72 | F90: 72 | G90: 72 | H90: 72 | I90: 72 | J90: 72 | P90: SGI KM | Q90: =+S90/R90 -> 0.23581793 | R90: 192144 | S90: 45311 | T90: =1/(1+(8/60)*Q90) -> 0.9695161
A91: Determinación de Horas Extras del personal de Conducción | P91: SGII | Q91: =+S91/R91 -> 0.16612376 | R91: 162090 | S91: 26927 | T91: =1/(1+(8/60)*Q91) -> 0.97833015
A92: Horas anuales de conducción por vehículo | B92: =+'2- EMP. REP'!B8/'2- EMP. REP'!B12 -> 4042.0406 | C92: =+'2- EMP. REP'!C8/'2- EMP. REP'!C12 -> 3631.0704 | D92: =+'2- EMP. REP'!D8/'2- EMP. REP'!D12 -> 3882.9036 | E92: =+'2- EMP. REP'!E8/'2- EMP. REP'!E12 -> 3739.2665 | F92: =+'2- EMP. REP'!F8/'2- EMP. REP'!F12 -> 3462.9344 | G92: =+'2- EMP. REP'!G8/'2- EMP. REP'!G12 -> 4075.872 | H92: =+'2- EMP. REP'!H8/'2- EMP. REP'!H12 -> 4129.4683 | I92: =+'2- EMP. REP'!I8/'2- EMP. REP'!I12 -> 4044.0538 | J92: =+'2- EMP. REP'!J8/'2- EMP. REP'!J12 -> 3744.6524 | L92: Días del año | N92: 365 | P92: INP | Q92: =+S92/R92 -> 0.16609771 | R92: 53607 | S92: 8904 | T92: =1/(1+(8/60)*Q92) -> 0.97833347
A93: Horas normales de conducción anual de la Dotación (horas) | B93: =+B4*B97*B94 -> 3964.7504 | C93: =+C4*C97*C94 -> 4095.9075 | D93: =+D4*D97*D94 -> 4073.8822 | E93: =+E4*E97*E94 -> 4212.3712 | F93: =+F4*F97*F94 -> 4091.3738 | G93: =+G4*G97*G94 -> 4102.6184 | H93: =+H4*H97*H94 -> 4082.2115 | I93: =+I4*I97*I94 -> 3978.8699 | J93: =+J4*J97*J94 -> 3984.5177 | L93: Francos (6*11) | N93: 66 | P93: UPA | Q93: =+S93/R93 -> 0.14663162 | R93: 1408823 | S93: 206578 | T93: =1/(1+(8/60)*Q93) -> 0.98082402
A94: Días anuales de trabajo por conductor | B94: 242 | C94: =+B94 -> 242 | D94: =+C94 -> 242 | E94: =+D94 -> 242 | F94: =+E94 -> 242 | G94: =+F94 -> 242 | H94: =+G94 -> 242 | I94: =+H94 -> 242 | J94: =+I94 -> 242 | L94: Vacaciones | N94: 21 | P94: UPA KM | Q94: =+S94/R94 -> 0.19627329 | R94: 323610 | S94: 63516 | T94: =1/(1+(8/60)*Q94) -> 0.97449762
A95: Horas diarias de conducción por chofer | B95: 7.5 | C95: =+B95 -> 7.5 | D95: =+C95 -> 7.5 | E95: =+D95 -> 7.5 | F95: =+E95 -> 7.5 | G95: =+F95 -> 7.5 | H95: =+G95 -> 7.5 | I95: =+H95 -> 7.5 | J95: =+I95 -> 7.5 | L95: Feriados | N95: 19 | P95: UMA 1 | Q95: =+S95/R95 -> 0.13807749 | R95: 858221 | S95: 118501 | T95: =1/(1+(8/60)*Q95) -> 0.98192248
A96: Factor de nocturnidad | B96: 0.9828 | C96: 0.98348861 | D96: 0.9782 | E96: 0.9834 | F96: 0.9824 | G96: 0.9851 | H96: 0.9802 | I96: 0.9863 | J96: 0.9877 | L96: Inasistencia (enfermedad, otras licencias) | N96: 17 | P96: UMA 2 | Q96: =+S96/R96 -> 0.11356982 | R96: 293379 | S96: 33319 | T96: =1/(1+(8/60)*Q96) -> 0.98508324
A97: Horas diarias corregidas de conducción por chofer | B97: =+B96*B95 -> 7.371 | C97: =+C96*C95 -> 7.3761646 | D97: =+D96*D95 -> 7.3365 | E97: =+E96*E95 -> 7.3755 | F97: =+F96*F95 -> 7.368 | G97: =+G96*G95 -> 7.38825 | H97: =+H96*H95 -> 7.3515 | I97: =+I96*I95 -> 7.39725 | J97: =+J96*J95 -> 7.40775 | L97: Total de inasistencias | N97: =SUM(N93:N96) -> 123
A98: Ppción. Conducción Feriados | B98: 0.42758 | C98: 0.37366633 | D98: 0.33235851 | E98: 0.43748587 | F98: 0.51586389 | G98: 0.4197786 | H98: 0.43357182 | I98: 0.39372341 | J98: 0.42241549 | L98: Días anuales de trabajo por conductor | N98: =+N92-N97 -> 242
A99: Horas de Conducción Feriados | B99: =+B4*B97*B98*$N$95 -> 133.09798 | C99: =+C4*C97*C98*$N$95 -> 120.16344 | D99: =+D4*D97*D98*$N$95 -> 106.30495 | E99: =+E4*E97*E98*$N$95 -> 144.6868 | F99: =+F4*F97*F98*$N$95 -> 165.70764 | G99: =+G4*G97*G98*$N$95 -> 135.21338 | H99: =+H4*H97*H98*$N$95 -> 138.96159 | I99: =+I4*I97*I98*$N$95 -> 122.9955 | J99: =+J4*J97*J98*$N$95 -> 132.14594 | N99: =+N97/N98 -> 0.50826446
A100: Hs. extras anuales por vehículo | B100: =IF(B92-B93-B99<0,0,B92-B93-B99) -> 0 | C100: =IF(C92-C93-C99<0,0,C92-C93-C99) -> 0 | D100: =IF(D92-D93-D99<0,0,D92-D93-D99) -> 0 | E100: =IF(E92-E93-E99<0,0,E92-E93-E99) -> 0 | F100: =IF(F92-F93-F99<0,0,F92-F93-F99) -> 0 | G100: =IF(G92-G93-G99<0,0,G92-G93-G99) -> 0 | H100: =IF(H92-H93-H99<0,0,H92-H93-H99) -> 0 | I100: =IF(I92-I93-I99<0,0,I92-I93-I99) -> 0 | J100: =IF(J92-J93-J99<0,0,J92-J93-J99) -> 0 | P100: Grupo Tarifario | Q100: internos hábil | R100: interno feriado | S100: coef.corrección
A101: Factor mayoración horas extras (%) | B101: 1.514 | C101: =+B101 -> 1.514 | D101: =+C101 -> 1.514 | E101: =+D101 -> 1.514 | F101: =+E101 -> 1.514 | G101: =+F101 -> 1.514 | H101: =+G101 -> 1.514 | I101: =+H101 -> 1.514 | J101: =+I101 -> 1.514 | P101: DF | Q101: 2076 | R101: 740 | S101: =+R101/Q101 -> 0.35645472
A102: Horas extras totales | B102: =+B99*2+B100*B101 -> 266.19596 | C102: =+C99*2+C100*C101 -> 240.32688 | D102: =+D99*2+D100*D101 -> 212.60991 | E102: =+E99*2+E100*E101 -> 289.37359 | F102: =+F99*2+F100*F101 -> 331.41528 | G102: =+G99*2+G100*G101 -> 270.42675 | H102: =+H99*2+H100*H101 -> 277.92319 | I102: =+I99*2+I100*I101 -> 245.99099 | J102: =+J99*2+J100*J101 -> 264.29188 | P102: SGI | Q102: 8003 | R102: 2862 | S102: =+R102/Q102 -> 0.35761589
A103: Factor de retribución anual total de hs. Extras | B103: =1+B102/B93 -> 1.0671407 | C103: =1+C102/C93 -> 1.0586749 | D103: =1+D102/D93 -> 1.0521885 | E103: =1+E102/E93 -> 1.0686961 | F103: =1+F102/F93 -> 1.0810034 | G103: =1+G102/G93 -> 1.0659156 | H103: =1+H102/H93 -> 1.0680815 | I103: =1+I102/I93 -> 1.0618243 | J103: =1+J102/J93 -> 1.0663297 | P103: SGI KM | Q103: 671 | R103: 200 | S103: =+R103/Q103 -> 0.29806259
P104: SGII | Q104: 622 | R104: 245 | S104: =+R104/Q104 -> 0.39389068
A105: Tráfico | P105: INP | Q105: 211 | R105: 105.15 | S105: =+R105/Q105 -> 0.49834123
A106: Jefes de tráfico | B106: =+B107*2.2788191 -> 2698342.9 | C106: =+B106 -> 2698342.9 | D106: =+C106 -> 2698342.9 | E106: =+D106 -> 2698342.9 | F106: =+E106 -> 2698342.9 | G106: =+G107*2.2788191 -> 2698342.9 | H106: =+G106 -> 2698342.9 | I106: =+H106 -> 2698342.9 | J106: =+I106 -> 2698342.9 | P106: UPA | Q106: 5022 | R106: 2023 | S106: =+R106/Q106 -> 0.40282756
A107: Inspectores (Inspector 1°) | B107: 1184097 | C107: =+B107 -> 1184097 | D107: =+C107 -> 1184097 | E107: =+D107 -> 1184097 | F107: =+E107 -> 1184097 | G107: =+F107 -> 1184097 | H107: =+G107 -> 1184097 | I107: =+H107 -> 1184097 | J107: =+I107 -> 1184097 | P107: UPA KM | Q107: 1143 | R107: 479 | S107: =+R107/Q107 -> 0.41907262
...

Sheet 5-PRECIOS SIN IVA
A1: ANEXO 5 - PRECIOS CONSIDERADOS EN LA ESTIMACIÓN - SIN I.V.A.
A3: PARAMETROS DE CALCULO | B3: DF | C3: SGI | D3: SGI KM | E3: SGII | F3: INP | G3: UPA | H3: UPA KM | I3: UMA 1 | J3: UMA 2 | L3: diciembre | M3: enero | N3: febrero | O3: marzo | P3: abril | Q3: mayo | R3: julio | S3: % GO
A4: PRECIO DEL GASOIL ($/Lt) | B4: =+'8- COSTO COMBUST'!B4 -> 1548.852 | C4: =+'8- COSTO COMBUST'!D4 -> 1548.852 | D4: =+C4 -> 1548.852 | E4: =+D4 -> 1548.852 | F4: =+E4 -> 1548.852 | G4: =+F4 -> 1548.852 | H4: =+G4 -> 1548.852 | I4: =+H4 -> 1548.852 | J4: =+I4 -> 1548.852 | L4: 1123 | M4: 1143 | N4: 1170 | O4: 1188 | P4: 1209 | Q4: 1173 | R4: 1251 | S4: 35 | T4: =+R4*S4 -> 43785
A5: PRECIO DEL GASOIL ($/Lt) (sin IVA) | B5: =+'8- COSTO COMBUST'!B18 -> 1216.6782 | C5: =+'8- COSTO COMBUST'!D18 -> 1216.6782 | D5: =+C5 -> 1216.6782 | E5: =+D5 -> 1216.6782 | F5: =+E5 -> 1216.6782 | G5: =+F5 -> 1216.6782 | H5: =+G5 -> 1216.6782 | I5: =+H5 -> 1216.6782 | J5: =+I5 -> 1216.6782 | L5: 1368 | M5: 1392 | N5: 1420 | O5: 1448 | P5: 1472 | Q5: 1354 | R5: 1444 | S5: 65 | T5: =+R5*S5 -> 93860
A6: PRECIO DEL ACEITE ($/Lt) | B6: 4906.11 | C6: 4906.11 | D6: =+C6 -> 4906.11 | E6: =+D6 -> 4906.11 | F6: =+E6 -> 4906.11 | G6: =+F6 -> 4906.11 | H6: =+G6 -> 4906.11 | I6: =+H6 -> 4906.11 | J6: =+I6 -> 4906.11 | S6: =+S4+S5 -> 100 | T6: =(+T4+T5)/100 -> 1376.45
A7: PRECIO DE LA GRASA ($/Kg) | B7: 5175.96 | C7: 5175.96 | D7: =+C7 -> 5175.96 | E7: =+D7 -> 5175.96 | F7: =+E7 -> 5175.96 | G7: =+F7 -> 5175.96 | H7: =+G7 -> 5175.96 | I7: =+H7 -> 5175.96 | J7: =+I7 -> 5175.96 | S7: % GO
A8: PRECIO DE LA CUBIERTA ($) | B8: 934456.46 | C8: 934456.46 | D8: =+C8 -> 934456.46 | E8: =+D8 -> 934456.46 | F8: =+E8 -> 934456.46 | G8: =+F8 -> 934456.46 | H8: =+G8 -> 934456.46 | I8: =+H8 -> 934456.46 | J8: =+I8 -> 934456.46 | S8: 30 | T8: =+R4*S8 -> 37530
A9: PRECIO DEL RECAPADO ($) | B9: 301111.59 | C9: 301111.59 | D9: =+C9 -> 301111.59 | E9: =+D9 -> 301111.59 | F9: =+E9 -> 301111.59 | G9: =+F9 -> 301111.59 | H9: =+G9 -> 301111.59 | I9: =+H9 -> 301111.59 | J9: =+I9 -> 301111.59 | L9: =+L8/100 -> 0 | S9: 70 | T9: =+R5*S9 -> 101080
A10: PRECIO DEL ENGRASE GENERAL ($) | B10: 32729.66 | C10: 32729.66 | D10: =+C10 -> 32729.66 | E10: =+D10 -> 32729.66 | F10: =+E10 -> 32729.66 | G10: =+F10 -> 32729.66 | H10: =+G10 -> 32729.66 | I10: =+H10 -> 32729.66 | J10: =+I10 -> 32729.66 | S10: =+S8+S9 -> 100 | T10: =(+T8+T9)/100 -> 1386.1
A11: PRECIO DEL LAVADO DE CARROCERIA ($) | B11: 31713.11 | C11: 31713.11 | D11: =+C11 -> 31713.11 | E11: =+D11 -> 31713.11 | F11: =+E11 -> 31713.11 | G11: =+F11 -> 31713.11 | H11: =+G11 -> 31713.11 | I11: =+H11 -> 31713.11 | J11: =+I11 -> 31713.11
A12: PRECIO DEL LAVADO DE MOTOR ($) | B12: 31713.11 | C12: 31713.11 | D12: =+C12 -> 31713.11 | E12: =+D12 -> 31713.11 | F12: =+E12 -> 31713.11 | G12: =+F12 -> 31713.11 | H12: =+G12 -> 31713.11 | I12: =+H12 -> 31713.11 | J12: =+I12 -> 31713.11
A13: PRECIO DEL LAVADO DE CHASIS ($) | B13: 35067.49 | C13: 35067.49 | D13: =+C13 -> 35067.49 | E13: =+D13 -> 35067.49 | F13: =+E13 -> 35067.49 | G13: =+F13 -> 35067.49 | H13: =+G13 -> 35067.49 | I13: =+H13 -> 35067.49 | J13: =+I13 -> 35067.49
A14: PRECIO DEL FILTRO DE GASOIL ($) | B14: 50843.46 | C14: 50843.46 | D14: =+C14 -> 50843.46 | E14: =+D14 -> 50843.46 | F14: =+E14 -> 50843.46 | G14: =+F14 -> 50843.46 | H14: =+G14 -> 50843.46 | I14: =+H14 -> 50843.46 | J14: =+I14 -> 50843.46
A15: PRECIO DEL FILTRO DE ACEITE ($) | B15: 33805.49 | C15: 33805.49 | D15: =+C15 -> 33805.49 | E15: =+D15 -> 33805.49 | F15: =+E15 -> 33805.49 | G15: =+F15 -> 33805.49 | H15: =+G15 -> 33805.49 | I15: =+H15 -> 33805.49 | J15: =+I15 -> 33805.49
A16: PRECIO DEL FILTRO DE AIRE ($) | B16: 58289.96 | C16: 58289.96 | D16: =+C16 -> 58289.96 | E16: =+D16 -> 58289.96 | F16: =+E16 -> 58289.96 | G16: =+F16 -> 58289.96 | H16: =+G16 -> 58289.96 | I16: =+H16 -> 58289.96 | J16: =+I16 -> 58289.96 | L16: SGI | M16: SGII | N16: UMA | P16: D.F. | V16: D.F. | W16: PRECIO CHASIS | X16: P.M. | Y16: TOTAL
A17: PRECIO DEL CHASIS ($) | B17: 1.2544662e+08 | C17: 1.2544662e+08 | D17: =+C17 -> 1.2544662e+08 | E17: 1.6188094e+08 | F17: =+D17 -> 1.2544662e+08 | G17: =+D17 -> 1.2544662e+08 | H17: =+G17 -> 1.2544662e+08 | I17: 1.0859084e+08 | J17: 1.0859084e+08 | L17: 98250477 | M17: 1.2678603e+08 | N17: 85048936 | P17: 1.047893e+08 | V17: GO | W17: 1.0471239e+08 | X17: 1151 | Y17: =+W17*X17 -> 1.2052396e+11
A18: PRECIO DE LA CARROCERIA ($) +Aire Acondicionado | B18: 54521302 | C18: 54521302 | D18: =+C18 -> 54521302 | E18: 88333609 | F18: =+D18 -> 54521302 | G18: =+D18 -> 54521302 | H18: =+G18 -> 54521302 | I18: 47171064 | J18: =+I18 -> 47171064 | L18: 42701380 | M18: 69183363 | N18: 36944634 | P18: 45667067 | V18: GNC | W18: 1.6442601e+08 | X18: 2 | Y18: =+W18*X18 -> 3.2885202e+08
A19: GASTOS INICIALES MATERIAL RODANTE (%) | B19: 0.02 | C19: =+B19 -> 0.02 | D19: =+C19 -> 0.02 | E19: =+D19 -> 0.02 | F19: =+E19 -> 0.02 | G19: =+F19 -> 0.02 | H19: =+G19 -> 0.02 | I19: =+H19 -> 0.02 | J19: =+I19 -> 0.02 | L19: =+L17+L18 -> 1.4095186e+08 | M19: =+M17+M18 -> 1.9596939e+08 | X19: =SUM(X17:X18) -> 1153 | Y19: =SUM(Y17:Y18) -> 1.2085282e+11 | Z19: =+Y19/X19 -> 1.0481597e+08
A20: VALOR RESIDUAL DEL VEHICULO (%) | B20: 0.05 | C20: =+B20 -> 0.05 | D20: =+C20 -> 0.05 | E20: =+D20 -> 0.05 | F20: =+E20 -> 0.05 | G20: =+F20 -> 0.05 | H20: =+G20 -> 0.05 | I20: =+H20 -> 0.05 | J20: =+I20 -> 0.05 | W20: PRECIO CARROC. | X20: P.M. | Y20: TOTAL
A21: VALOR DEPRECIABLE DEL CHASIS ($) | B21: =+(B17-6*(B8))*(1-B20) -> 1.1384789e+08 | C21: =+(C17-6*(C8))*(1-C20) -> 1.1384789e+08 | D21: =+(D17-6*(D8))*(1-D20) -> 1.1384789e+08 | E21: =+(E17-6*(E8))*(1-E20) -> 1.4846049e+08 | F21: =+(F17-6*(F8))*(1-F20) -> 1.1384789e+08 | G21: =+(G17-6*(G8))*(1-G20) -> 1.1384789e+08 | H21: =+(H17-6*(H8))*(1-H20) -> 1.1384789e+08 | I21: =+(I17-6*(I8))*(1-I20) -> 97834895 | J21: =+(J17-6*(J8))*(1-J20) -> 97834895 | V21: GO | W21: 45509842 | X21: 1151 | Y21: =+W21*X21 -> 5.2381828e+10
A22: VALOR DEPRECIABLE DE LA CARROCERÍA ($) | B22: =+B18*(1-B20) -> 51795237 | C22: =+C18*(1-C20) -> 51795237 | D22: =+D18*(1-D20) -> 51795237 | E22: =+E18*(1-E20) -> 83916929 | F22: =+F18*(1-F20) -> 51795237 | G22: =+G18*(1-G20) -> 51795237 | H22: =+H18*(1-H20) -> 51795237 | I22: =+I18*(1-I20) -> 44812511 | J22: =+J18*(1-J20) -> 44812511 | V22: GNC | W22: 1.6767013e+08 | X22: 2 | Y22: =+W22*X22 -> 3.3534027e+08
A23: PRECIO DE CADA CONTROL TECNICO ($) Sin IVA | B23: 228468.57 | C23: 228468.57 | D23: =+C23 -> 228468.57 | E23: =+D23 -> 228468.57 | F23: =+E23 -> 228468.57 | G23: =+F23 -> 228468.57 | H23: =+G23 -> 228468.57 | I23: =+H23 -> 228468.57 | J23: =+I23 -> 228468.57 | X23: =SUM(X21:X22) -> 1153 | Y23: =SUM(Y21:Y22) -> 5.2717169e+10 | Z23: =+Y23/X23 -> 45721742
A24: COEFICIENTE DE AMORTIZACION VEHICULOS (fondo) | B24: =+(B40)/(((B40+1)^'2- EMP. REP'!B11)-1) -> 0.075867958 | C24: =+(C40)/(((C40+1)^'2- EMP. REP'!C11)-1) -> 0.052960105 | D24: =+(D40)/(((D40+1)^'2- EMP. REP'!D11)-1) -> 0.052960105 | E24: =+(E40)/(((E40+1)^'2- EMP. REP'!E11)-1) -> 0.052960105 | F24: =+(F40)/(((F40+1)^'2- EMP. REP'!F11)-1) -> 0.052960105 | G24: =+(G40)/(((G40+1)^'2- EMP. REP'!G11)-1) -> 0.052960105 | H24: =+(H40)/(((H40+1)^'2- EMP. REP'!H11)-1) -> 0.052960105 | I24: =+(I40)/(((I40+1)^'2- EMP. REP'!I11)-1) -> 0.052960105 | J24: =+(J40)/(((J40+1)^'2- EMP. REP'!J11)-1) -> 0.052960105
A25: Precio del chasis al 50% de su vida útil | B25: =+(B17/2)+(B17*$B$20/2) -> 65859477 | C25: =+(C17/2)+(C17*$B$20/2) -> 65859477 | D25: =+(D17/2)+(D17*$B$20/2) -> 65859477 | E25: =+(E17/2)+(E17*$B$20/2) -> 84987491 | F25: =+(F17/2)+(F17*$B$20/2) -> 65859477 | G25: =+(G17/2)+(G17*$B$20/2) -> 65859477 | H25: =+(H17/2)+(H17*$B$20/2) -> 65859477 | I25: =+(I17/2)+(I17*$B$20/2) -> 57010191 | J25: =+(J17/2)+(J17*$B$20/2) -> 57010191
A26: Precio de la carrocería al 50% de su vida útil | B26: =+(B18/2)+(B18*$B$20/2) -> 28623684 | C26: =+(C18/2)+(C18*$B$20/2) -> 28623684 | D26: =+(D18/2)+(D18*$B$20/2) -> 28623684 | E26: =+(E18/2)+(E18*$B$20/2) -> 46375145 | F26: =+(F18/2)+(F18*$B$20/2) -> 28623684 | G26: =+(G18/2)+(G18*$B$20/2) -> 28623684 | H26: =+(H18/2)+(H18*$B$20/2) -> 28623684 | I26: =+(I18/2)+(I18*$B$20/2) -> 24764808 | J26: =+(J18/2)+(J18*$B$20/2) -> 24764808
A27: PREMIO SEGURO RESPONSABILIDAD CIVIL ($/Año) | B27: =+B28*12 -> 4279151.5 | C27: =+C28*12 -> 4279151.5 | D27: =+D28*12 -> 4279151.5 | E27: =+E28*12 -> 4279151.5 | F27: =+F28*12 -> 4279151.5 | G27: =+G28*12 -> 4279151.5 | H27: =+H28*12 -> 4279151.5 | I27: =+I28*12 -> 4279151.5 | J27: =+J28*12 -> 4279151.5
A28: PREMIO SEGURO RESPONSABILIDAD CIVIL ($/mes) | B28: 356595.96 | C28: 356595.96 | D28: =+C28 -> 356595.96 | E28: =+D28 -> 356595.96 | F28: =+E28 -> 356595.96 | G28: =+F28 -> 356595.96 | H28: =+G28 -> 356595.96 | I28: =+H28 -> 356595.96 | J28: =+I28 -> 356595.96
A29: COSTO ANUAL DE FRANQUICIA POR VEHÍCULO ($) | B29: =+B27 -> 4279151.5 | C29: =+C27 -> 4279151.5 | D29: =+D27 -> 4279151.5 | E29: =+E27 -> 4279151.5 | F29: =+F27 -> 4279151.5 | G29: =+G27 -> 4279151.5 | H29: =+H27 -> 4279151.5 | I29: =+I27 -> 4279151.5 | J29: =+J27 -> 4279151.5
A30: COEFICIENTE DE SEGURO DE CHASIS / VALOR ASEGURADO | B30: 0.025 | C30: =+B30 -> 0.025 | D30: =+C30 -> 0.025 | E30: =+D30 -> 0.025 | F30: =+E30 -> 0.025 | G30: =+F30 -> 0.025 | H30: =+G30 -> 0.025 | I30: =+H30 -> 0.025 | J30: =+I30 -> 0.025
A31: COEFICIENTE DE SEGURO DE CARROCERÍA / VALOR ASEGURADO | B31: 0.025 | C31: =+B31 -> 0.025 | D31: =+C31 -> 0.025 | E31: =+D31 -> 0.025 | F31: =+E31 -> 0.025 | G31: =+F31 -> 0.025 | H31: =+G31 -> 0.025 | I31: =+H31 -> 0.025 | J31: =+I31 -> 0.025
A32: Valor asegurado / Valor chasis depreciable | B32: 0.6 | C32: =+B32 -> 0.6 | D32: =+C32 -> 0.6 | E32: =+D32 -> 0.6 | F32: =+E32 -> 0.6 | G32: =+F32 -> 0.6 | H32: =+G32 -> 0.6 | I32: =+H32 -> 0.6 | J32: =+I32 -> 0.6
A33: Valor asegurado / Valor carrocería depreciable | B33: 0.6 | C33: =+B33 -> 0.6 | D33: =+C33 -> 0.6 | E33: =+D33 -> 0.6 | F33: =+E33 -> 0.6 | G33: =+F33 -> 0.6 | H33: =+G33 -> 0.6 | I33: =+H33 -> 0.6 | J33: =+I33 -> 0.6
A34: COSTO ANUAL SEGURO DEL CHASIS ($/año) | B34: =+B17*B30*B32 -> 1881699.3 | C34: =+C17*C30*C32 -> 1881699.3 | D34: =+D17*D30*D32 -> 1881699.3 | E34: =+E17*E30*E32 -> 2428214 | F34: =+F17*F30*F32 -> 1881699.3 | G34: =+G17*G30*G32 -> 1881699.3 | H34: =+H17*H30*H32 -> 1881699.3 | I34: =+I17*I30*I32 -> 1628862.6 | J34: =+J17*J30*J32 -> 1628862.6
A35: COSTO ANUAL DEL SEGURO DE CARROCERÍA ($/año) | B35: =+B18*B31*B33 -> 817819.54 | C35: =+C18*C31*C33 -> 817819.54 | D35: =+D18*D31*D33 -> 817819.54 | E35: =+E18*E31*E33 -> 1325004.1 | F35: =+F18*F31*F33 -> 817819.54 | G35: =+G18*G31*G33 -> 817819.54 | H35: =+H18*H31*H33 -> 817819.54 | I35: =+I18*I31*I33 -> 707565.96 | J35: =+J18*J31*J33 -> 707565.96
A36: VALOR DE LA PATENTE ($/Año) | B36: 0 | C36: 2500 | D36: 2500 | E36: 2500 | F36: 2500 | G36: 2046 | H36: =+G36 -> 2046 | I36: =+H36 -> 2046 | J36: =+I36 -> 2046
A37: VALOR DE LA T,N,F,T, ($/vehículo-año) | B37: 58414.88 | C37: 58414.88 | D37: =C37 -> 58414.88 | E37: =D37 -> 58414.88 | F37: =E37 -> 58414.88 | G37: 0 | H37: 0 | I37: 0 | J37: 0
A38: APORTE A ACTRANS | B38: 34.6 | C38: =+B38 -> 34.6 | D38: =+C38 -> 34.6 | E38: =+D38 -> 34.6 | F38: =+E38 -> 34.6 | G38: =+F38 -> 34.6 | H38: =+G38 -> 34.6 | I38: =+H38 -> 34.6 | J38: =+I38 -> 34.6
A39: TASA DE INTERES SOBRE EL CAPITAL INVERTIDO (%) | B39: 0.0655 | C39: 0.0655 | D39: =+C39 -> 0.0655 | E39: =+D39 -> 0.0655 | F39: =+E39 -> 0.0655 | G39: =+F39 -> 0.0655 | H39: =+G39 -> 0.0655 | I39: =+H39 -> 0.0655 | J39: =+I39 -> 0.0655
A40: TASA DE INTERES PASIVA (%) | B40: 0.06 | C40: =+B40 -> 0.06 | D40: =+C40 -> 0.06 | E40: =+D40 -> 0.06 | F40: =+E40 -> 0.06 | G40: =+F40 -> 0.06 | H40: =+G40 -> 0.06 | I40: =+H40 -> 0.06 | J40: =+I40 -> 0.06
A41: Remuneración del gerenciamiento | B41: 0.08 | C41: =+B41 -> 0.08 | D41: =+C41 -> 0.08 | E41: =+D41 -> 0.08 | F41: =+E41 -> 0.08 | G41: =+F41 -> 0.08 | H41: =+G41 -> 0.08 | I41: =+H41 -> 0.08 | J41: =+I41 -> 0.08
A42: Remuneración del gerenciamiento personal | B42: 0.04 | C42: =+B42 -> 0.04 | D42: =+C42 -> 0.04 | E42: =+D42 -> 0.04 | F42: =+E42 -> 0.04 | G42: =+F42 -> 0.04 | H42: =+G42 -> 0.04 | I42: =+H42 -> 0.04 | J42: =+I42 -> 0.04
A43: PRECIO DEL METRO CUADRADO DE PAVIMENTO ($/m²) | B43: 81323.65 | C43: 81323.65 | D43: =+C43 -> 81323.65 | E43: =+D43 -> 81323.65 | F43: =+E43 -> 81323.65 | G43: =+F43 -> 81323.65 | H43: =+G43 -> 81323.65 | I43: =+H43 -> 81323.65 | J43: =+I43 -> 81323.65
A44: PRECIO DEL METRO CUADRADO DE GARAGE ($/m²) | B44: 528603.72 | C44: 528603.72 | D44: =+C44 -> 528603.72 | E44: =+D44 -> 528603.72 | F44: 379355.42 | G44: 379355.42 | H44: 379355.42 | I44: 379355.42 | J44: 379355.42
A45: PRECIO DEL METRO CUADRADO DE ADMINIST. ($/m²) | B45: 813236.49 | C45: 813236.49 | D45: =+C45 -> 813236.49 | E45: =+D45 -> 813236.49 | F45: 583623.72 | G45: 583623.72 | H45: 583623.72 | I45: 583623.72 | J45: 583623.72
A46: PRECIO DEL METRO CUADRADO DE TERRENO ($/m²) | B46: 329123.89 | C46: 329123.89 | D46: =+C46 -> 329123.89 | E46: =+D46 -> 329123.89 | F46: 236197.6 | G46: 236197.6 | H46: 236197.6 | I46: 236197.6 | J46: 236197.6
A47: ALICUOTA IMPUESTO A LOS INGRESOS BRUTOS (%) | B47: 0.0075 | C47: 0.01129 | D47: 0.01129 | E47: 0.01129 | F47: =2*B47 -> 0.015 | G47: =+F47 -> 0.015 | H47: =+G47 -> 0.015 | I47: =+H47 -> 0.015 | J47: =+I47 -> 0.015
A48: PRECIO CAMARAS DE SEGURIDAD POR VEHÍCULO ($) | B48: 0 | C48: 0 | D48: 0 | E48: 0 | F48: 0 | G48: 191655.74 | H48: =+G48 -> 191655.74 | I48: =+H48 -> 191655.74 | J48: =+I48 -> 191655.74
A49: GASTO ANUAL EN SISTEMA DE CÁMARAS ($/vehículo-año) | B49: 0 | C49: 0 | D49: 0 | E49: 0 | F49: 0 | G49: 0 | H49: 0 | I49: =+H49 -> 0 | J49: =+I49 -> 0
A50: COSTO ANUAL CAMARAS DE SEGURIDAD ($/vehículo-año) | B50: 0 | C50: 0 | D50: 0 | E50: 0 | F50: 0 | G50: =+G48*12 -> 2299868.9 | H50: =+G50 -> 2299868.9 | I50: =+H50 -> 2299868.9 | J50: =+I50 -> 2299868.9
A52: VALUACION FISCAL / VALUACION VENAL (%) | B52: 0.66 | C52: =+B52 -> 0.66 | D52: =+C52 -> 0.66 | E52: =+D52 -> 0.66 | F52: =+E52 -> 0.66 | G52: =+F52 -> 0.66 | H52: =+G52 -> 0.66 | I52: =+H52 -> 0.66 | J52: =+I52 -> 0.66
A54: PARAMETROS DE CALCULO | B54: DF | C54: SGI | D54: SGI KM | E54: SGII | F54: INP | G54: UPA | H54: UPA KM | I54: UMA 1 | J54: UMA 2
A55: ALUMBRADO BARRIDO Y LIMPIEZA (%) | B55: 0.0032 | C55: =+B55 -> 0.0032 | D55: =+C55 -> 0.0032 | E55: =+D55 -> 0.0032 | F55: =+E55 -> 0.0032 | G55: =+F55 -> 0.0032 | H55: =+G55 -> 0.0032 | I55: =+H55 -> 0.0032 | J55: =+I55 -> 0.0032
A56: CONTRIBUCION TERRITORIAL (%) | B56: 0.0044 | C56: =+B56 -> 0.0044 | D56: =+C56 -> 0.0044 | E56: =+D56 -> 0.0044 | F56: =+E56 -> 0.0044 | G56: =+F56 -> 0.0044 | H56: =+G56 -> 0.0044 | I56: =+H56 -> 0.0044 | J56: =+I56 -> 0.0044
A57: PAVIMENTOS Y ACERAS (%) | B57: 0.0025 | C57: =+B57 -> 0.0025 | D57: =+C57 -> 0.0025 | E57: =+D57 -> 0.0025 | F57: =+E57 -> 0.0025 | G57: =+F57 -> 0.0025 | H57: =+G57 -> 0.0025 | I57: =+H57 -> 0.0025 | J57: =+I57 -> 0.0025
A58: COSTO GASTO GENERAL / KM BASE 1983 | B58: 0.03 | C58: =+B58 -> 0.03 | D58: =+C58 -> 0.03 | E58: =+D58 -> 0.03 | F58: =+E58 -> 0.03 | G58: =+F58 -> 0.03 | H58: =+G58 -> 0.03 | I58: =+H58 -> 0.03 | J58: =+I58 -> 0.03
A59: VALOR VEHICULO 5 AÑOS/VALOR VEHICULO 0 KM | B59: =+(1+B20)/2 -> 0.525 | C59: =+(1+C20)/2 -> 0.525 | D59: =+(1+D20)/2 -> 0.525 | E59: =+(1+E20)/2 -> 0.525 | F59: =+(1+F20)/2 -> 0.525 | G59: =+(1+G20)/2 -> 0.525 | H59: =+(1+H20)/2 -> 0.525 | I59: =+(1+I20)/2 -> 0.525 | J59: =+(1+J20)/2 -> 0.525
A60: TASA DE INTERES EN FINANCIACION (%) | B60: 0.17 | C60: =+B60 -> 0.17 | D60: =+C60 -> 0.17 | E60: =+D60 -> 0.17 | F60: =+E60 -> 0.17 | G60: =+F60 -> 0.17 | H60: =+G60 -> 0.17 | I60: =+H60 -> 0.17 | J60: =+I60 -> 0.17
A61: PORCENTAJE FINANCIACION EN COMPRA 0 KM,(%) | B61: 0.35 | C61: =+B61 -> 0.35 | D61: =+C61 -> 0.35 | E61: =+D61 -> 0.35 | F61: =+E61 -> 0.35 | G61: =+F61 -> 0.35 | H61: =+G61 -> 0.35 | I61: =+H61 -> 0.35 | J61: =+I61 -> 0.35

Sheet 5.A SALDO A FAVOR IVA
A1: ANEXO 5.A. - SALDO TECNICO A FAVOR DE IVA
A3: ITEM | B3: CONCEPTOS | C3: UNIDAD | D3: DF | E3: SGI | F3: SGI KM | G3: SGII | H3: INP | I3: UPA | J3: UPA KM | K3: UMA 1 | L3: UMA 2
A4: SALDO TÉCNICO A FAVOR DEL IVA | B4: IVA Débito fiscal | C4: $/año por línea | D4: =+D14 -> 4.1866126e+08 | E4: =+E14 -> 3.902706e+08 | F4: =+F14 -> 1.0851388e+09 | G4: =+G14 -> 1.0284234e+09 | H4: =+H14 -> 2.9683915e+08 | I4: =+I14 -> 2.7329956e+08 | J4: =+J14 -> 3.5725104e+08 | K4: =+K14 -> 2.2307633e+08 | L4: =+L14 -> 1.2349558e+08
A5: SALDO TÉCNICO A FAVOR DEL IVA | B5: IVA Crédito fiscal | C5: $/año por línea | D5: =+D36 -> 1.0827063e+09 | E5: =+E36 -> 1.2396815e+09 | F5: =+F36 -> 3.8142894e+09 | G5: =+G36 -> 2.8692793e+09 | H5: =+H36 -> 3.4630695e+08 | I5: =+I36 -> 7.1629497e+08 | J5: =+J36 -> 1.0264261e+09 | K5: =+K36 -> 5.4735564e+08 | L5: =+L36 -> 3.4616706e+08
A6: SALDO TÉCNICO A FAVOR DEL IVA | B6: SALDO TÉCNICO | C6: $/año / empresa | D6: =+(D4-D5)*'5-PRECIOS SIN IVA'!B40 -> -39842700 | E6: =+(E4-E5)*'5-PRECIOS SIN IVA'!C40 -> -50964657 | F6: =+(F4-F5)*'5-PRECIOS SIN IVA'!D40 -> -1.6374903e+08 | G6: =+(G4-G5)*'5-PRECIOS SIN IVA'!E40 -> -1.1045135e+08 | H6: =+(H4-H5)*'5-PRECIOS SIN IVA'!F40 -> -2968067.9 | I6: =+(I4-I5)*'5-PRECIOS SIN IVA'!G40 -> -26579725 | J6: =+(J4-J5)*'5-PRECIOS SIN IVA'!H40 -> -40150503 | K6: =+(K4-K5)*'5-PRECIOS SIN IVA'!I40 -> -19456758 | L6: =+(L4-L5)*'5-PRECIOS SIN IVA'!J40 -> -13360289
A7: SALDO TÉCNICO A FAVOR DEL IVA | B7: RESULTADO DE LA POSICIÓN | D7: Saldo a favor | E7: Saldo a favor | F7: Saldo a favor | G7: Saldo a favor | H7: Saldo a favor | I7: Saldo a favor | J7: Saldo a favor | K7: Saldo a favor | L7: Saldo a favor
A8: SALDO TÉCNICO A FAVOR DEL IVA | B8: SALDO TÉCNICO | C8: $/km | D8: =-D6/'2- EMP. REP'!B5 -> 14.178225 | E8: =-E6/'2- EMP. REP'!C5 -> 13.448899 | F8: =-F6/'2- EMP. REP'!D5 -> 12.252906 | G8: =-G6/'2- EMP. REP'!E5 -> 10.492457 | H8: =-H6/'2- EMP. REP'!F5 -> 1.9442437 | I8: =-I6/'2- EMP. REP'!G5 -> 10.577387 | J8: =-J6/'2- EMP. REP'!H5 -> 10.033136 | K8: =-K6/'2- EMP. REP'!I5 -> 9.9132817 | L8: =-L6/'2- EMP. REP'!J5 -> 10.457359
A9: IVA DEBITO FISCAL | B9: Recaudación Anual | C9: $ | D9: =+'7-CALCULO TARIFARIO'!B23 -> 132177340882 | E9: =+'7-CALCULO TARIFARIO'!C23 -> 394284812368 | F9: =+'7-CALCULO TARIFARIO'!D23 -> 34259382336 | G9: =+'7-CALCULO TARIFARIO'!E23 -> 54114661209 | H9: =+'7-CALCULO TARIFARIO'!F23 -> 31238787108 | I9: =+'7-CALCULO TARIFARIO'!G23 -> 310624476947 | J9: =+'7-CALCULO TARIFARIO'!H23 -> 78952479202 | K9: =+'7-CALCULO TARIFARIO'!I23 -> 183113802602 | L9: =+'7-CALCULO TARIFARIO'!J23 -> 63682555003
A10: IVA DEBITO FISCAL | B10: alic50%=Alícuota IVA al 50 % | C10: % | D10: 0.105 | E10: =+D10 -> 0.105 | F10: =+E10 -> 0.105 | G10: =+F10 -> 0.105 | H10: =+G10 -> 0.105 | I10: =+H10 -> 0.105 | J10: =+I10 -> 0.105 | K10: =+J10 -> 0.105 | L10: =+K10 -> 0.105
A11: IVA DEBITO FISCAL | B11: Cantidad de Líneas | D11: =+'7-CALCULO TARIFARIO'!B6 -> 30 | E11: =+'7-CALCULO TARIFARIO'!C6 -> 96 | F11: =+'7-CALCULO TARIFARIO'!D6 -> 3 | G11: =+'7-CALCULO TARIFARIO'!E6 -> 5 | H11: =+'7-CALCULO TARIFARIO'!F6 -> 10 | I11: =+'7-CALCULO TARIFARIO'!G6 -> 108 | J11: =+'7-CALCULO TARIFARIO'!H6 -> 21 | K11: =+'7-CALCULO TARIFARIO'!I6 -> 78 | L11: =+'7-CALCULO TARIFARIO'!J6 -> 49
A12: IVA DEBITO FISCAL | B12: Ingresos por Publicidad Anual sin IVA | C12: $ | D12: 0 | E12: 0 | F12: 0 | G12: 0 | H12: 0 | I12: 0 | J12: 0 | K12: 0 | L12: 0
A13: IVA DEBITO FISCAL | B13: alicgral=Alícuota general IVA | C13: % | D13: 0.21 | E13: =+D13 -> 0.21 | F13: =+E13 -> 0.21 | G13: =+F13 -> 0.21 | H13: =+G13 -> 0.21 | I13: =+H13 -> 0.21 | J13: =+I13 -> 0.21 | K13: =+J13 -> 0.21 | L13: =+K13 -> 0.21
A14: IVA DEBITO FISCAL | B14: IVA DEBITO FISCAL | D14: =+(D9-D9/1.105)/D11 -> 4.1866126e+08 | E14: =+(E9-E9/1.105)/E11 -> 3.902706e+08 | F14: =+(F9-F9/1.105)/F11 -> 1.0851388e+09 | G14: =+(G9-G9/1.105)/G11 -> 1.0284234e+09 | H14: =+(H9-H9/1.105)/H11 -> 2.9683915e+08 | I14: =+(I9-I9/1.105)/I11 -> 2.7329956e+08 | J14: =+(J9-J9/1.105)/J11 -> 3.5725104e+08 | K14: =+(K9-K9/1.105)/K11 -> 2.2307633e+08 | L14: =+(L9-L9/1.105)/L11 -> 1.2349558e+08
A15: IVA CREDITO FISCAL | B15: ivacpcombust=IVA por la compra de combustible | C15: $/Lt | D15: =+'8- COSTO COMBUST'!B20-'8- COSTO COMBUST'!B18-'8- COSTO COMBUST'!B14 -> 309.07007 | E15: =+'8- COSTO COMBUST'!D20-'8- COSTO COMBUST'!D18-'8- COSTO COMBUST'!D14 -> 309.07007 | F15: =+E15 -> 309.07007 | G15: =+F15 -> 309.07007 | H15: =+G15 -> 309.07007 | I15: =+H15 -> 309.07007 | J15: =+I15 -> 309.07007 | K15: =+J15 -> 309.07007 | L15: =+K15 -> 309.07007
A16: IVA CREDITO FISCAL | B16: ivacpcombust(Acuerdo)=IVA por la compra de combustible. Acuerdo | C16: $/Lt | D16: =+'8- COSTO COMBUST'!C20-'8- COSTO COMBUST'!C18-'8- COSTO COMBUST'!C14 -> 0 | E16: =+'8- COSTO COMBUST'!E20-'8- COSTO COMBUST'!E18-'8- COSTO COMBUST'!E14 -> 305.59899 | F16: =+E16 -> 305.59899 | G16: =+F16 -> 305.59899 | H16: =+G16 -> 305.59899 | I16: =+H16 -> 305.59899 | J16: =+I16 -> 305.59899 | K16: =+J16 -> 305.59899 | L16: =+K16 -> 305.59899
A17: IVA CREDITO FISCAL | B17: ivaflete=IVA por flete | C17: $/Lt | D17: =+'8- COSTO COMBUST'!D15*0.21 -> 0.02709 | E17: =+'8- COSTO COMBUST'!C15*0.21 -> 0 | F17: =+'8- COSTO COMBUST'!E15*0.21 -> 0.02709 | G17: =+'8- COSTO COMBUST'!F15*0.21 -> 0.02709 | H17: =+'8- COSTO COMBUST'!G15*0.21 -> 0.02709 | I17: =+'8- COSTO COMBUST'!H15*0.21 -> 0.02709 | J17: =+'8- COSTO COMBUST'!I15*0.21 -> 0.02709 | K17: =+'8- COSTO COMBUST'!J15*0.21 -> 0.02709 | L17: =+'8- COSTO COMBUST'!K15*0.21 -> 0.02709
A18: IVA CREDITO FISCAL | B18: Ckm= Consumo de combustible por km. Recorrido | C18: Lt/Km | D18: =+'8- COSTO COMBUST'!B16 -> 0.6327615 | E18: =+'8- COSTO COMBUST'!E16 -> 0.51478549 | F18: =+'8- COSTO COMBUST'!F16 -> 0.48390863 | G18: =+'8- COSTO COMBUST'!G16 -> 0.37991355 | H18: =+'8- COSTO COMBUST'!H16 -> 0.33488895 | I18: =+'8- COSTO COMBUST'!I16 -> 0.42428741 | J18: =+'8- COSTO COMBUST'!J16 -> 0.43341033 | K18: =+'8- COSTO COMBUST'!K16 -> 0.41255866 | L18: =+'8- COSTO COMBUST'!L16 -> 0.41255867
A19: IVA CREDITO FISCAL | B19: ivapcombustibletotal=IVA por la compra de combustible + Acuerdo + Flete | C19: $/km | D19: =(+D15+D17)*D18 -> 195.58478 | E19: =(+E15*0.1+E16*0.9+E17)*E18 -> 157.49661 | F19: =(+F15*0.1+F16*0.9+F17)*F18 -> 148.06307 | G19: =(+G15*0.1+G16*0.9+G17)*G18 -> 116.24336 | H19: =(+H15*0.1+H16*0.9+H17)*H18 -> 102.46704 | I19: =(+I15*0.1+I16*0.9+I17)*I18 -> 129.82057 | J19: =(+J15*0.1+J16*0.9+J17)*J18 -> 132.61194 | K19: =(+K15*0.1+K16*0.9+K17)*K18 -> 126.23189 | L19: =(+L15*0.1+L16*0.9+L17)*L18 -> 126.23189
A20: IVA CREDITO FISCAL | B20: cpralubr=Compra de lubricantes y filtros | C20: $/km | D20: =+'1-COSTO X KM'!B5 -> 21.787509 | E20: =+'1-COSTO X KM'!C5 -> 21.787509 | F20: =+E20 -> 21.787509 | G20: =+F20 -> 21.787509 | H20: =+G20 -> 21.787509 | I20: =+H20 -> 21.787509 | J20: =+I20 -> 21.787509 | K20: =+J20 -> 21.787509 | L20: =+K20 -> 21.787509
A21: IVA CREDITO FISCAL | B21: cpraneum=Compra y recapado de neumáticos | C21: $/km | D21: =+'1-COSTO X KM'!B6 -> 79.139001 | E21: =+'1-COSTO X KM'!C6 -> 79.139001 | F21: =+'1-COSTO X KM'!D6 -> 79.139001 | G21: =+'1-COSTO X KM'!E6 -> 79.139001 | H21: =+'1-COSTO X KM'!F6 -> 79.139001 | I21: =+H21 -> 79.139001 | J21: =+I21 -> 79.139001 | K21: =+J21 -> 79.139001 | L21: =+K21 -> 79.139001
A22: IVA CREDITO FISCAL | B22: mantyrep=Servicio de mantenimiento y reparación | C22: $/km | D22: =+'1-COSTO X KM'!B8 -> 256.95858 | E22: =+'1-COSTO X KM'!C8 -> 236.57637 | F22: =+'1-COSTO X KM'!D8 -> 179.31954 | G22: =+'1-COSTO X KM'!E8 -> 331.63573 | H22: =+'1-COSTO X KM'!F8 -> 157.16111 | I22: =+'1-COSTO X KM'!G8 -> 211.81001 | J22: =+'1-COSTO X KM'!H8 -> 155.52701 | K22: =+'1-COSTO X KM'!I8 -> 197.02863 | L22: =+'1-COSTO X KM'!J8 -> 183.0581
A23: IVA CREDITO FISCAL | B23: 4. ENGRASE Y LAVADO | C23: $/km | D23: =+'1-COSTO X KM'!B7 -> 54.825193 | E23: =+'1-COSTO X KM'!C7 -> 54.825193 | F23: =+'1-COSTO X KM'!D7 -> 54.825193 | G23: =+F23 -> 54.825193 | H23: =+G23 -> 54.825193 | I23: =+H23 -> 54.825193 | J23: =+I23 -> 54.825193 | K23: =+J23 -> 54.825193 | L23: =+K23 -> 54.825193
A24: IVA CREDITO FISCAL | B24: peajes=Costo anual de peajes | C24: $/km | D24: 0 | E24: 0 | F24: 0 | G24: 0.14 | H24: 0.01 | I24: 0 | J24: 0 | K24: 0 | L24: 0
A25: IVA CREDITO FISCAL | B25: 18. SERVICIO DE VIGILANCIA | C25: $/km | D25: =+'1-COSTO X KM'!B41 -> 1.310824 | E25: =+'1-COSTO X KM'!C41 -> 0.97205068 | F25: =+'1-COSTO X KM'!D41 -> 0.27563327 | G25: =+'1-COSTO X KM'!E41 -> 0.349927 | H25: =+'1-COSTO X KM'!F41 -> 2.4129491 | I25: =+'1-COSTO X KM'!G41 -> 1.4658827 | J25: =+'1-COSTO X KM'!H41 -> 0.92048564 | K25: =+'1-COSTO X KM'!I41 -> 1.8768011 | L25: =+'1-COSTO X KM'!J41 -> 2.8832178
A26: IVA CREDITO FISCAL | B26: seguros=Costo anual seguros | C26: $/km | D26: =+'1-COSTO X KM'!B14 -> 207.38517 | E26: =+'1-COSTO X KM'!C14 -> 190.93517 | F26: =+'1-COSTO X KM'!D14 -> 144.72455 | G26: =+'1-COSTO X KM'!E14 -> 104.32364 | H26: =+'1-COSTO X KM'!F14 -> 126.841 | I26: =+'1-COSTO X KM'!G14 -> 170.94683 | J26: =+'1-COSTO X KM'!H14 -> 125.52216 | K26: =+'1-COSTO X KM'!I14 -> 178.69632 | L26: =+'1-COSTO X KM'!J14 -> 166.02566
A27: IVA CREDITO FISCAL | B27: gg=Gastos generales anuales | C27: $/km | D27: =+'1-COSTO X KM'!B44 -> 109.12256 | E27: =+'1-COSTO X KM'!C44 -> 97.325426 | F27: =+'1-COSTO X KM'!D44 -> 78.286689 | G27: =+'1-COSTO X KM'!E44 -> 65.774943 | H27: =+'1-COSTO X KM'!F44 -> 66.417528 | I27: =+'1-COSTO X KM'!G44 -> 86.39985 | J27: =+'1-COSTO X KM'!H44 -> 69.349055 | K27: =+'1-COSTO X KM'!I44 -> 87.268446 | L27: =+'1-COSTO X KM'!J44 -> 82.687214
A28: IVA CREDITO FISCAL | B28: 15. CONTROL TECNICO DEL MATERIAL RODANTE | C28: $/km | D28: =+'1-COSTO X KM'!B38 -> 8.4174351 | E28: =+'1-COSTO X KM'!C38 -> 7.7497557 | F28: =+'1-COSTO X KM'!D38 -> 5.8741399 | G28: =+'1-COSTO X KM'!E38 -> 3.8719299 | H28: =+'1-COSTO X KM'!F38 -> 5.1482751 | I28: =+'1-COSTO X KM'!G38 -> 6.9384608 | J28: =+'1-COSTO X KM'!H38 -> 5.0947455 | K28: =+'1-COSTO X KM'!I38 -> 7.494722 | L28: =+'1-COSTO X KM'!J38 -> 6.9633006
A29: IVA CREDITO FISCAL | B29: valoramortbsuso=Valor amortizable bienes de uso | C29: $/km | D29: =+'1-COSTO X KM'!B29+'1-COSTO X KM'!B30 -> 7.293586 | E29: =+'1-COSTO X KM'!C29+'1-COSTO X KM'!C30 -> 6.7150514 | F29: =+'1-COSTO X KM'!D29+'1-COSTO X KM'!D30 -> 5.0898574 | G29: =+'1-COSTO X KM'!E29+'1-COSTO X KM'!E30 -> 4.6645124 | H29: =+'1-COSTO X KM'!F29+'1-COSTO X KM'!F30 -> 4.4609061 | I29: =+'1-COSTO X KM'!G29+'1-COSTO X KM'!G30 -> 6.0120761 | J29: =+'1-COSTO X KM'!H29+'1-COSTO X KM'!H30 -> 4.4145234 | K29: =+'1-COSTO X KM'!I29+'1-COSTO X KM'!I30 -> 5.6206041 | L29: =+'1-COSTO X KM'!J29+'1-COSTO X KM'!J30 -> 5.222069
A30: IVA CREDITO FISCAL | B30: valorconseredif=Valor conservación edificios | C30: $/km | D30: =+'1-COSTO X KM'!B27 -> 2.435158 | E30: =+'1-COSTO X KM'!C27 -> 2.2419989 | F30: =+'1-COSTO X KM'!D27 -> 1.6993845 | G30: =+'1-COSTO X KM'!E27 -> 1.2011513 | H30: =+'1-COSTO X KM'!F27 -> 1.3275737 | I30: =+'1-COSTO X KM'!G27 -> 1.7892047 | J30: =+'1-COSTO X KM'!H27 -> 1.3137701 | K30: =+'1-COSTO X KM'!I27 -> 1.9326465 | L30: =+'1-COSTO X KM'!J27 -> 1.7956101
A31: IVA CREDITO FISCAL | B31: valoramortvehic=Valor amortizable de vehículos | C31: $/km | D31: =+'1-COSTO X KM'!B11 -> 309.33279 | E31: =+'1-COSTO X KM'!C11 -> 219.074 | F31: =+'1-COSTO X KM'!D11 -> 166.05315 | G31: =+'1-COSTO X KM'!E11 -> 153.40363 | H31: =+'1-COSTO X KM'!F11 -> 145.53404 | I31: =+'1-COSTO X KM'!G11 -> 196.13991 | J31: =+'1-COSTO X KM'!H11 -> 144.02084 | K31: =+'1-COSTO X KM'!I11 -> 182.44684 | L31: =+'1-COSTO X KM'!J11 -> 169.51024
A32: IVA CREDITO FISCAL | B32: Kilómetros anuales | C32: km anuales | D32: =+'7-CALCULO TARIFARIO'!B17 -> 84303992 | E32: =+'7-CALCULO TARIFARIO'!C17 -> 363792391 | F32: =+'7-CALCULO TARIFARIO'!D17 -> 40092293 | G32: =+'7-CALCULO TARIFARIO'!E17 -> 52633692 | H32: =+'7-CALCULO TARIFARIO'!F17 -> 15265925 | I32: =+'7-CALCULO TARIFARIO'!G17 -> 271391239 | J32: =+'7-CALCULO TARIFARIO'!H17 -> 84037585 | K32: =+'7-CALCULO TARIFARIO'!I17 -> 153090289 | L32: =+'7-CALCULO TARIFARIO'!J17 -> 62602247
A33: IVA CREDITO FISCAL | B33: Cantidad de Líneas | D33: =+'7-CALCULO TARIFARIO'!B6 -> 30 | E33: =+'7-CALCULO TARIFARIO'!C6 -> 96 | F33: =+'7-CALCULO TARIFARIO'!D6 -> 3 | G33: =+'7-CALCULO TARIFARIO'!E6 -> 5 | H33: =+'7-CALCULO TARIFARIO'!F6 -> 10 | I33: =+'7-CALCULO TARIFARIO'!G6 -> 108 | J33: =+'7-CALCULO TARIFARIO'!H6 -> 21 | K33: =+'7-CALCULO TARIFARIO'!I6 -> 78 | L33: =+'7-CALCULO TARIFARIO'!J6 -> 49
A34: IVA CREDITO FISCAL | B34: alic50%=Alícuota IVA al 50 % | C34: % | D34: 0.105 | E34: =+D34 -> 0.105 | F34: =+E34 -> 0.105 | G34: =+F34 -> 0.105 | H34: =+G34 -> 0.105 | I34: =+H34 -> 0.105 | J34: =+I34 -> 0.105 | K34: =+J34 -> 0.105 | L34: =+K34 -> 0.105
A35: IVA CREDITO FISCAL | B35: alicgral=Alícuota general IVA | C35: % | D35: 0.21 | E35: =+D35 -> 0.21 | F35: =+E35 -> 0.21 | G35: =+F35 -> 0.21 | H35: =+G35 -> 0.21 | I35: =+H35 -> 0.21 | J35: =+I35 -> 0.21 | K35: =+J35 -> 0.21 | L35: =+K35 -> 0.21
A36: IVA CREDITO FISCAL | B36: IVA CREDITO FISCAL | D36: =(SUM(D20:D30)*0.21+D31*0.105+D19)*D32/D33 -> 1.0827063e+09 | E36: =(SUM(E20:E30)*0.21+E31*0.105+E19)*E32/E33 -> 1.2396815e+09 | F36: =(SUM(F20:F30)*0.21+F31*0.105+F19)*F32/F33 -> 3.8142894e+09 | G36: =(SUM(G20:G30)*0.21+G31*0.105+G19)*G32/G33 -> 2.8692793e+09 | H36: =(SUM(H20:H30)*0.21+H31*0.105+H19)*H32/H33 -> 3.4630695e+08 | I36: =(SUM(I20:I30)*0.21+I31*0.105+I19)*I32/I33 -> 7.1629497e+08 | J36: =(SUM(J20:J30)*0.21+J31*0.105+J19)*J32/J33 -> 1.0264261e+09 | K36: =(SUM(K20:K30)*0.21+K31*0.105+K19)*K32/K33 -> 5.4735564e+08 | L36: =(SUM(L20:L30)*0.21+L31*0.105+L19)*L32/L33 -> 3.4616706e+08

Sheet 6- IMPUESTOS
A1: ANEXO 6 - IMPUESTOS
A2: Impuesto al cheque | B2: DF $/Km | C2: SGI $/Km | D2: SGI KM $/Km | E2: SGII $/Km | F2: INP $/Km | G2: UPA $/Km | H2: UPA KM $/Km | I2: UMA 1 $/Km | J2: UMA 2 $/Km
A3: Depósitos | B3: =+'1-COSTO X KM'!B45*0.006 -> 21.824512 | C3: =+'1-COSTO X KM'!C45*0.006 -> 19.465085 | D3: =+'1-COSTO X KM'!D45*0.006 -> 15.657338 | E3: =+'1-COSTO X KM'!E45*0.006 -> 13.154989 | F3: =+'1-COSTO X KM'!F45*0.006 -> 13.283506 | G3: =+'1-COSTO X KM'!G45*0.006 -> 17.27997 | H3: =+'1-COSTO X KM'!H45*0.006 -> 13.869811 | I3: =+'1-COSTO X KM'!I45*0.006 -> 17.453689 | J3: =+'1-COSTO X KM'!J45*0.006 -> 16.537443
A4: Extracciones | B4: =+B3 -> 21.824512 | C4: =+C3 -> 19.465085 | D4: =+D3 -> 15.657338 | E4: =+E3 -> 13.154989 | F4: =+F3 -> 13.283506 | G4: =+G3 -> 17.27997 | H4: =+H3 -> 13.869811 | I4: =+I3 -> 17.453689 | J4: =+J3 -> 16.537443

Sheet 7-CALCULO TARIFARIO
A1: ANEXO 7 - DATOS BÁSICOS PARA EL CÁLCULO TARIFARIO
A3: Indicador Cantidad de líneas
A4: Unidad
A5: Grupo tarifario | B5: DF | C5: SGI | D5: SGI KM | E5: SGII | F5: INP | G5: UPA | H5: UPA KM | I5: UMA 1 | J5: UMA 2 | K5: TOTAL
B6: 30 | C6: 96 | D6: 3 | E6: 5 | F6: 10 | G6: 108 | H6: 21 | I6: 78 | J6: 49 | K6: =SUM(B6:J6) -> 400
A8: Indicador Pasajeros Transportados SUBE
A9: Unidad
A10: Grupo tarifario | B10: DF | C10: SGI | D10: SGI KM | E10: SGII | F10: INP | G10: UPA | H10: UPA KM | I10: UMA 1 | J10: UMA 2
A11: Total Anual Proyectado | B11: 290382450 | C11: 989385618 | D11: 70045340 | E11: 45626084 | F11: 17163704 | G11: 755337038 | H11: 145045944 | I11: 477430257 | J11: 156461382 | K11: TOTAL
A12: Promedio mensual | B12: =+B11/12 -> 24198538 | C12: =+C11/12 -> 82448802 | D12: =+D11/12 -> 5837111.7 | E12: =+E11/12 -> 3802173.7 | F12: =+F11/12 -> 1430308.7 | G12: =+G11/12 -> 62944753 | H12: =+H11/12 -> 12087162 | I12: =+I11/12 -> 39785855 | J12: =+J11/12 -> 13038448 | K12: =SUM(B12:J12) -> 2.4557315e+08
A14: Indicador Kilómetros recorridos
A15: Unidad
A16: Grupo tarifario | B16: DF | C16: SGI | D16: SGI KM | E16: SGII | F16: INP | G16: UPA | H16: UPA KM | I16: UMA 1 | J16: UMA 2 | K16: TOTAL
A17: Total Anual | B17: 84303992 | C17: 363792391 | D17: 40092293 | E17: 52633692 | F17: 15265925 | G17: 271391239 | H17: 84037585 | I17: 153090289 | J17: 62602247 | K17: =SUM(B17:J17) -> 1127209653
A18: Datos GPS SUBE | B18: =+B17/12 -> 7025332.7 | C18: =+C17/12 -> 30316033 | D18: =+D17/12 -> 3341024.4 | E18: =+E17/12 -> 4386141 | F18: =+F17/12 -> 1272160.4 | G18: =+G17/12 -> 22615937 | H18: =+H17/12 -> 7003132.1 | I18: =+I17/12 -> 12757524 | J18: =+J17/12 -> 5216853.9 | K18: =SUM(B18:J18) -> 93934138
A20: Indicador Recaudación SUBE
A21: Unidad
A22: Grupo tarifario | B22: DF | C22: SGI | D22: SGI KM | E22: SGII | F22: INP | G22: UPA | H22: UPA KM | I22: UMA 1 | J22: UMA 2 | K22: TOTAL
A23: Total Anual Proyectado | B23: 132177340882 | C23: 394284812368 | D23: 34259382336 | E23: 54114661209 | F23: 31238787108 | G23: 310624476947 | H23: 78952479202 | I23: 183113802602 | J23: 63682555003 | K23: =SUM(B23:J23) -> 1282448297657
A24: Promedio mensual | B24: =+B23/12 -> 1.1014778e+10 | C24: =+C23/12 -> 3.2857068e+10 | D24: =+D23/12 -> 2854948528 | E24: =+E23/12 -> 4.5095551e+09 | F24: =+F23/12 -> 2603232259 | G24: =+G23/12 -> 2.5885373e+10 | H24: =+H23/12 -> 6.5793733e+09 | I24: =+I23/12 -> 1.5259484e+10 | J24: =+J23/12 -> 5.3068796e+09 | K24: =SUM(B24:J24) -> 1.0687069e+11
A25: Ingreso Medio por pasajero | B25: =+B24/B12 -> 455.18364 | C25: =+C24/C12 -> 398.5148 | D25: =+D24/D12 -> 489.10295 | E25: =+E24/E12 -> 1186.0466 | F25: =+F24/F12 -> 1820.0493 | G25: =+G24/G12 -> 411.23957 | H25: =+H24/H12 -> 544.32738 | I25: =+I24/I12 -> 383.54042 | J25: =+J24/J12 -> 407.01772
A27: Indicador Parque móvil
A28: Unidad
A29: Grupo tarifario | B29: DF | C29: SGI | D29: SGI KM | E29: SGII | F29: INP | G29: UPA | H29: UPA KM | I29: UMA 1 | J29: UMA 2 | K29: TOTAL
A30: Diciembre 2018 CNRT | B30: 1553 | C30: 6170 | D30: 515.40511 | E30: 446 | F30: 171.99999 | G30: 4120.999 | H30: 937.00001 | I30: 2511 | J30: 954.00051 | K30: =SUM(B30:J30) -> 17379.405
A32: KM MES/parque movil | B32: =+B18/B30 -> 4523.7171 | C32: =+C18/C30 -> 4913.4575 | D32: =+D18/D30 -> 6482.3269 | E32: =+E18/E30 -> 9834.3969 | F32: =+F18/F30 -> 7396.2821 | G32: =+G18/G30 -> 5487.9744 | H32: =+H18/H30 -> 7473.9936 | I32: =+I18/I30 -> 5080.6548 | J32: =+J18/J30 -> 5468.3974

Sheet 8- COSTO COMBUST
A1: ANEXO 8 - COSTO DEL COMBUSTIBLE
A2: Período Acuerdo Gasoil a Precio Diferencial
C3: DF | E3: SGI | F3: SGI KM | G3: SGII | H3: INP | I3: UPA | J3: UPA KM | K3: UMA 1 | L3: UMA 2
A4: Precio al público (1) ($/L) | B4: 1548.852 | D4: 1548.852 | E4: 20 | F4: =+E4 -> 20 | G4: =+F4 -> 20 | H4: =+G4 -> 20 | I4: =+H4 -> 20 | J4: =+I4 -> 20 | K4: =+J4 -> 20 | L4: =+K4 -> 20
A5: Alícuota de descuento/aumento | B5: -0.015 | D5: -0.015
A6: Precio final de referencia ($/L) | B6: =+B4+(B5*B4) -> 1525.6192 | D6: =+D4+(D5*D4) -> 1525.6192 | E6: =+D6-E4 -> 1505.6192 | F6: =+E6 -> 1505.6192 | G6: =+F6 -> 1505.6192 | H6: =+G6 -> 1505.6192 | I6: =+H6 -> 1505.6192 | J6: =+I6 -> 1505.6192 | K6: =+J6 -> 1505.6192 | L6: =+K6 -> 1505.6192
A7: Precio en planta (2) ($/L) | B7: 12.5835 | D7: 12.5835 | E7: =+D7 -> 12.5835 | F7: =+E7 -> 12.5835 | G7: =+F7 -> 12.5835 | H7: =+G7 -> 12.5835 | I7: =+H7 -> 12.5835 | J7: =+I7 -> 12.5835 | K7: =+J7 -> 12.5835 | L7: =+K7 -> 12.5835
A8: Impuesto a los combustibles líquidos (Icl) ($/L) | B8: 172.5717 | D8: 172.5717 | E8: =+D8 -> 172.5717 | F8: =+E8 -> 172.5717 | G8: =+F8 -> 172.5717 | H8: =+G8 -> 172.5717 | I8: =+H8 -> 172.5717 | J8: =+I8 -> 172.5717 | K8: =+J8 -> 172.5717 | L8: =+K8 -> 172.5717
A9: Impuesto al dióxido de carbono (Icd) ($/L) | B9: 19.6692 | D9: 19.6692 | E9: =+D9 -> 19.6692 | F9: =+E9 -> 19.6692 | G9: =+F9 -> 19.6692 | H9: =+G9 -> 19.6692 | I9: =+H9 -> 19.6692 | J9: =+I9 -> 19.6692 | K9: =+J9 -> 19.6692 | L9: =+K9 -> 19.6692
A10: Iva ($/L) | B10: =+(B6-(B8+B9))*0.21/1.21 -> 231.41277 | D10: =+(D6-(D8+D9))*0.21/1.21 -> 231.41277 | E10: =+(E6-(E8+E9))*0.21/1.21 -> 227.94169 | F10: =+(F6-(F8+F9))*0.21/1.21 -> 227.94169 | G10: =+(G6-(G8+G9))*0.21/1.21 -> 227.94169 | H10: =+(H6-(H8+H9))*0.21/1.21 -> 227.94169 | I10: =+(I6-(I8+I9))*0.21/1.21 -> 227.94169 | J10: =+(J6-(J8+J9))*0.21/1.21 -> 227.94169 | K10: =+(K6-(K8+K9))*0.21/1.21 -> 227.94169 | L10: =+(L6-(L8+L9))*0.21/1.21 -> 227.94169
A11: Iibc ($/L) | B11: 28.4851 | D11: 28.0983 | E11: =+(E6-(E10*0.6+SUM(E8:E10)*0.4))*0.0234 -> 28.098279 | F11: =+(F6-(F10*0.6+SUM(F8:F10)*0.4))*0.0234 -> 28.098279 | G11: =+(G6-(G10*0.6+SUM(G8:G10)*0.4))*0.0234 -> 28.098279 | H11: =+(H6-(H10*0.6+SUM(H8:H10)*0.4))*0.0234 -> 28.098279 | I11: =+(I6-(I10*0.6+SUM(I8:I10)*0.4))*0.0234 -> 28.098279 | J11: =+(J6-(J10*0.6+SUM(J8:J10)*0.4))*0.0234 -> 28.098279 | K11: =+(K6-(K10*0.6+SUM(K8:K10)*0.4))*0.0234 -> 28.098279 | L11: =+(L6-(L10*0.6+SUM(L8:L10)*0.4))*0.0234 -> 28.098279
A12: Precio sin impuesto ($/L) | B12: =+B6-SUM(B8:B11) -> 1073.4805 | D12: =+D6-SUM(D8:D11) -> 1073.8673 | E12: =+E6-SUM(E8:E11) -> 1057.3383 | F12: =+F6-SUM(F8:F11) -> 1057.3383 | G12: =+G6-SUM(G8:G11) -> 1057.3383 | H12: =+H6-SUM(H8:H11) -> 1057.3383 | I12: =+I6-SUM(I8:I11) -> 1057.3383 | J12: =+J6-SUM(J8:J11) -> 1057.3383 | K12: =+K6-SUM(K8:K11) -> 1057.3383 | L12: =+L6-SUM(L8:L11) -> 1057.3383
A13: Compensación ($/L) | E13: =+$D$12-E12 -> 16.528905 | F13: =+$D$12-F12 -> 16.528905 | G13: =+$D$12-G12 -> 16.528905 | H13: =+$D$12-H12 -> 16.528905 | I13: =+$D$12-I12 -> 16.528905 | J13: =+$D$12-J12 -> 16.528905 | K13: =+$D$12-K12 -> 16.528905 | L13: =+$D$12-L12 -> 16.528905
A14: Iclgn A Cuenta IVA | B14: -77.6573 | D14: -77.6573 | E14: =+D14 -> -77.6573 | F14: =+E14 -> -77.6573 | G14: =+F14 -> -77.6573 | H14: =+G14 -> -77.6573 | I14: =+H14 -> -77.6573 | J14: =+I14 -> -77.6573 | K14: =+J14 -> -77.6573 | L14: =+K14 -> -77.6573
A15: Flete | B15: 0.129 | D15: 0.129 | E15: =+D15 -> 0.129 | F15: =+E15 -> 0.129 | G15: =+F15 -> 0.129 | H15: =+G15 -> 0.129 | I15: =+H15 -> 0.129 | J15: =+I15 -> 0.129 | K15: =+J15 -> 0.129 | L15: =+K15 -> 0.129
A16: Consumo x Km | B16: 0.6327615 | E16: 0.51478549 | F16: 0.48390863 | G16: 0.37991355 | H16: 0.33488895 | I16: 0.42428741 | J16: 0.43341033 | K16: 0.41255866 | L16: 0.41255867
A17: % de Consumo cubierto por el cupo | B17: 0.9 | D17: 0.9 | E17: =+D17 -> 0.9 | F17: =+E17 -> 0.9 | G17: =+F17 -> 0.9 | H17: =+G17 -> 0.9 | I17: =+H17 -> 0.9 | J17: =+I17 -> 0.9 | K17: =+J17 -> 0.9 | L17: =+K17 -> 0.9
A18: Costo Final Empresas ($/L) s/IVA | B18: =+B12+B11+B9+B8+B14+B15 -> 1216.6782 | D18: =+D12+D11+D9+D8+D14+D15 -> 1216.6782 | E18: =(+E12+E11+E9+E8+E14+E15)*E17+$D$18*(1-E17) -> 1201.8021 | F18: =(+F12+F11+F9+F8+F14+F15)*F17+$D$18*(1-F17) -> 1201.8021 | G18: =(+G12+G11+G9+G8+G14+G15)*G17+$D$18*(1-G17) -> 1201.8021 | H18: =(+H12+H11+H9+H8+H14+H15)*H17+$D$18*(1-H17) -> 1201.8021 | I18: =(+I12+I11+I9+I8+I14+I15)*I17+$D$18*(1-I17) -> 1201.8021 | J18: =(+J12+J11+J9+J8+J14+J15)*J17+$D$18*(1-J17) -> 1201.8021 | K18: =(+K12+K11+K9+K8+K14+K15)*K17+$D$18*(1-K17) -> 1201.8021 | L18: =(+L12+L11+L9+L8+L14+L15)*L17+$D$18*(1-L17) -> 1201.8021
A19: Costo Final Empresas ($/Km) s/IVA | B19: =+B18*'8- COSTO COMBUST'!C16 -> 0 | E19: =+E18*'8- COSTO COMBUST'!E16 -> 618.67029 | F19: =+F18*'8- COSTO COMBUST'!F16 -> 581.56242 | G19: =+G18*'8- COSTO COMBUST'!G16 -> 456.58091 | H19: =+H18*'8- COSTO COMBUST'!H16 -> 402.47025 | I19: =+I18*'8- COSTO COMBUST'!I16 -> 509.9095 | J19: =+J18*'8- COSTO COMBUST'!J16 -> 520.87345 | K19: =+K18*'8- COSTO COMBUST'!K16 -> 495.81387 | L19: =+L18*'8- COSTO COMBUST'!L16 -> 495.81389
A20: Costo Final Empresas ($/L) c/IVA | B20: =+B18+B10 -> 1448.0909 | D20: =+D18+D10 -> 1448.0909 | E20: =+E18+E10 -> 1429.7438 | F20: =+F18+F10 -> 1429.7438 | G20: =+G18+G10 -> 1429.7438 | H20: =+H18+H10 -> 1429.7438 | I20: =+I18+I10 -> 1429.7438 | J20: =+J18+J10 -> 1429.7438 | K20: =+K18+K10 -> 1429.7438 | L20: =+L18+L10 -> 1429.7438
A21: Costo Final Empresas ($/Km) c/IVA | B21: =+B20*'8- COSTO COMBUST'!B16 -> 916.29618 | E21: =+E20*'8- COSTO COMBUST'!E16 -> 736.01137 | F21: =+F20*'8- COSTO COMBUST'!F16 -> 691.86537 | G21: =+G20*'8- COSTO COMBUST'!G16 -> 543.17905 | H21: =+H20*'8- COSTO COMBUST'!H16 -> 478.8054 | I21: =+I20*'8- COSTO COMBUST'!I16 -> 606.62229 | J21: =+J20*'8- COSTO COMBUST'!J16 -> 619.66574 | K21: =+K20*'8- COSTO COMBUST'!K16 -> 589.85319 | L21: =+L20*'8- COSTO COMBUST'!L16 -> 589.85321
A22: Compensación $/Km | B22: =+$B18*'8- COSTO COMBUST'!B16-B19 -> 769.86709 | E22: =+$D18*'8- COSTO COMBUST'!E16-E19 -> 7.6579659 | F22: =+$D18*'8- COSTO COMBUST'!F16-F19 -> 7.1986408 | G22: =+$D18*'8- COSTO COMBUST'!G16-G19 -> 5.6516065 | H22: =+$D18*'8- COSTO COMBUST'!H16-H19 -> 4.9818191 | I22: =+$D18*'8- COSTO COMBUST'!I16-I19 -> 6.3117135 | J22: =+$D18*'8- COSTO COMBUST'!J16-J19 -> 6.4474264 | K22: =+$D18*'8- COSTO COMBUST'!K16-K19 -> 6.1372363 | L22: =+$D18*'8- COSTO COMBUST'!L16-L19 -> 6.1372364
A24: Indicador | C24: DF | E24: SGI | F24: SGI KM | G24: SGII | H24: INP | I24: UPA | J24: UPA KM | K24: UMA 1 | L24: UMA 2
A25: IPK | C25: =+'2- EMP. REP'!B14 -> 3.4444686 | E25: =+'2- EMP. REP'!C14 -> 2.7196435 | F25: =+'2- EMP. REP'!D14 -> 1.7471024 | G25: =+'2- EMP. REP'!E14 -> 0.86686079 | H25: =+'2- EMP. REP'!F14 -> 1.1243147 | I25: =+'2- EMP. REP'!G14 -> 2.7832035 | J25: =+'2- EMP. REP'!H14 -> 1.7259652 | K25: =+'2- EMP. REP'!I14 -> 3.1186188 | L25: =+'2- EMP. REP'!J14 -> 2.4992934
A26: Compensación por pasajero | C26: =+C22/C25 -> 0 | E26: =+E22/E25 -> 2.8157977 | F26: =+F22/F25 -> 4.1203314 | G26: =+G22/G25 -> 6.5196241 | H26: =+H22/H25 -> 4.4309828 | I26: =+I22/I25 -> 2.2677873 | J26: =+J22/J25 -> 3.7355484 | K26: =+K22/K25 -> 1.9679341 | L26: =+L22/L25 -> 2.4555886
A29: Compensación $/Km c/IVA | C29: =+C22*1.21 -> 0 | E29: =+E22*1.21 -> 9.2661388 | F29: =+F22*1.21 -> 8.7103553 | G29: =+G22*1.21 -> 6.8384439 | H29: =+H22*1.21 -> 6.0280011 | I29: =+I22*1.21 -> 7.6371733 | J29: =+J22*1.21 -> 7.8013859 | K29: =+K22*1.21 -> 7.4260559 | L29: =+L22*1.21 -> 7.4260561
A30: Compensación total GO c/IVA | C30: =+C29*'11-BALANCE DE COMPENSACION'!C10 -> 0 | E30: =+E29*'11-BALANCE DE COMPENSACION'!D10 -> 2.8091257e+08 | F30: =+F29*'11-BALANCE DE COMPENSACION'!E10 -> 29101510 | G30: =+G29*'11-BALANCE DE COMPENSACION'!F10 -> 29994379 | H30: =+H29*'11-BALANCE DE COMPENSACION'!G10 -> 7668584.4 | I30: =+I29*'11-BALANCE DE COMPENSACION'!H10 -> 1.7272183e+08 | J30: =+J29*'11-BALANCE DE COMPENSACION'!I10 -> 54634136 | K30: =+K29*'11-BALANCE DE COMPENSACION'!J10 -> 94738087 | L30: =+L29*'11-BALANCE DE COMPENSACION'!K10 -> 38740650
A32: Consumo total GO | C32: =+'8- COSTO COMBUST'!C16*'11-BALANCE DE COMPENSACION'!C10 -> 0 | E32: =+'8- COSTO COMBUST'!E16*'11-BALANCE DE COMPENSACION'!D10 -> 15606254 | F32: =+'8- COSTO COMBUST'!F16*'11-BALANCE DE COMPENSACION'!E10 -> 1616750.5 | G32: =+'8- COSTO COMBUST'!G16*'11-BALANCE DE COMPENSACION'!F10 -> 1666354.4 | H32: =+'8- COSTO COMBUST'!H16*'11-BALANCE DE COMPENSACION'!G10 -> 426032.47 | I32: =+'8- COSTO COMBUST'!I16*'11-BALANCE DE COMPENSACION'!H10 -> 9595657 | J32: =+'8- COSTO COMBUST'!J16*'11-BALANCE DE COMPENSACION'!I10 -> 3035229.8 | K32: =+'8- COSTO COMBUST'!K16*'11-BALANCE DE COMPENSACION'!J10 -> 5263227 | L32: =+'8- COSTO COMBUST'!L16*'11-BALANCE DE COMPENSACION'!K10 -> 2152258.3

Sheet 9- COSTO POR VEHICULO
A1: ANEXO 9 - COSTOS MENSUALES POR VEHÍCULO
A2: Grupo Tarifario | B2: COSTO TOTAL | C2: EROGABLE | D2: NO EROGABLE
A3: Distrito Federal | B3: =+'1-COSTO X KM'!B51*'10-RESUMEN DE COSTOS'!C5/12 -> 17532879 | C3: =+('1-COSTO X KM'!B51-'1-COSTO X KM'!B11-'1-COSTO X KM'!B32-'1-COSTO X KM'!B49)*'2- EMP. REP'!B8/12 -> 14654654 | D3: =+B3-C3 -> 2878225.1
A4: Suburbana Grupo 1 | B4: =+'1-COSTO X KM'!C51*'10-RESUMEN DE COSTOS'!D5/12 -> 17008779 | C4: =+('1-COSTO X KM'!C51-'1-COSTO X KM'!C11-'1-COSTO X KM'!C32-'1-COSTO X KM'!C49)*'2- EMP. REP'!C8/12 -> 14475573 | D4: =+B4-C4 -> 2533205.9
A5: Suburbana KM | B5: =+'1-COSTO X KM'!D51*'10-RESUMEN DE COSTOS'!E5/12 -> 18074229 | C5: =+('1-COSTO X KM'!D51-'1-COSTO X KM'!D11-'1-COSTO X KM'!D32-'1-COSTO X KM'!D49)*'2- EMP. REP'!D8/12 -> 15461599 | D5: =+B5-C5 -> 2612629.8
A6: Suburbana Grupo 2 | B6: =+'1-COSTO X KM'!E51*'10-RESUMEN DE COSTOS'!F5/12 -> 23132491 | C6: =+('1-COSTO X KM'!E51-'1-COSTO X KM'!E11-'1-COSTO X KM'!E32-'1-COSTO X KM'!E49)*'2- EMP. REP'!E8/12 -> 19569959 | D6: =+B6-C6 -> 3562532.3
A7: Urbanas Interprovinciales | B7: =+'1-COSTO X KM'!F51*'10-RESUMEN DE COSTOS'!G5/12 -> 17581698 | C7: =+('1-COSTO X KM'!F51-'1-COSTO X KM'!F11-'1-COSTO X KM'!F32-'1-COSTO X KM'!F49)*'2- EMP. REP'!F8/12 -> 15042079 | D7: =+B7-C7 -> 2539619.3
A8: Provinciales | B8: =+'1-COSTO X KM'!G51*'10-RESUMEN DE COSTOS'!H5/12 -> 16890698 | C8: =+('1-COSTO X KM'!G51-'1-COSTO X KM'!G11-'1-COSTO X KM'!G32-'1-COSTO X KM'!G49)*'2- EMP. REP'!G8/12 -> 14393479 | D8: =+B8-C8 -> 2497219.6
A9: Provinciales KM | B9: =+'1-COSTO X KM'!H51*'10-RESUMEN DE COSTOS'!I5/12 -> 18498857 | C9: =+('1-COSTO X KM'!H51-'1-COSTO X KM'!H11-'1-COSTO X KM'!H32-'1-COSTO X KM'!H49)*'2- EMP. REP'!H8/12 -> 15884345 | D9: =+B9-C9 -> 2614511.9
A10: Municipal 1 | B10: =+'1-COSTO X KM'!I51*'10-RESUMEN DE COSTOS'!J5/12 -> 15793653 | C10: =+('1-COSTO X KM'!I51-'1-COSTO X KM'!I11-'1-COSTO X KM'!I32-'1-COSTO X KM'!I49)*'2- EMP. REP'!I8/12 -> 13571677 | D10: =+B10-C10 -> 2221976.7
A11: Municipal 2 | B11: =+'1-COSTO X KM'!J51*'10-RESUMEN DE COSTOS'!K5/12 -> 16107883 | C11: =+('1-COSTO X KM'!J51-'1-COSTO X KM'!J11-'1-COSTO X KM'!J32-'1-COSTO X KM'!J49)*'2- EMP. REP'!J8/12 -> 13863391 | D11: =+B11-C11 -> 2244492.5
A13: Grupo Tarifario | B13: COSTO TOTAL | C13: EROGABLE | D13: NO EROGABLE
A14: Distrito Federal | B14: 1 | C14: =+C3/B3 -> 0.83583842 | D14: =+B14-C14 -> 0.16416158
A15: Suburbana Grupo 1 | B15: 1 | C15: =+C4/B4 -> 0.8510648 | D15: =+B15-C15 -> 0.1489352
A16: Suburbana G1 KM | B16: 1 | C16: =+C5/B5 -> 0.85545 | D16: =+B16-C16 -> 0.14455
A17: Suburbana Grupo 2 | B17: 1 | C17: =+C6/B6 -> 0.84599444 | D17: =+B17-C17 -> 0.15400556
A18: Urbanas Interprovinciales | B18: 1 | C18: =+C7/B7 -> 0.85555324 | D18: =+B18-C18 -> 0.14444676
A19: Provinciales | B19: 1 | C19: =+C8/B8 -> 0.85215415 | D19: =+B19-C19 -> 0.14784585
A20: Provinciales KM | B20: 1 | C20: =+C9/B9 -> 0.8586663 | D20: =+B20-C20 -> 0.1413337
A21: Municipal 1 | B21: 1 | C21: =+C10/B10 -> 0.85931205 | D21: =+B21-C21 -> 0.14068795
A22: Municipal 2 | B22: 1 | C22: =+C11/B11 -> 0.86065876 | D22: =+B22-C22 -> 0.13934124

Sheet 10-RESUMEN DE COSTOS
A1: ANEXO 10 - RESUMEN DE COSTOS OCTUBRE 2025
A2: 10.a. VARIABLES REPRESENTATIVAS
A3: Variable | B3: unidad | C3: DF | D3: SGI | E3: SGI KM | F3: Grupo Tarifario SGII INP UPA | I3: UPA KM | J3: UMA 1 | K3: UMA 2
A4: IPK (Índice pasajero kilómetro) | B4: pas/km | C4: =+'2- EMP. REP'!B14 -> 3.4444686 | D4: =+'2- EMP. REP'!C14 -> 2.7196435 | E4: =+'2- EMP. REP'!D14 -> 1.7471024 | F4: =+'2- EMP. REP'!E14 -> 0.86686079 | G4: =+'2- EMP. REP'!F14 -> 1.1243147 | H4: =+'2- EMP. REP'!G14 -> 2.7832035 | I4: =+'2- EMP. REP'!H14 -> 1.7259652 | J4: =+'2- EMP. REP'!I14 -> 3.1186188 | K4: =+'2- EMP. REP'!J14 -> 2.4992934
A5: Recorrido medio anual por vehículo | B5: km/veh | C5: =+'2- EMP. REP'!B8 -> 54284.605 | D5: =+'2- EMP. REP'!C8 -> 58961.49 | E5: =+'2- EMP. REP'!D8 -> 77787.923 | F5: =+'2- EMP. REP'!E8 -> 118012.76 | G5: =+'2- EMP. REP'!F8 -> 88755.385 | H5: =+'2- EMP. REP'!G8 -> 65855.692 | I5: =+'2- EMP. REP'!H8 -> 89687.923 | J5: =+'2- EMP. REP'!I8 -> 60967.857 | K5: =+'2- EMP. REP'!J8 -> 65620.769
A6: Relación conductor por vehículo | B6: cond/veh | C6: =+'4- PERSONAL'!B4 -> 2.2226653 | D6: =+'4- PERSONAL'!C4 -> 2.2945852 | E6: =+'4- PERSONAL'!D4 -> 2.2945852 | F6: =+'4- PERSONAL'!E4 -> 2.3600424 | G6: =+'4- PERSONAL'!F4 -> 2.2945852 | H6: =+'4- PERSONAL'!G4 -> 2.2945852 | I6: =+'4- PERSONAL'!H4 -> 2.2945852 | J6: =+'4- PERSONAL'!I4 -> 2.2226653 | K6: =+'4- PERSONAL'!J4 -> 2.2226653
A7: Velocidad comercial | B7: km/h | C7: =+'2- EMP. REP'!B12 -> 13.43 | D7: =+'2- EMP. REP'!C12 -> 16.238046 | E7: =+'2- EMP. REP'!D12 -> 20.033442 | F7: =+'2- EMP. REP'!E12 -> 31.560404 | G7: =+'2- EMP. REP'!F12 -> 25.630109 | H7: =+'2- EMP. REP'!G12 -> 16.157449 | I7: =+'2- EMP. REP'!H12 -> 21.719 | J7: =+'2- EMP. REP'!I12 -> 15.075926 | K7: =+'2- EMP. REP'!J12 -> 17.523861
A8: 10.b. PRECIOS RELEVANTES
A9: Precio | B9: unidad | C9: DF | D9: SGI | E9: SGI KM | F9: Grupo Tarifario SGII INP UPA | I9: UPA KM | J9: UMA 1 | K9: UMA 2
A10: Vehículo 0 km (sin IVA) | B10: $/veh | C10: =+'5-PRECIOS SIN IVA'!B17+'5-PRECIOS SIN IVA'!B18 -> 1.7996793e+08 | D10: =+'5-PRECIOS SIN IVA'!C17+'5-PRECIOS SIN IVA'!C18 -> 1.7996793e+08 | E10: =+'5-PRECIOS SIN IVA'!D17+'5-PRECIOS SIN IVA'!D18 -> 1.7996793e+08 | F10: =+'5-PRECIOS SIN IVA'!E17+'5-PRECIOS SIN IVA'!E18 -> 2.5021455e+08 | G10: =+'5-PRECIOS SIN IVA'!F17+'5-PRECIOS SIN IVA'!F18 -> 1.7996793e+08 | H10: =+'5-PRECIOS SIN IVA'!G17+'5-PRECIOS SIN IVA'!G18 -> 1.7996793e+08 | I10: =+'5-PRECIOS SIN IVA'!H17+'5-PRECIOS SIN IVA'!H18 -> 1.7996793e+08 | J10: =+'5-PRECIOS SIN IVA'!I17+'5-PRECIOS SIN IVA'!I18 -> 155761903 | K10: =+'5-PRECIOS SIN IVA'!J17+'5-PRECIOS SIN IVA'!J18 -> 155761903
A11: Adicionales (rampa y boletera- sin IVA) | B11: $/un | C11: 0 | D11: 0 | E11: 0 | F11: 0 | G11: 0 | H11: 0 | I11: 0 | J11: 0 | K11: 0
A12: Combustible (Gas oil) (precio relevado) | B12: $/lt | C12: =+'8- COSTO COMBUST'!D4 -> 1548.852 | D12: =+C12 -> 1548.852 | E12: =+D12 -> 1548.852 | F12: =+E12 -> 1548.852 | G12: =+F12 -> 1548.852 | H12: =+G12 -> 1548.852 | I12: =+H12 -> 1548.852 | J12: =+I12 -> 1548.852 | K12: =+J12 -> 1548.852
A13: Combustible (Gas oil) (sin IVA) | B13: $/lt | C13: =+'8- COSTO COMBUST'!D18 -> 1216.6782 | D13: =+C13 -> 1216.6782 | E13: =+D13 -> 1216.6782 | F13: =+E13 -> 1216.6782 | G13: =+F13 -> 1216.6782 | H13: =+G13 -> 1216.6782 | I13: =+H13 -> 1216.6782 | J13: =+I13 -> 1216.6782 | K13: =+J13 -> 1216.6782
A14: Salario del conductor | B14: $/cond | C14: =SUM(C15:C17) -> 1370000 | D14: =SUM(D15:D17) -> 1370000 | E14: =SUM(E15:E17) -> 1370000 | F14: =SUM(F15:F17) -> 1370000 | G14: =SUM(G15:G17) -> 1370000 | H14: =SUM(H15:H17) -> 1370000 | I14: =SUM(I15:I17) -> 1370000 | J14: =SUM(J15:J17) -> 1370000 | K14: =SUM(K15:K17) -> 1370000
A15: Sueldo Básico | B15: $/cond | C15: =+'4- PERSONAL'!B51 -> 972700 | D15: =+C15 -> 972700 | E15: =+D15 -> 972700 | F15: =+E15 -> 972700 | G15: =+F15 -> 972700 | H15: =+G15 -> 972700 | I15: =+H15 -> 972700 | J15: =+I15 -> 972700 | K15: =+J15 -> 972700
A16: Premio Asistencia | B16: $/cond | C16: =+'4- PERSONAL'!B52 -> 274000 | D16: =+C16 -> 274000 | E16: =+D16 -> 274000 | F16: =+E16 -> 274000 | G16: =+F16 -> 274000 | H16: =+G16 -> 274000 | I16: =+H16 -> 274000 | J16: =+I16 -> 274000 | K16: =+J16 -> 274000
A17: Atención de boletera | B17: $/cond | C17: =+'4- PERSONAL'!B53 -> 123300 | D17: =+C17 -> 123300 | E17: =+D17 -> 123300 | F17: =+E17 -> 123300 | G17: =+F17 -> 123300 | H17: =+G17 -> 123300 | I17: =+H17 -> 123300 | J17: =+I17 -> 123300 | K17: =+J17 -> 123300
A18: Viático diario | B18: $/día | C18: =+'4- PERSONAL'!B60 -> 13000 | D18: =+C18 -> 13000 | E18: =+D18 -> 13000 | F18: =+E18 -> 13000 | G18: =+F18 -> 13000 | H18: =+G18 -> 13000 | I18: =+H18 -> 13000 | J18: =+I18 -> 13000 | K18: =+J18 -> 13000
A19: Adicional no remunerativo | B19: $/cond | C19: =+'4- PERSONAL'!B63 -> 0 | D19: =+C19 -> 0 | E19: =+D19 -> 0 | F19: =+E19 -> 0 | G19: =+F19 -> 0 | H19: =+G19 -> 0 | I19: =+H19 -> 0 | J19: =+I19 -> 0 | K19: =+J19 -> 0
A22: 10.c. RESULTADOS | C22: Grupo Tarifario SGII INP UPA
C23: DF | D23: SGI | E23: SG KM | F23: SGII | G23: INP | H23: UPA | I23: UPA KM | J23: UMA 1 | K23: UMA 2
A24: Costo por km (Cm) (sin iva) | B24: $/veh | C24: =+'1-COSTO X KM'!B51 -> 3875.7682 | D24: =+'1-COSTO X KM'!C51 -> 3461.6721 | E24: =+'1-COSTO X KM'!D51 -> 2788.2316 | F24: =+'1-COSTO X KM'!E51 -> 2352.2023 | G24: =+'1-COSTO X KM'!F51 -> 2377.0995 | H24: =+'1-COSTO X KM'!G51 -> 3077.7655 | I24: =+'1-COSTO X KM'!H51 -> 2475.0967 | J24: =+'1-COSTO X KM'!I51 -> 3108.5862 | K24: =+'1-COSTO X KM'!J51 -> 2945.6314
A25: Tarifa media sin Compensación (Tm = Cm/IPK) | B25: $/pas | C25: =+'1-COSTO X KM'!B53 -> 1125.2152 | D25: =+'1-COSTO X KM'!C53 -> 1272.8404 | E25: =+'1-COSTO X KM'!D53 -> 1595.9177 | F25: =+'1-COSTO X KM'!E53 -> 2713.4718 | G25: =+'1-COSTO X KM'!F53 -> 2114.2652 | H25: =+'1-COSTO X KM'!G53 -> 1105.8356 | I25: =+'1-COSTO X KM'!H53 -> 1434.0363 | J25: =+'1-COSTO X KM'!I53 -> 996.78299 | K25: =+'1-COSTO X KM'!J53 -> 1178.5857
C26: =+C25/C24 -> 0.29032055 | D26: =+D25/D24 -> 0.36769525 | E26: =+E25/E24 -> 0.57237631 | F26: =+F25/F24 -> 1.1535878 | G26: =+G25/G24 -> 0.88943068 | H26: =+H25/H24 -> 0.3592982 | I26: =+I25/I24 -> 0.57938597 | J26: =+J25/J24 -> 0.32065477 | K26: =+K25/K24 -> 0.40011309

Sheet 11-BALANCE DE COMPENSACION
A1: ANEXO 11 - BALANCE DE COMPENSACIÓN
A3: Variable | B3: Unidad | C3: DF | D3: SGI | E3: SGI KM | F3: SGII | G3: INP | H3: UPA | I3: UPA KM | J3: UMA 1 | K3: UMA 2 | L3: Total
A4: Costo por km | B4: $/km | C4: =+'1-COSTO X KM'!B51 -> 3875.7682 | D4: =+'1-COSTO X KM'!C51 -> 3461.6721 | E4: =+'1-COSTO X KM'!D51 -> 2788.2316 | F4: =+'1-COSTO X KM'!E51 -> 2352.2023 | G4: =+'1-COSTO X KM'!F51 -> 2377.0995 | H4: =+'1-COSTO X KM'!G51 -> 3077.7655 | I4: =+'1-COSTO X KM'!H51 -> 2475.0967 | J4: =+'1-COSTO X KM'!I51 -> 3108.5862 | K4: =+'1-COSTO X KM'!J51 -> 2945.6314 | L4: =+(C4*C10+D4*D10+E4*E10+F4*F10+G4*G10+H4*H10+I4*I10+J4*J10+K4*K10)/L10 -> 3415.0071
A5: IPK | B5: pas / km | C5: =+'1-COSTO X KM'!B52 -> 3.4444686 | D5: =+'1-COSTO X KM'!C52 -> 2.7196435 | E5: =+'1-COSTO X KM'!D52 -> 1.7471024 | F5: =+'1-COSTO X KM'!E52 -> 0.86686079 | G5: =+'1-COSTO X KM'!F52 -> 1.1243147 | H5: =+'1-COSTO X KM'!G52 -> 2.7832035 | I5: =+'1-COSTO X KM'!H52 -> 1.7259652 | J5: =+'1-COSTO X KM'!I52 -> 3.1186188 | K5: =+'1-COSTO X KM'!J52 -> 2.4992934 | L5: =+L7/L10 -> 2.8256418
A6: Tarifa media sin Compensación (Tm = Cm/IPK) | B6: $/pas | C6: =+'1-COSTO X KM'!B53 -> 1125.2152 | D6: =+'1-COSTO X KM'!C53 -> 1272.8404 | E6: =+'1-COSTO X KM'!D53 -> 1595.9177 | F6: =+'1-COSTO X KM'!E53 -> 2713.4718 | G6: =+'1-COSTO X KM'!F53 -> 2114.2652 | H6: =+'1-COSTO X KM'!G53 -> 1105.8356 | I6: =+'1-COSTO X KM'!H53 -> 1434.0363 | J6: =+'1-COSTO X KM'!I53 -> 996.78299 | K6: =+'1-COSTO X KM'!J53 -> 1178.5857 | L6: =+L4/L5 -> 1208.5775
A7: Pasajeros mensuales (prom) | B7: pas | C7: =+'7-CALCULO TARIFARIO'!B12 -> 24198538 | D7: =+'7-CALCULO TARIFARIO'!C12 -> 82448802 | E7: =+'7-CALCULO TARIFARIO'!D12 -> 5837111.7 | F7: =+'7-CALCULO TARIFARIO'!E12 -> 3802173.7 | G7: =+'7-CALCULO TARIFARIO'!F12 -> 1430308.7 | H7: =+'7-CALCULO TARIFARIO'!G12 -> 62944753 | I7: =+'7-CALCULO TARIFARIO'!H12 -> 12087162 | J7: =+'7-CALCULO TARIFARIO'!I12 -> 39785855 | K7: =+'7-CALCULO TARIFARIO'!J12 -> 13038448 | L7: =SUM(C7:K7) -> 2.4557315e+08
A8: Monto a cubrir | B8: $ | C8: =+C4*C10 -> 2.7228561e+10 | D8: =+D4*D10 -> 1.0494416e+11 | E8: =+E4*E10 -> 9.3155497e+09 | F8: =+F4*F10 -> 1.0317091e+10 | G8: =+G4*G10 -> 3.0240518e+09 | H8: =+H4*H10 -> 6.9606549e+10 | I8: =+I4*I10 -> 1.7333429e+10 | J8: =+J4*J10 -> 3.9657863e+10 | K8: =+K4*K10 -> 1.5366929e+10 | L8: =SUM(D8:K8) -> 2.6956563e+11
A9: Compensación al gas oil | B9: $ | D9: =+'8- COSTO COMBUST'!E$29*'11-BALANCE DE COMPENSACION'!D10 -> 2.8091257e+08 | E9: =+'8- COSTO COMBUST'!F$29*'11-BALANCE DE COMPENSACION'!E10 -> 29101510 | F9: =+'8- COSTO COMBUST'!G$29*'11-BALANCE DE COMPENSACION'!F10 -> 29994379 | G9: =+'8- COSTO COMBUST'!H$29*'11-BALANCE DE COMPENSACION'!G10 -> 7668584.4 | H9: =+'8- COSTO COMBUST'!I$29*'11-BALANCE DE COMPENSACION'!H10 -> 1.7272183e+08 | I9: =+'8- COSTO COMBUST'!J$29*'11-BALANCE DE COMPENSACION'!I10 -> 54634136 | J9: =+'8- COSTO COMBUST'!K$29*'11-BALANCE DE COMPENSACION'!J10 -> 94738087 | K9: =+'8- COSTO COMBUST'!L$29*'11-BALANCE DE COMPENSACION'!K10 -> 38740650 | L9: =SUM(C9:K9) -> 7.0851174e+08
A10: Kilómeros Mensuales | B10: km | C10: =+'7-CALCULO TARIFARIO'!B18 -> 7025332.7 | D10: =+'7-CALCULO TARIFARIO'!C18 -> 30316033 | E10: =+'7-CALCULO TARIFARIO'!D18 -> 3341024.4 | F10: =+'7-CALCULO TARIFARIO'!E18 -> 4386141 | G10: =+'7-CALCULO TARIFARIO'!F18 -> 1272160.4 | H10: =+'7-CALCULO TARIFARIO'!G18 -> 22615937 | I10: =+'7-CALCULO TARIFARIO'!H18 -> 7003132.1 | J10: =+'7-CALCULO TARIFARIO'!I18 -> 12757524 | K10: =+'7-CALCULO TARIFARIO'!J18 -> 5216853.9 | L10: =SUM(D10:K10) -> 86908805
A11: Ingreso medio por pasajero (Im) | B11: $/pas | C11: =+C12/C7 -> 411.9309 | D11: =+D12/D7 -> 360.64688 | E11: =+E12/E7 -> 442.6271 | F11: =+F12/F7 -> 1073.3453 | G11: =+G12/G7 -> 1647.1034 | H11: =+H12/H7 -> 372.1625 | I11: =+I12/I7 -> 492.60397 | J11: =+J12/J7 -> 347.09541 | ... L11: =+L12/L7 -> 393.83604
A12: Recaudación sin IVA | B12: $/pas | C12: =+'7-CALCULO TARIFARIO'!B24/1.105 -> 9.9681253e+09 | D12: =+'7-CALCULO TARIFARIO'!C24/1.105 -> 2.9734903e+10 | E12: =+'7-CALCULO TARIFARIO'!D24/1.105 -> 2.5836638e+09 | F12: =+'7-CALCULO TARIFARIO'!E24/1.105 -> 4.0810453e+09 | G12: =+'7-CALCULO TARIFARIO'!F24/1.105 -> 2.3558663e+09 | H12: =+'7-CALCULO TARIFARIO'!G24/1.105 -> 2.3425677e+10 | I12: =+'7-CALCULO TARIFARIO'!H24/1.105 -> 5.954184e+09 | J12: =+'7-CALCULO TARIFARIO'!I24/1.105 -> 1.3809487e+10 | K12: =+'7-CALCULO TARIFARIO'!J24/1.105 -> 4.802606e+09 | L12: =SUM(C12:K12) -> 9.6715558e+10
A13: Compensación Requerida | B13: $ | C13: =+(C4*C10)-C9-C12 -> 1.7260436e+10 | D13: =+(D4*D10)-D9-D12 -> 7.4928348e+10 | E13: =+(E4*E10)-E9-E12 -> 6.7027844e+09 | F13: =+(F4*F10)-F9-F12 -> 6.2060512e+09 | G13: =+(G4*G10)-G9-G12 -> 6.6051696e+08 | H13: =+(H4*H10)-H9-H12 -> 4.6008151e+10 | I13: =+(I4*I10)-I9-I12 -> 1.1324611e+10 | J13: =+(J4*J10)-J9-J12 -> 2.5753638e+10 | K13: =+(K4*K10)-K9-K12 -> 1.0525582e+10 | L13: =SUM(D13:K13) -> 1.8210968e+11
A14: Compensación Requerida Área Gran La Plata | B14: $ | C14: 0 | D14: 0 | E14: 0 | F14: 0 | G14: 0 | H14: 215991595 | I14: 6409112 | J14: 0 | K14: 207673738 | L14: =SUM(C14:K14) -> 430074445
A15: Diferenciales y Redeterminaciones - Cuota 4/4 | B15: $ | D15: 1862871874 | E15: 74118961 | F15: -63760106 | G15: -329421745 | H15: -917768749 | I15: -405707576 | J15: -554978434 | K15: 21418113 | L15: =SUM(C15:K15) -> -313227662
A16: Previsión Paritarias Jul-Oct 2025 - Cuota 4/4 | D16: 1177281678 | E16: 99454817 | F16: 98752075 | G16: 33864017 | H16: 808354096 | I16: 183586341 | J16: 475915250 | K16: 186033635 | L16: =SUM(D16:K16) -> 3063241909
A17: TOTAL COMPENSACIONES | B17: $ | C17: =+C13+C14+C15+C16 -> 1.7260436e+10 | D17: =+D13+D14+D15+D16 -> 7.7968502e+10 | E17: =+E13+E14+E15+E16 -> 6.8763582e+09 | F17: =+F13+F14+F15+F16 -> 6.2410432e+09 | G17: =+G13+G14+G15+G16 -> 3.6495923e+08 | H17: =+H13+H14+H15+H16 -> 4.6114728e+10 | I17: =+I13+I14+I15+I16 -> 1.1108899e+10 | J17: =+J13+J14+J15+J16 -> 2.5674575e+10 | ... L17: =+L13+L14+L15+L16 -> 1.8528977e+11
